Workbook
Name cat: #REF!
Name d: #REF!
Name g: #REF!
Name ORIGINE: #REF!
Name porteur: #REF!
Name prio: #REF!
Name Réinitialiser_Zone_Impression: OFFSET(#REF!,0,0,COUNTA(#REF!)+5)
Name s: #REF!
Name stat: #REF!
Name SurlignageTâchesÀFaire: #REF!
Name SurlignerActivités: #REF!
Name valHDébut: #REF!
Name valHFin: #REF!

Sheet Plan d'action
A1: N° | B1: PA | C1: Porteur | D1: Date d'affection | E1: Deadline | F1: Date de realisation | G1: Durée
A2: 1 | G2: =F2-D2 -> 0
A3: 2
A4: 3
A5: 4
A6: 5
A7: 6
A8: 7
A9: 8
A10: 9
A11: 10

Sheet Suivi Perfomances
B2: Team | C2: Performances | D2: Jan | E2: Fev | F2: Mar | G2: Avr | H2: Mai | I2: Juin | J2: Juillet | K2: Août | L2: Sept | M2: Oct | N2: Nov | O2: Déc | P2: Total | Q2: Moy Global
B3: Alpho D | C3: % PA Soldés | P3: 0.4 | Q3: =AVERAGE(P3:P7) -> 0.68
C4: Nombre Incidents | P4: 0.7
C5: % Reception et archivage RI | P5: 1
C6: % Cloture des TQ | P6: 1
C7: Taux d'atteintes des Objectifs | P7: 0.3
B8: Keita | C8: % PA Soldés | P8: 0.5 | Q8: =AVERAGE(P8:P12) -> 0.7
C9: Nombre Incidents | P9: 0.7
C10: % Reception et archivage RI | P10: 1
C11: % Cloture des TQ | P11: 1
C12: Taux d'atteintes des Objectifs | P12: 0.3
B13: Alpha B | C13: % PA Soldés | P13: 0.4 | Q13: =AVERAGE(P13:P17) -> 0.68
C14: Nombre Incidents | P14: 0.8
C15: % Reception et archivage RI | P15: 0.9
C16: % Cloture des TQ | P16: 1
C17: Taux d'atteintes des Objectifs | P17: 0.3
B18: Bobo | C18: % PA Soldés | P18: 0.3 | Q18: =AVERAGE(P18:P22) -> 0.66
C19: Nombre Incidents | P19: 0.7
C20: % Reception et archivage RI | P20: 1
C21: % Cloture des TQ | P21: 1
C22: Taux d'atteintes des Objectifs | P22: 0.3

Sheet Objectifs_2022
B1: Objectifs 2022
A2: N° | B2: Nom | C2: Commentaire | D2: Periode
A3: 1 | B3: Vulgarisation de l'utilisation des outils calipso (Swan et Oceane), Helios et brise | D3: S2
A4: 2 | B4: Mise à jour de la base Marine des Produits (automatisation si possible) | D4: S2
A5: 3 | B5: Mise à jour de la base Marine des ressources (automatisation si possible) | D5: S2
A6: 4 | B6: Création de la dépendance ressource - produit et produit-produit | D6: S2
A7: 5 | B7: Mise à jour des reporting des incidents, problemes, plaintes et changement sur brise | D7: S2
A8: 6 | B8: Mise à Jour du Catalogue OGN Swan dans Marine (association des impacts (dépendance) par operation depuis la création du TQ) | D8: S2
A9: 7 | B9: Mise en place d'un tableau de Bord Supervision des incident et ATP sur Helios | D9: S2
A10: 8 | B10: Automatisation des notifications (mail et SMS) de la gestion des Incidents (la signalisation des incidents vers les TMC et le CCC) | D10: S2
A11: 9 | B11: Développement de l'outil central de Knowledge Management des différentes supervisions (Services, Huawei, GNOC et IPT) | D11: S2
A12: 10 | B12: POC Supervision du reseau (RAN, Network IP, Data Mobile et VAS) avec ELK (Elasticsearch & Kibana), | D12: S2
A13: 11 | B13: Mise en place de la supervision du réseaux IP sur OPMANAGER | D13: S2
A14: 12 | B14: Mise en place de la supervision du réseaux IP sur Prometheus & Grafana | D14: S2
... A16: 14 | B16: Mise à jour des fiches Consigne existantes et Elaboration des fiches de certains services | D16: S2

Sheet JANVIER_2026
A1: N° | B1: N°ticket | C1: Priorité | D1: Origine | E1: Nom de service | F1: Début | G1: Fin retablissement | H1: Fin réparation | I1: Durée rétablissement (hh:mn) | J1: Durée rétablissement (mn) | K1: Durée réparation (hh:mn) | L1: Durée réparation (mn) | M1: Description | N1: Cause de l'incident | O1: Actions correctives | P1: TMC | Q1: Statut | R1: Observation | S1: SLA | T1: Exlusion | U1: RI
A2: 1 | B2: 2601Q38109 | C2: P1 | D2: Supervision | E2: Orange Money add-on Local / EDG Prepaid | F2: 46023.733 | G2: 46024.24 | H2: 46024.24 | I2: =G2-F2 -> 0.50763889 | J2: =I2*1440 -> 731 | K2: =H2-F2 -> 0.50763889 | L2: =K2*1440 -> 731 | M2: Impossible d'effectuer des paiements de facture EDG via Orange Money | N2: Inconnue | O2: Inconnue | P2: DSI | Q2: Clos | S2: =IF(AND(C2="P1",J2<=240),"ISLA",IF((AND(C2="P2",J2<=480)),"ISLA",IF((AND(C2="P3",J2<=2880)),"ISLA","OSLA"))) -> OSLA | T2: =IF((AND(MID(P2,1,2)="IT",S2="OSLA")),"OUI","NON") -> NON | U2: NON
A3: 2 | B3: 2601Q39915 | C3: P1 | D3: Supervision | E3: Orange Money add-on / Bank to Wallet / FBNBank | F3: 46023.735 | G3: 46023.982 | H3: 46023.982 | I3: =G3-F3 -> 0.24722222 | J3: =I3*1440 -> 356 | K3: =H3-F3 -> 0.24722222 | L3: =K3*1440 -> 356 | M3: Impossible d’effectuer des transactions bancaires FBNBank via Orange Money | N3: Inconnue | O3: Inconnue | P3: IT FBNBANK | Q3: Clos | S3: =IF(AND(C3="P1",J3<=240),"ISLA",IF((AND(C3="P2",J3<=480)),"ISLA",IF((AND(C3="P3",J3<=2880)),"ISLA","OSLA"))) -> OSLA | T3: =IF((AND(MID(P3,1,2)="IT",S3="OSLA")),"OUI","NON") -> OUI | U3: Pas de RI
A4: 3 | B4: 2601Q41376 | C4: P1 | D4: Supervision | E4: Orange Money add-on Locaux / Douane REDEVANCE / Contravention_GN | F4: 46023.838 | G4: 46023.876 | H4: 46023.876 | I4: =G4-F4 -> 0.038888889 | J4: =I4*1440 -> 56 | K4: =H4-F4 -> 0.038888889 | L4: =K4*1440 -> 56 | M4: Indisponibilité du service Douane REDEVANCE et Contravention GN | N4: Inconnue | O4: Inconnue | P4: IT NGSER | Q4: Clos | S4: =IF(AND(C4="P1",J4<=240),"ISLA",IF((AND(C4="P2",J4<=480)),"ISLA",IF((AND(C4="P3",J4<=2880)),"ISLA","OSLA"))) -> ISLA | T4: =IF((AND(MID(P4,1,2)="IT",S4="OSLA")),"OUI","NON") -> NON | U4: Pas de RI
A5: 4 | B5: 2601Q52339 | C5: P1 | D5: Supervision | E5: Orange Money add-on Local / CRG | F5: 46024.392 | G5: 46024.417 | H5: 46024.417 | I5: =G5-F5 -> 0.024305556 | J5: =I5*1440 -> 35 | K5: =H5-F5 -> 0.024305556 | L5: =K5*1440 -> 35 | M5: Impossible pour le client de faire des épargnes via Orange money | N5: Inconnue | O5: Inconnue | P5: IT CRG | Q5: Clos | S5: =IF(AND(C5="P1",J5<=240),"ISLA",IF((AND(C5="P2",J5<=480)),"ISLA",IF((AND(C5="P3",J5<=2880)),"ISLA","OSLA"))) -> ISLA | T5: =IF((AND(MID(P5,1,2)="IT",S5="OSLA")),"OUI","NON") -> NON | U5: Pas de RI
A6: 5 | B6: 2601Q55215 & 2601Q57185 | C6: P1 | D6: Supervision | E6: Orange Money add-on Locaux | Nimba Plus | F6: 46024.438 | G6: 46025.417 | H6: 46025.417 | I6: =G6-F6 -> 0.97916667 | J6: =I6*1440 -> 1410 | K6: =H6-F6 -> 0.97916667 | L6: =K6*1440 -> 1410 | M6: Instabilité sur plusieurs services Orange Money Addons-Locaux et Nimba Plus | N6: Problème de certificat observés sur plusieurs micro-services | O6: Une solution de contournement pour faire passer toutes les rêquetes https en http sur les intances de kira | P6: DSI | Q6: Clos | S6: =IF(AND(C6="P1",J6<=240),"ISLA",IF((AND(C6="P2",J6<=480)),"ISLA",IF((AND(C6="P3",J6<=2880)),"ISLA","OSLA"))) -> OSLA | T6: =IF((AND(MID(P6,1,2)="IT",S6="OSLA")),"OUI","NON") -> NON | U6: NON
A7: 6 | B7: 2601Q78476 | C7: P1 | D7: Supervision | E7: Orange Money add-on Local / Identification Compte | F7: 46025.41 | G7: 46025.618 | H7: 46025.618 | I7: =G7-F7 -> 0.20833333 | J7: =I7*1440 -> 300 | K7: =H7-F7 -> 0.20833333 | L7: =K7*1440 -> 300 | M7: Impossible pour les clients d'identifier leur compte Orange Money via le *144# | N7: Inconnue | O7: Inconnue | P7: DSI | Q7: Clos | S7: =IF(AND(C7="P1",J7<=240),"ISLA",IF((AND(C7="P2",J7<=480)),"ISLA",IF((AND(C7="P3",J7<=2880)),"ISLA","OSLA"))) -> OSLA | T7: =IF((AND(MID(P7,1,2)="IT",S7="OSLA")),"OUI","NON") -> NON | U7: NON
A8: 7 | B8: 2601Q81413 | C8: P1 | D8: Supervision | E8: Orange Money add-on Locaux | Nimba Plus | F8: 46025.476 | G8: 46025.514 | H8: 46025.514 | I8: =G8-F8 -> 0.038194444 | J8: =I8*1440 -> 55 | K8: =H8-F8 -> 0.038194444 | L8: =K8*1440 -> 55 | M8: Instabilité sur plusieurs services Orange Money Addons-Locaux et Nimba Plus | N8: Problème de certificat sur les instances de kira | O8: Inconnue | P8: DSI | Q8: Clos | S8: =IF(AND(C8="P1",J8<=240),"ISLA",IF((AND(C8="P2",J8<=480)),"ISLA",IF((AND(C8="P3",J8<=2880)),"ISLA","OSLA"))) -> ISLA | T8: =IF((AND(MID(P8,1,2)="IT",S8="OSLA")),"OUI","NON") -> NON | U8: NON
A9: 8 | B9: 2601Q81730 | C9: P1 | D9: Supervision | E9: Orange Money add-on Locaux / Guinée GAMES TICKET / Lafarge Client / Lanala Assurance / Ouverture de compte OM / PayCard / School Fees USSD / YellowBet Orange Money Core / Achat Forfait Choco pour soi OM / Achat Forfait Choco pour tiers OM / Achat de credit pour tiers OM & Consul 10 dern trans OM | F9: 46025.528 | G9: 46025.615 | H9: 46025.615 | I9: =G9-F9 -> 0.086805556 | J9: =I9*1440 -> 125 | K9: =H9-F9 -> 0.086805556 | L9: =K9*1440 -> 125 | M9: Indisponibilité de plusieurs services Orange Money add-on-Locaux et Orange Money Core | N9: Inconnue | O9: Inconnue | P9: DSI | Q9: Clos | S9: =IF(AND(C9="P1",J9<=240),"ISLA",IF((AND(C9="P2",J9<=480)),"ISLA",IF((AND(C9="P3",J9<=2880)),"ISLA","OSLA"))) -> ISLA | T9: =IF((AND(MID(P9,1,2)="IT",S9="OSLA")),"OUI","NON") -> NON | U9: NON
A10: 9 | B10: 2601Q87978 & 2601R21759 | C10: P1 | D10: Supervision | E10: Orange Money add-on Locaux / Minigrid_Souscription / Minigrid_Paiement / UGAR-ACTIVA / School Fees USSD / MSC_GUI / Mouna / UBIPHARM Client / UBIPHARM Marchand / Paycard | Nimba Plus_API_SETTINGS / Nimba Plus_API_TELCO / Nimba Plus_API_Transaction OM & Big Data Check MSISDN Frequent hbase | F10: 46025.802 | G10: 46029.005 | H10: 46029.005 | I10: =G10-F10 -> 3.2027778 | J10: =I10*1440 -> 4612 | K10: =H10-F10 -> 3.2027778 | L10: =K10*1440 -> 4612 | M10: Instabilité de plusieurs services Orange Money Add-ons Locaux, Nimba Plus & Outils SI | N10: Souci sur Kira | O10: Inconnue | P10: DSI | Q10: Clos | S10: =IF(AND(C10="P1",J10<=240),"ISLA",IF((AND(C10="P2",J10<=480)),"ISLA",IF((AND(C10="P3",J10<=2880)),"ISLA","OSLA"))) -> OSLA | T10: =IF((AND(MID(P10,1,2)="IT",S10="OSLA")),"OUI","NON") -> NON | U10: NON
A11: 10 | B11: 2511Z13777 | C11: P1 | D11: Supervision | E11: Orange Money add-on Locaux / UBIPHARM Client & Marchand | F11: 46026.052 | G11: 46026.257 | H11: 46026.257 | I11: =G11-F11 -> 0.20486111 | J11: =I11*1440 -> 295 | K11: =H11-F11 -> 0.20486111 | L11: =K11*1440 -> 295 | M11: Impossible pour les clients et marchands de UBIPHARM de payer leur facture via Orange Money | N11: Inconnue | O11: Inconnue | P11: DSI | Q11: Clos | S11: =IF(AND(C11="P1",J11<=240),"ISLA",IF((AND(C11="P2",J11<=480)),"ISLA",IF((AND(C11="P3",J11<=2880)),"ISLA","OSLA"))) -> OSLA | T11: =IF((AND(MID(P11,1,2)="IT",S11="OSLA")),"OUI","NON") -> NON | U11: NON
A12: 11 | B12: 2601Q97232 | C12: P1 | D12: Supervision | E12: Orange Money add-on / Bank to Wallet / FBNBank | F12: 46026.389 | G12: 46026.764 | H12: 46026.764 | I12: =G12-F12 -> 0.375 | J12: =I12*1440 -> 540 | K12: =H12-F12 -> 0.375 | L12: =K12*1440 -> 540 | M12: Impossible d’effectuer des transactions bancaires FBNBank via Orange Money | N12: Inconnue | O12: Inconnue | P12: IT FBNBANK | Q12: Clos | S12: =IF(AND(C12="P1",J12<=240),"ISLA",IF((AND(C12="P2",J12<=480)),"ISLA",IF((AND(C12="P3",J12<=2880)),"ISLA","OSLA"))) -> OSLA | T12: =IF((AND(MID(P12,1,2)="IT",S12="OSLA")),"OUI","NON") -> OUI | U12: Pas de RI
A13: 12 | B13: 2601R16562 | C13: P1 | D13: Supervision | E13: Orange Money add-on Local / Contravention_GN | F13: 46027.367 | G13: 46027.406 | H13: 46027.406 | I13: =G13-F13 -> 0.038888889 | J13: =I13*1440 -> 56 | K13: =H13-F13 -> 0.038888889 | L13: =K13*1440 -> 56 | M13: Indisponibilité du service Contravention GN | N13: Inconnue | O13: Inconnue | P13: IT NGSER | Q13: Clos | S13: =IF(AND(C13="P1",J13<=240),"ISLA",IF((AND(C13="P2",J13<=480)),"ISLA",IF((AND(C13="P3",J13<=2880)),"ISLA","OSLA"))) -> ISLA | T13: =IF((AND(MID(P13,1,2)="IT",S13="OSLA")),"OUI","NON") -> NON | U13: Pas de RI
... A132: 131 | B132: 2601A12810 | C132: P1 | D132: Supervision | E132: Orange Money add-on / Bank to Wallet / NSIA | F132: 46053.64 | G132: 46053.692 | H132: 46053.692 | I132: =G132-F132 -> 0.051388889 | J132: =I132*1440 -> 74 | K132: =H132-F132 -> 0.051388889 | L132: =K132*1440 -> 74 | M132: Impossible d’effectuer des transactions bancaires NSIA via Orange Money | N132: Inconnue | O132: Inconnue | P132: IT NSIA | Q132: Clos | S132: =IF(AND(C132="P1",J132<=240),"ISLA",IF((AND(C132="P2",J132<=480)),"ISLA",IF((AND(C132="P3",J132<=2880)),"ISLA","OSLA"))) -> ISLA | T132: =IF((AND(MID(P132,1,2)="IT",S132="OSLA")),"OUI","NON") -> NON | U132: Pas de RI

Sheet Synthese_2018
A1: Overview | P1: Priorité | AD1: TMC
B3: Jan | C3: Jan | D3: Fev | E3: Mars | F3: Avril | G3: Mai | H3: Juin | I3: Juillet | J3: Août | K3: Sept | L3: Oct | M3: Nov | N3: Dec | Q3: Jan | R3: Fev | S3: Mars | T3: Avril | U3: Mai | V3: Juin | W3: Juillet | X3: Août | Y3: Sept | Z3: Oct | AA3: Nov | AB3: Dec | AE3: Jan | AF3: Fev | AG3: Mars | AH3: Avril | AI3: Mai | AJ3: Juin | AK3: Juillet | AL3: Août | AM3: Sept | AN3: Oct | AO3: Nov | AP3: Dec
A4: Nombre d'incidents | C4: =COUNTA(Janvier_2018!C2:C37) -> 31 | D4: =COUNTA(Février_2018!C2:C29) -> 28 | E4: =COUNTA(Mars_2018!C2:C41) -> 40 | F4: =COUNTA(Avril_2018!C2:C44) -> 43 | G4: =COUNTA(Mai_2018!C2:C30) -> 29 | H4: =COUNTA(Juin_2018!C2:C45) -> 44 | I4: =COUNTA(Juillet_2018!C2:C17) -> 16 | J4: =COUNTA(Aout_2018!C2:C45) -> 22 | K4: =COUNTA(Septembre_2018!C2:C20) -> 15 | L4: =COUNTA(Octobre_2018!C2:C41) -> 40 | M4: =COUNTA(Novembre_2018!C2:C48) -> 47 | N4: =COUNTA(Decembre_2018!C2:C54) -> 53 | P4: P1 | Q4: =COUNTIF(Janvier_2018!C:C,"=P1") -> 26 | R4: =COUNTIF(Février_2018!C:C,"=P1") -> 20 | S4: =COUNTIF(Mars_2018!C:C,"=P1") -> 27 | T4: =COUNTIF(Avril_2018!C:C,"=P1") -> 37 | U4: =COUNTIF(Mai_2018!C:C,"=P1") -> 24 | V4: =COUNTIF(Juin_2018!C:C,"=P1") -> 33 | W4: =COUNTIF(Juillet_2018!C:C,"=P1") -> 15 | X4: =COUNTIF(Aout_2018!C:C,"=P1") -> 19 | Y4: =COUNTIF(Septembre_2018!C:C,"=P1") -> 12 | Z4: =COUNTIF(Octobre_2018!C:C,"=P1") -> 36 | AA4: =COUNTIF(Novembre_2018!C:C,"=P1") -> 43 | AB4: =COUNTIF(Decembre_2018!C:C,"=P1") -> 48 | AD4: GIN | AE4: =COUNTIF(Janvier_2018!$L:$L,"GIN") -> 0 | AF4: =COUNTIF(Février_2018!$L:$L,"GIN") -> 0 | AG4: =COUNTIF(Mars_2018!$L:$L,"GIN") -> 0 | AH4: =COUNTIF(Avril_2018!$L:$L,"GIN") -> 0 | AI4: =COUNTIF(Mai_2018!$L:$L,"GIN") -> 0 | AJ4: =COUNTIF(Juin_2018!$L:$L,"GIN") -> 0 | AK4: =COUNTIF(Juillet_2018!$L:$L,"GIN") -> 0 | AL4: =COUNTIF(Aout_2018!$L:$L,"GIN") -> 0 | AM4: =COUNTIF(Septembre_2018!$L:$L,"GIN") -> 0 | AN4: =COUNTIF(Octobre_2018!$L:$L,"GIN") -> 0 | AO4: =COUNTIF(Novembre_2018!$L:$L,"GIN") -> 0 | AP4: =COUNTIF(Decembre_2018!$L:$L,"GIN") -> 0
A5: InSLA | C5: =COUNTIF(Janvier_2018!$O$2:$O$32,"ISLA") -> 17 | D5: =COUNTIF(Février_2018!$O$2:$O$29,"ISLA") -> 15 | E5: =+COUNTIF(Mars_2018!$O$2:$O$41,"ISLA") -> 26 | F5: =COUNTIF(Avril_2018!$O$2:$O$44,"ISLA") -> 34 | G5: =+COUNTIF(Mai_2018!$O$2:$O$30,"ISLA") -> 22 | H5: =+COUNTIF(Juin_2018!$O$2:$O$45,"ISLA") -> 27 | I5: =COUNTIF(Juillet_2018!$O$2:$O$45,"ISLA") -> 11 | J5: =COUNTIF(Aout_2018!$O$2:$O$45,"ISLA") -> 12 | K5: =COUNTIF(Septembre_2018!$O$2:$O$20,"ISLA") -> 11 | L5: =COUNTIF(Octobre_2018!$O$2:$O$41,"ISLA") -> 25 | M5: =COUNTIF(Novembre_2018!$O$2:$O$48,"ISLA") -> 29 | N5: =COUNTIF(Decembre_2018!$O$2:$O$54,"ISLA") -> 36 | P5: P2 | Q5: =COUNTIF(Janvier_2018!C:C,"=P2") -> 4 | R5: =COUNTIF(Février_2018!C:C,"=P2") -> 7 | S5: =COUNTIF(Mars_2018!C:C,"=P2") -> 8 | T5: =COUNTIF(Avril_2018!C:C,"=P2") -> 5 | U5: =COUNTIF(Mai_2018!C:C,"=P2") -> 5 | V5: =COUNTIF(Juin_2018!C:C,"=P2") -> 11 | W5: =COUNTIF(Juillet_2018!C:C,"=P2") -> 0 | X5: =COUNTIF(Aout_2018!C:C,"=P2") -> 3 | Y5: =COUNTIF(Septembre_2018!C:C,"=P2") -> 3 | Z5: =COUNTIF(Octobre_2018!C:C,"=P2") -> 4 | AA5: =COUNTIF(Novembre_2018!C:C,"=P2") -> 4 | AB5: =COUNTIF(Decembre_2018!C:C,"=P2") -> 5 | AD5: SSPO | AE5: =COUNTIF(Janvier_2018!$L:$L,"SSPO") -> 16 | AF5: =COUNTIF(Février_2018!$L:$L,"SSPO") -> 8 | AG5: =COUNTIF(Mars_2018!$L:$L,"SSPO") -> 17 | AH5: =COUNTIF(Avril_2018!$L:$L,"SSPO") -> 19 | AI5: =COUNTIF(Mai_2018!$L:$L,"SSPO") -> 12 | AJ5: =COUNTIF(Juin_2018!$L:$L,"SSPO") -> 17 | AK5: =COUNTIF(Juillet_2018!$L:$L,"SSPO") -> 7 | AL5: =COUNTIF(Aout_2018!$L:$L,"SSPO") -> 15 | AM5: =COUNTIF(Septembre_2018!$L:$L,"SSPO") -> 8 | AN5: =COUNTIF(Octobre_2018!$L:$L,"SSPO") -> 19 | AO5: =COUNTIF(Novembre_2018!$L:$L,"SSPO") -> 21 | AP5: =COUNTIF(Decembre_2018!$L:$L,"SSPO") -> 30
A6: OutofSLA | C6: =COUNTIF(Janvier_2018!$O$2:$O$32,"oSLA") -> 14 | D6: =COUNTIF(Février_2018!$O$2:$O$29,"OSLA") -> 13 | E6: =+COUNTIF(Mars_2018!$O$2:$O$41,"OSLA") -> 14 | F6: =COUNTIF(Avril_2018!$O$2:$O$44,"OSLA") -> 9 | G6: =+COUNTIF(Mai_2018!$O$2:$O$30,"OSLA") -> 7 | H6: =+COUNTIF(Juin_2018!$O$2:$O$45,"OSLA") -> 17 | I6: =COUNTIF(Juillet_2018!$O$2:$O$45,"OSLA") -> 5 | J6: =COUNTIF(Aout_2018!$O$2:$O$45,"OSLA") -> 10 | K6: =COUNTIF(Septembre_2018!$O$2:$O$20,"OSLA") -> 4 | L6: =COUNTIF(Octobre_2018!$O$2:$O$41,"OSLA") -> 14 | M6: =COUNTIF(Novembre_2018!$O$2:$O$48,"OSLA") -> 18 | N6: =COUNTIF(Decembre_2018!$O$2:$O$54,"OSLA") -> 17 | P6: P3 | Q6: =COUNTIF(Janvier_2018!C:C,"=P3") -> 1 | R6: =COUNTIF(Février_2018!C:C,"=P3") -> 1 | S6: =COUNTIF(Mars_2018!C:C,"=P3") -> 5 | T6: =COUNTIF(Avril_2018!C:C,"=P3") -> 1 | U6: =COUNTIF(Mai_2018!C:C,"=P3") -> 0 | V6: =COUNTIF(Juin_2018!C:C,"=P3") -> 0 | W6: =COUNTIF(Juillet_2018!C:C,"=P3") -> 1 | X6: =COUNTIF(Aout_2018!C:C,"=P3") -> 0 | Y6: =COUNTIF(Septembre_2018!C:C,"=P3") -> 0 | Z6: =COUNTIF(Octobre_2018!C:C,"=P3") -> 0 | AA6: =COUNTIF(Novembre_2018!C:C,"=P3") -> 0 | AB6: =COUNTIF(Decembre_2018!C:C,"=P3") -> 0 | AD6: GOS | AE6: =COUNTIF(Janvier_2018!$L:$L,"GOS") -> 6 | AF6: =COUNTIF(Février_2018!$L:$L,"GOS") -> 9 | AG6: =COUNTIF(Mars_2018!$L:$L,"GOS") -> 4 | AH6: =COUNTIF(Avril_2018!$L:$L,"GOS") -> 5 | AI6: =COUNTIF(Mai_2018!$L:$L,"GOS") -> 1 | AJ6: =COUNTIF(Juin_2018!$L:$L,"GOS") -> 4 | AK6: =COUNTIF(Juillet_2018!$L:$L,"GOS") -> 0 | AL6: =COUNTIF(Aout_2018!$L:$L,"GOS") -> 1 | AM6: =COUNTIF(Septembre_2018!$L:$L,"GOS") -> 1 | AN6: =COUNTIF(Octobre_2018!$L:$L,"GOS") -> 2 | AO6: =COUNTIF(Novembre_2018!$L:$L,"GOS") -> 3 | AP6: =COUNTIF(Decembre_2018!$L:$L,"GOS") -> 8
A7: Nombre d'incidents causés par TP | C7: 5 | D7: 1 | E7: 3 | F7: 1 | G7: 0 | H7: 1 | I7: 0 | J7: 0 | K7: 1 | L7: 2 | M7: 0 | N7: 0 | P7: P4 | Q7: =COUNTIF(Janvier_2018!C:C,"=P4") -> 0 | R7: =COUNTIF(Février_2018!C:C,"=P4") -> 0 | S7: =COUNTIF(Mars_2018!C:C,"=P4") -> 0 | T7: =COUNTIF(Avril_2018!C:C,"=P4") -> 0 | U7: =COUNTIF(Mai_2018!C:C,"=P4") -> 0 | V7: =COUNTIF(Juin_2018!C:C,"=P4") -> 0 | W7: =COUNTIF(Juillet_2018!C:C,"=P4") -> 0 | X7: =COUNTIF(Aout_2018!C:C,"=P4") -> 0 | Y7: =COUNTIF(Septembre_2018!C:C,"=P4") -> 0 | Z7: =COUNTIF(Octobre_2018!C:C,"=P4") -> 0 | AA7: =COUNTIF(Novembre_2018!C:C,"=P4") -> 0 | AB7: =COUNTIF(Decembre_2018!C:C,"=P4") -> 0 | AD7: GNOC | AE7: =COUNTIF(Janvier_2018!$L:$L,"GNOC") -> 4 | AF7: =COUNTIF(Février_2018!$L:$L,"GNOC") -> 4 | AG7: =COUNTIF(Mars_2018!$L:$L,"GNOC") -> 6 | AH7: =COUNTIF(Avril_2018!$L:$L,"GNOC") -> 4 | AI7: =COUNTIF(Mai_2018!$L:$L,"GNOC") -> 7 | AJ7: =COUNTIF(Juin_2018!$L:$L,"GNOC") -> 5 | AK7: =COUNTIF(Juillet_2018!$L:$L,"GNOC") -> 5 | AL7: =COUNTIF(Aout_2018!$L:$L,"GNOC") -> 2 | AM7: =COUNTIF(Septembre_2018!$L:$L,"GNOC") -> 3 | AN7: =COUNTIF(Octobre_2018!$L:$L,"GNOC") -> 2 | AO7: =COUNTIF(Novembre_2018!$L:$L,"GNOC") -> 11 | AP7: =COUNTIF(Decembre_2018!$L:$L,"GNOC") -> 4
A8: MTTR | C8: =(SUM(COUNTIFS(Janvier_2018!C:C,"=P1",Janvier_2018!H:H,"<=120"),COUNTIFS(Janvier_2018!C:C,"=P2",Janvier_2018!H:H,"<=240"),COUNTIFS(Janvier_2018!C:C,"=P3",Janvier_2018!H:H,"<=2880")))/(SUM(COUNTIF(Janvier_2018!C:C,"=P1"),COUNTIF(Janvier_2018!C:C,"=P2"),COUNTIF(Janvier_2018!C:C,"=P3"))) -> 0.5483871 | D8: =(SUM(COUNTIFS(Février_2018!C:C,"=P1",Février_2018!H:H,"<=120"),COUNTIFS(Février_2018!C:C,"=P2",Février_2018!H:H,"<=240"),COUNTIFS(Février_2018!C:C,"=P3",Février_2018!H:H,"<=2880")))/(SUM(COUNTIF(Février_2018!C:C,"=P1"),COUNTIF(Février_2018!C:C,"=P2"),COUNTIF(Février_2018!C:C,"=P3"))) -> 0.53571429 | E8: =(SUM(COUNTIFS(Mars_2018!C:C,"=P1",Mars_2018!H:H,"<=120"),COUNTIFS(Mars_2018!C:C,"=P2",Mars_2018!H:H,"<=240"),COUNTIFS(Mars_2018!C:C,"=P3",Mars_2018!H:H,"<=2880")))/(SUM(COUNTIF(Mars_2018!C:C,"=P1"),COUNTIF(Mars_2018!C:C,"=P2"),COUNTIF(Mars_2018!C:C,"=P3"))) -> 0.65 | F8: =(SUM(COUNTIFS(Avril_2018!C:C,"=P1",Avril_2018!H:H,"<=120"),COUNTIFS(Avril_2018!C:C,"=P2",Avril_2018!H:H,"<=240"),COUNTIFS(Avril_2018!C:C,"=P3",Avril_2018!H:H,"<=2880")))/(SUM(COUNTIF(Avril_2018!C:C,"=P1"),COUNTIF(Avril_2018!C:C,"=P2"),COUNTIF(Avril_2018!C:C,"=P3"))) -> 0.79069767 | G8: =(SUM(COUNTIFS(Mai_2018!C:C,"=P1",Mai_2018!H:H,"<=120"),COUNTIFS(Mai_2018!C:C,"=P2",Mai_2018!H:H,"<=240"),COUNTIFS(Mai_2018!C:C,"=P3",Mai_2018!H:H,"<=2880")))/(SUM(COUNTIF(Mai_2018!C:C,"=P1"),COUNTIF(Mai_2018!C:C,"=P2"),COUNTIF(Mai_2018!C:C,"=P3"))) -> 0.75862069 | H8: =(SUM(COUNTIFS(Juin_2018!C:C,"=P1",Juin_2018!H:H,"<=120"),COUNTIFS(Juin_2018!C:C,"=P2",Juin_2018!H:H,"<=240"),COUNTIFS(Juin_2018!C:C,"=P3",Juin_2018!H:H,"<=2880")))/(SUM(COUNTIF(Juin_2018!C:C,"=P1"),COUNTIF(Juin_2018!C:C,"=P2"),COUNTIF(Juin_2018!C:C,"=P3"))) -> 0.61363636 | I8: =(SUM(COUNTIFS(Juillet_2018!C:C,"=P1",Juillet_2018!H:H,"<=120"),COUNTIFS(Juillet_2018!C:C,"=P2",Juillet_2018!H:H,"<=240"),COUNTIFS(Juillet_2018!C:C,"=P3",Juillet_2018!H:H,"<=2880")))/(SUM(COUNTIF(Juillet_2018!C:C,"=P1"),COUNTIF(Juillet_2018!C:C,"=P2"),COUNTIF(Juillet_2018!C:C,"=P3"))) -> 0.6875 | J8: =(SUM(COUNTIFS(Aout_2018!C:C,"=P1",Aout_2018!H:H,"<=120"),COUNTIFS(Aout_2018!C:C,"=P2",Aout_2018!H:H,"<=240"),COUNTIFS(Aout_2018!C:C,"=P3",Aout_2018!H:H,"<=2880")))/(SUM(COUNTIF(Aout_2018!C:C,"=P1"),COUNTIF(Aout_2018!C:C,"=P2"),COUNTIF(Aout_2018!C:C,"=P3"))) -> 0.54545455 | K8: =(SUM(COUNTIFS(Septembre_2018!C:C,"=P1",Septembre_2018!H:H,"<=120"),COUNTIFS(Septembre_2018!C:C,"=P2",Septembre_2018!H:H,"<=240"),COUNTIFS(Septembre_2018!C:C,"=P3",Septembre_2018!H:H,"<=2880")))/(SUM(COUNTIF(Septembre_2018!C:C,"=P1"),COUNTIF(Septembre_2018!C:C,"=P2"),COUNTIF(Septembre_2018!C:C,"=P3"))) -> 0.73333333 | L8: =(SUM(COUNTIFS(Octobre_2018!C:C,"=P1",Octobre_2018!H:H,"<=120"),COUNTIFS(Octobre_2018!C:C,"=P2",Octobre_2018!H:H,"<=240"),COUNTIFS(Octobre_2018!C:C,"=P3",Octobre_2018!H:H,"<=2880")))/(SUM(COUNTIF(Octobre_2018!C:C,"=P1"),COUNTIF(Octobre_2018!C:C,"=P2"),COUNTIF(Octobre_2018!C:C,"=P3"))) -> 0.65 | M8: =(SUM(COUNTIFS(Novembre_2018!C:C,"=P1",Novembre_2018!H:H,"<=120"),COUNTIFS(Novembre_2018!C:C,"=P2",Novembre_2018!H:H,"<=240"),COUNTIFS(Novembre_2018!C:C,"=P3",Novembre_2018!H:H,"<=2880")))/(SUM(COUNTIF(Novembre_2018!C:C,"=P1"),COUNTIF(Novembre_2018!C:C,"=P2"),COUNTIF(Novembre_2018!C:C,"=P3"))) -> 0.61702128 | N8: =(SUM(COUNTIFS(Decembre_2018!C:C,"=P1",Decembre_2018!H:H,"<=120"),COUNTIFS(Decembre_2018!C:C,"=P2",Decembre_2018!H:H,"<=240"),COUNTIFS(Decembre_2018!C:C,"=P3",Decembre_2018!H:H,"<=2880")))/(SUM(COUNTIF(Decembre_2018!C:C,"=P1"),COUNTIF(Decembre_2018!C:C,"=P2"),COUNTIF(Decembre_2018!C:C,"=P3"))) -> 0.66037736 | P8: Total | Q8: =SUM(Q4:Q7) -> 31 | R8: =SUM(R4:R7) -> 28 | S8: =SUM(S4:S7) -> 40 | T8: =SUM(T4:T7) -> 43 | U8: =SUM(U4:U7) -> 29 | V8: =SUM(V4:V7) -> 44 | W8: =SUM(W4:W7) -> 16 | X8: =SUM(X4:X7) -> 22 | ... AB8: =SUM(AB4:AB7) -> 53 | AD8: ASBD | AE8: =COUNTIF(Janvier_2018!$L:$L,"ASBD") -> 2 | AF8: =COUNTIF(Février_2018!$L:$L,"ASBD") -> 2 | AG8: =COUNTIF(Mars_2018!$L:$L,"ASBD") -> 4 | AH8: =COUNTIF(Avril_2018!$L:$L,"ASBD") -> 8 | AI8: =COUNTIF(Mai_2018!$L:$L,"ASBD") -> 3 | AJ8: =COUNTIF(Juin_2018!$L:$L,"ASBD") -> 3 | AK8: =COUNTIF(Juillet_2018!$L:$L,"ASBD") -> 1 | AL8: =COUNTIF(Aout_2018!$L:$L,"ASBD") -> 2 | AM8: =COUNTIF(Septembre_2018!$L:$L,"ASBD") -> 1 | AN8: =COUNTIF(Octobre_2018!$L:$L,"ASBD") -> 11 | AO8: =COUNTIF(Novembre_2018!$L:$L,"ASBD") -> 6 | AP8: =COUNTIF(Decembre_2018!$L:$L,"ASBD") -> 3
AD9: DevOps | AE9: =COUNTIF(Janvier_2018!$L:$L,"PSIVAS") -> 1 | AF9: =COUNTIF(Février_2018!$L:$L,"DevOps") -> 0 | AG9: =COUNTIF(Mars_2018!$L:$L,"DevOps") -> 0 | AH9: =COUNTIF(Avril_2018!$L:$L,"DevOps") -> 0 | AI9: =COUNTIF(Mai_2018!$L:$L,"DevOps") -> 0 | AJ9: =COUNTIF(Juin_2018!$L:$L,"DevOps") -> 2 | AK9: =COUNTIF(Juillet_2018!$L:$L,"DevOps") -> 0 | AL9: =COUNTIF(Aout_2018!$L:$L,"DevOps") -> 0 | AM9: =COUNTIF(Septembre_2018!$L:$L,"DevOps") -> 1 | AN9: =COUNTIF(Octobre_2018!$L:$L,"DevOps") -> 0 | AO9: =COUNTIF(Novembre_2018!$L:$L,"DevOps") -> 0 | AP9: =COUNTIF(Decembre_2018!$L:$L,"DevOps") -> 3
A11: Service | P11: Statut | AD11: TPS vs trafic
B13: Jan | C13: Jan | D13: Fev | E13: Mars | F13: Avril | G13: Mai | H13: Juin | I13: Juillet | J13: Août | K13: Sept | L13: Oct | M13: Nov | N13: Dec | Q13: Jan | R13: Fev | S13: Mars | T13: Avril | U13: Mai | V13: Juin | W13: Juillet | X13: Août | Y13: Sept | Z13: Oct | AA13: Nov | AB13: Dec | AE13: Jan | AF13: Fev | AG13: Mars | AH13: Avril | AI13: Mai | AJ13: Juin | AK13: Juillet | AL13: Août | AM13: Sept | AN13: Oct | AO13: Nov
A14: E-recharge | C14: =COUNTIF(Janvier_2018!$E$2:$E$32,"*E-recharge*") -> 3 | D14: =COUNTIF(Février_2018!$E$2:$E$45,"*E-recharge*") -> 1 | E14: =COUNTIF(Mars_2018!$E$2:$E$45,"*E-recharge*") -> 2 | F14: =COUNTIF(Avril_2018!$E$2:$E$45,"*E-recharge*") -> 4 | G14: =COUNTIF(Mai_2018!$E$2:$E$45,"*E-recharge*") -> 6 | H14: =COUNTIF(Juin_2018!$E$2:$E$45,"*E-recharge*") -> 9 | I14: =COUNTIF(Juillet_2018!$E$2:$E$45,"*E-recharge*") -> 2 | J14: =COUNTIF(Aout_2018!$E$2:$E$45,"*E-recharge*") -> 0 | K14: =COUNTIF(Septembre_2018!$E$2:$E$45,"*E-recharge*") -> 0 | L14: =COUNTIF(Octobre_2018!$E$2:$E$46,"*E-recharge*") -> 3 | M14: =COUNTIF(Novembre_2018!$I$2:$I$48,"*E-recharge*") -> 6 | N14: =COUNTIF(Novembre_2018!$I$2:$I$54,"*E-recharge*") -> 6 | P14: En cours | Q14: =COUNTIF(Janvier_2018!$M$2:$M$45,"En cours") -> 0 | R14: =COUNTIF(Février_2018!$M$2:$M$45,"En cours") -> 0 | S14: =COUNTIF(Mars_2018!$M$2:$M$45,"En cours") -> 0 | T14: =COUNTIF(Avril_2018!$M$2:$M$45,"En cours") -> 0 | U14: =COUNTIF(Mai_2018!$M$2:$M$45,"En cours") -> 0 | V14: =COUNTIF(Juin_2018!$M$2:$M$45,"En cours") -> 0 | W14: =COUNTIF(Juillet_2018!$M$2:$M$45,"En cours") -> 0 | X14: =COUNTIF(Aout_2018!$M$2:$M$45,"En cours") -> 0 | Y14: =COUNTIF(Septembre_2018!$M$2:$M$20,"En cours") -> 0 | Z14: =COUNTIF(Octobre_2018!$M$2:$M$41,"En cours") -> 0 | AA14: =COUNTIF(Novembre_2018!$M$2:$M$48,"En cours") -> 0 | AB14: =COUNTIF(Decembre_2018!$M$2:$M$53,"En cours") -> 1 | AD14: Trafic
A15: Orange Money | C15: =COUNTIF(Janvier_2018!$E$2:$E$32,"*Orange Money*") -> 13 | D15: =COUNTIF(Février_2018!$E$2:$E$45,"*Orange Money*") -> 7 | E15: =COUNTIF(Mars_2018!$E$2:$E$45,"*Orange Money*") -> 18 | F15: =COUNTIF(Avril_2018!$E$2:$E$45,"*Orange Money*") -> 20 | G15: =COUNTIF(Mai_2018!$E$2:$E$45,"*Orange Money*") -> 11 | H15: =COUNTIF(Juin_2018!$E$2:$E$45,"*Orange Money*") -> 15 | I15: =COUNTIF(Juillet_2018!$E$2:$E$45,"*Orange Money*") -> 7 | J15: =COUNTIF(Aout_2018!$E$2:$E$45,"*Orange Money*") -> 16 | K15: =COUNTIF(Septembre_2018!$E$2:$E$45,"*Orange Money*") -> 4 | L15: =COUNTIF(Octobre_2018!$E$2:$E$46,"*Orange Money*") -> 19 | M15: =COUNTIF(Novembre_2018!$E$2:$E$48,"*Orange Money*") -> 25 | N15: =COUNTIF(Novembre_2018!$E$2:$E$54,"*Orange Money*") -> 25 | P15: clos | Q15: =COUNTIF(Janvier_2018!$M$2:$M$45,"Clos") -> 31 | R15: =COUNTIF(Février_2018!$M$2:$M$45,"Clos") -> 28 | S15: =COUNTIF(Mars_2018!$M$2:$M$45,"Clos") -> 40 | T15: =COUNTIF(Avril_2018!$M$2:$M$45,"Clos") -> 43 | U15: =COUNTIF(Mai_2018!$M$2:$M$45,"Clos") -> 29 | V15: =COUNTIF(Juin_2018!$M$2:$M$45,"Clos") -> 44 | W15: =COUNTIF(Juillet_2018!$M$2:$M$45,"Clos") -> 16 | X15: =COUNTIF(Aout_2018!$M$2:$M$45,"Clos") -> 22 | Y15: =COUNTIF(Septembre_2018!$M$2:$M$20,"Clos") -> 15 | Z15: =COUNTIF(Octobre_2018!$M$2:$M$41,"Clos") -> 39 | AA15: =COUNTIF(Novembre_2018!$M$2:$M$48,"Clos") -> 47 | AB15: =COUNTIF(Decembre_2018!$M$2:$M$54,"Clos") -> 52 | AD15: TPS
A16: Internet | C16: =COUNTIF(Janvier_2018!$E$2:$E$32,"*Data mobile*") -> 2 | D16: =COUNTIF(Février_2018!$E$2:$E$45,"*Data mobile*") -> 2 | E16: =COUNTIF(Mars_2018!$E$2:$E$45,"*Data mobile*") -> 2 | F16: =COUNTIF(Avril_2018!$E$2:$E$45,"*Data mobile*") -> 2 | G16: =COUNTIF(Mai_2018!$E$2:$E$45,"*Data mobile*") -> 0 | H16: =COUNTIF(Juin_2018!$E$2:$E$45,"*Data mobile*") -> 0 | I16: =COUNTIF(Juillet_2018!$E$2:$E$45,"*Data mobile*") -> 1 | J16: =COUNTIF(Aout_2018!$E$2:$E$45,"*Data mobile*") -> 1 | K16: =COUNTIF(Septembre_2018!$E$2:$E$45,"*Data mobile*") -> 3 | L16: =COUNTIF(Octobre_2018!$E$2:$E$46,"*Data mobile*") -> 1 | M16: =COUNTIF(Novembre_2018!$I$2:$I$48,"*Data mobile*") -> 0 | N16: =COUNTIF(Novembre_2018!$I$2:$I$54,"*Data mobile*") -> 0 | P16: gélé | Q16: =COUNTIF(Janvier_2018!$M$2:$M$45,"gele") -> 0 | R16: =COUNTIF(Février_2018!$M$2:$M$45,"gele") -> 0 | S16: =COUNTIF(Mars_2018!$M$2:$M$45,"gele") -> 0 | T16: =COUNTIF(Avril_2018!$M$2:$M$45,"gele") -> 0 | U16: =COUNTIF(Mai_2018!$M$2:$M$45,"gele") -> 0 | V16: =COUNTIF(Juin_2018!$M$2:$M$45,"gele") -> 0 | W16: =COUNTIF(Juillet_2018!$M$2:$M$45,"gele") -> 0 | X16: =COUNTIF(Aout_2018!$M$2:$M$45,"gele") -> 0 | Y16: =COUNTIF(Septembre_2018!$M$2:$M$20,"gele") -> 0 | Z16: =COUNTIF(Octobre_2018!$M$2:$M$41,"gele") -> 0 | AA16: =COUNTIF(Novembre_2018!$M$2:$M$48,"gele") -> 0 | AB16: =COUNTIF(Decembre_2018!$M$2:$M$53,"gele") -> 0
A17: Voix | C17: =COUNTIF(Janvier_2018!$E$2:$E$32,"*VOIX*") -> 2 | D17: =COUNTIF(Février_2018!$E$2:$E$45,"*VOIX*") -> 0 | E17: =COUNTIF(Mars_2018!$E$2:$E$45,"*VOIX*") -> 1 | F17: =COUNTIF(Avril_2018!$E$2:$E$45,"*VOIX*") -> 0 | G17: =COUNTIF(Mai_2018!$E$2:$E$45,"*VOIX*") -> 1 | H17: =COUNTIF(Juin_2018!$E$2:$E$45,"*VOIX*") -> 3 | I17: =COUNTIF(Juillet_2018!$E$2:$E$45,"*VOIX*") -> 2 | J17: =COUNTIF(Aout_2018!$E$2:$E$45,"*VOIX*") -> 0 | K17: =COUNTIF(Septembre_2018!$E$2:$E$45,"*VOIX*") -> 0 | L17: =COUNTIF(Octobre_2018!$E$2:$E$46,"*VOIX*") -> 0 | M17: =COUNTIF(Novembre_2018!$I$2:$I$48,"*VOIX*") -> 3 | N17: =COUNTIF(Novembre_2018!$I$2:$I$54,"*VOIX*") -> 3
A18: SMS | C18: =COUNTIF(Janvier_2018!$E$2:$E$32,"*SMS*") -> 1 | D18: =COUNTIF(Février_2018!$E$2:$E$45,"*SMS*") -> 4 | E18: =COUNTIF(Mars_2018!$E$2:$E$45,"*SMS*") -> 0 | F18: =COUNTIF(Avril_2018!$E$2:$E$45,"*SMS*") -> 3 | G18: =COUNTIF(Mai_2018!$E$2:$E$45,"*SMS*") -> 2 | H18: =COUNTIF(Juin_2018!$E$2:$E$45,"*SMS*") -> 1 | I18: =COUNTIF(Juillet_2018!$E$2:$E$45,"*SMS*") -> 2 | J18: =COUNTIF(Aout_2018!$E$2:$E$45,"*SMS*") -> 0 | K18: =COUNTIF(Septembre_2018!$E$2:$E$45,"*SMS*") -> 1 | L18: =COUNTIF(Octobre_2018!$E$2:$E$46,"*SMS*") -> 1 | M18: =COUNTIF(Novembre_2018!$I$2:$I$48,"*SMS*") -> 5 | N18: =COUNTIF(Novembre_2018!$I$2:$I$54,"*SMS*") -> 5
A19: VAS | C19: =C4-(C14+C15+C16+C17+C18+C20+C21+C22) -> 10 | D19: =D4-(D14+D15+D16+D17+D18+D20+D21+D22) -> 13 | E19: =E4-(E14+E15+E16+E17+E18+E20+E21+E22) -> 17 | F19: =F4-(F14+F15+F16+F17+F18+F20+F21+F22) -> 14 | G19: =G4-(G14+G15+G16+G17+G18+G20+G21+G22) -> 9 | H19: =H4-(H14+H15+H16+H17+H18+H20+H21+H22) -> 16 | I19: =I4-(I14+I15+I16+I17+I18+I20+I21+I22) -> 2 | J19: =J4-(J14+J15+J16+J17+J18+J20+J21+J22) -> 4 | ... N19: =N4-(N14+N15+N16+N17+N18+N20+N21+N22) -> 14
A20: Roaming voix | C20: =COUNTIF(Janvier_2018!$E$2:$E$45,"*Roaming voix*") -> 0 | D20: =COUNTIF(Février_2018!$E$2:$E$45,"*Roaming voix*") -> 0 | E20: =COUNTIF(Mars_2018!$E$2:$E$45,"*Roaming voix*") -> 0 | F20: =COUNTIF(Avril_2018!$E$2:$E$45,"*Roaming voix*") -> 0 | G20: =COUNTIF(Mai_2018!$E$2:$E$45,"*Roaming voix*") -> 0 | H20: =COUNTIF(Juin_2018!$E$2:$E$45,"*Roaming voix*") -> 0 | I20: =COUNTIF(Juillet_2018!$E$2:$E$45,"*Roaming voix*") -> 0 | J20: =COUNTIF(Aout_2018!$E$2:$E$45,"*Roaming voix*") -> 0 | K20: =COUNTIF(Septembre_2018!$E$2:$E$45,"*Roaming voix*") -> 0 | L20: =COUNTIF(Octobre_2018!$E$2:$E$46,"*Roaming voix*") -> 0 | M20: =COUNTIF(Novembre_2018!$I$2:$I$48,"*Roaming voix*") -> 0 | N20: =COUNTIF(Novembre_2018!$I$2:$I$54,"*Roaming voix*") -> 0
A21: Roaming data | C21: =COUNTIF(Janvier_2018!$E$2:$E$45,"*Roaming data*") -> 0 | D21: =COUNTIF(Février_2018!$E$2:$E$45,"*Roaming data*") -> 1 | E21: =COUNTIF(Mars_2018!$E$2:$E$45,"*Roaming data*") -> 0 | F21: =COUNTIF(Avril_2018!$E$2:$E$45,"*Roaming data*") -> 0 | G21: =COUNTIF(Mai_2018!$E$2:$E$45,"*Roaming data*") -> 0 | H21: =COUNTIF(Juin_2018!$E$2:$E$45,"*Roaming data*") -> 0 | I21: =COUNTIF(Juillet_2018!$E$2:$E$45,"*Roaming data*") -> 0 | J21: =COUNTIF(Aout_2018!$E$2:$E$45,"*Roaming data*") -> 1 | K21: =COUNTIF(Septembre_2018!$E$2:$E$45,"*Roaming data*") -> 0 | L21: =COUNTIF(Octobre_2018!$E$2:$E$46,"*Roaming data*") -> 0 | M21: =COUNTIF(Novembre_2018!$I$2:$I$48,"*Roaming data*") -> 0 | N21: =COUNTIF(Novembre_2018!$I$2:$I$54,"*Roaming data*") -> 0
A22: Roaming SMS | C22: =COUNTIF(Janvier_2018!$E$2:$E$45,"*Roaming sms*") -> 0 | D22: =COUNTIF(Février_2018!$E$2:$E$45,"*Roaming sms*") -> 0 | E22: =COUNTIF(Mars_2018!$E$2:$E$45,"*Roaming sms*") -> 0 | F22: =COUNTIF(Avril_2018!$E$2:$E$45,"*Roaming sms*") -> 0 | G22: =COUNTIF(Mai_2018!$E$2:$E$45,"*Roaming sms*") -> 0 | H22: =COUNTIF(Juin_2018!$E$2:$E$45,"*Roaming sms*") -> 0 | I22: =COUNTIF(Juillet_2018!$E$2:$E$45,"*Roaming sms*") -> 0 | J22: =COUNTIF(Aout_2018!$E$2:$E$45,"*Roaming sms*") -> 0 | K22: =COUNTIF(Septembre_2018!$E$2:$E$45,"*Roaming sms*") -> 0 | L22: =COUNTIF(Octobre_2018!$E$2:$E$46,"*Roaming sms*") -> 0 | M22: =COUNTIF(Novembre_2018!$I$2:$I$48,"*Roaming sms*") -> 0 | N22: =COUNTIF(Novembre_2018!$I$2:$I$54,"*Roaming sms*") -> 0

Sheet objectifs_Semestre_2_2018
A3: Objectifs | B3: Sem 33 | C3: Sem 34 | D3: Sem 35 | E3: Sem 36 | F3: Sem 37 | G3: Sem 38 | H3: Sem 39 | I3: Sem 40 | J3: Sem 41 | K3: Sem 42 | L3: Sem 43 | M3: Sem 44 | N3: Sem 45 | O3: Sem 46 | P3: Sem 47 | Q3: Sem 48 | R3: Sem 49 | S3: Sem 50 | T3: Sem 51 | U3: Sem 52 | V3: Sem 01 | W3: Sem 02 | X3: Sem 03 | Y3: Sem 04 | Z3: Sem 05 | AA3: Sem 06 | AB3: Sem 07
A4: Faire un suivi journalier des tickets d’incidents en cours avec le GNOC et s’assurer que les rapports d’incidents P1 et P2 sont joints dans océane avant clôture. | B4: 1 | C4: 1 | D4: 1 | E4: 1 | F4: 1 | G4: 1 | H4: 1 | I4: 1 | J4: 1 | K4: 1 | L4: 1 | M4: 1 | N4: 1 | O4: 1 | P4: 1 | Q4: 1 | R4: 1 | S4: 1 | T4: 1 | U4: 1 | V4: - | W4: - | X4: - | Y4: - | Z4: - | AA4: - | AB4: -
A5: Initier les tickets problèmes vers les problem managers pour tous les incidents dont la RC n’est pas connue ou pour toutes récurrences avec les mêmes causes (3 ème récurrence). Relier les tickets d’incident au ticket problème pour une bonne traçabilité | B5: 1 | C5: 1 | D5: 1 | E5: 1 | F5: 1 | G5: 1 | H5: 1 | I5: 1 | J5: 1 | K5: 1 | L5: 1 | M5: 1 | N5: 1 | O5: 1 | P5: 1 | Q5: 1 | R5: 1 | S5: 1 | T5: 1 | U5: 1 | V5: 1 | W5: 1 | X5: 1 | Y5: 1 | Z5: 1 | AA5: 1 | AB5: 1
A6: Fournir le Rapport de pilotage d’incident au (rapport service) à J pour les P1 et P2 y compris les récurrences | B6: - | C6: - | D6: - | E6: - | F6: - | G6: - | H6: - | I6: 1 | J6: - | K6: - | L6: - | M6: 1 | N6: - | O6: - | P6: 1 | Q6: 1 | R6: - | S6: 1 | T6: - | U6: 1 | V6: - | W6: - | X6: - | Y6: - | Z6: - | AA6: - | AB6: -
A7: faire la mise à jour de toutes les architectures reseaux et service ainsi que les chaines de soutien (organiser des ateliers) | B7: NE | C7: NE | D7: NE | E7: NE | F7: NE | G7: NE | H7: NE | I7: 1 | J7: NE | K7: NE | L7: NE | M7: NE | N7: NE | O7: NE | P7: NE | Q7: NE | R7: 1 | S7: NE | T7: NE | U7: NE | V7: NE | W7: NE | X7: NE | Y7: NE | Z7: NE | AA7: NE | AB7: NE
A8: faire le suivi de traitement des alarmes et mettre à jour le fichier | B8: 1 | C8: 1 | D8: 1 | E8: 1 | F8: 1 | G8: 1 | H8: 1 | I8: 1 | J8: 1 | K8: 1 | L8: 1 | M8: 1 | N8: 1 | O8: 1 | P8: 1 | Q8: 1 | R8: 1 | S8: 1 | T8: 1 | U8: 1 | V8: 1 | W8: 1 | X8: 1 | Y8: 1 | Z8: 1 | AA8: 1 | AB8: 1

Sheet Janvier_2018
A1: N° | B1: N°ticket | C1: Priorité | D1: Origine | E1: Nom Service | F1: Date & heure de début | G1: Date & heure de fin | H1: Durée (mn) | I1: Description | J1: Cause de l'incident | K1: Actions correctives | L1: TMC | M1: Statut | N1: Observation | O1: SLA
A2: 1 | B2: 1712W17506 | C2: P1 | D2: Supervision | E2: Orange Money | F2: 43095.462 | G2: 04/01/2018 16:28 | H2: 13283 | I2: Instabilités sur Orange Money | J2: Saturation de la table de sessions TCP en cours(97-98%) sur le firewall Orange Infra ( PFSense) | K2: Augmentation de la capacité de la table de sessions TCP( de 47.000 à 201.000 sessions) et redémarrage du firewall | L2: GOS | M2: Clos | O2: =IF(AND(C2=Mai_2018!$B$47,H2<=Mai_2018!$D$47),"ISLA",IF((AND(C2=Mai_2018!$B$48,H2<=Mai_2018!$D$48)),"ISLA",IF((AND(C2=Mai_2018!$B$49,H2<=Mai_2018!$D$49)),"ISLA","OSLA"))) -> OSLA
A3: 2 | B3: 1801X31657 | C3: P1 | D3: Supervision | E3: E-recharge, Voix, Data mobile, SMS, USSD | F3: 43101.097 | G3: 43101.115 | H3: 25 | I3: Echecs de 60% des transactions E-recharge, consultation solde crédit et Data | J3: Redémarrage de plusieurs OCPRO sur le OCS6 | K3: Switching de l'OCS6 vers l'OCS5 | L3: GNOC | M3: Clos | O3: =IF(AND(C3=Mai_2018!$B$47,H3<=Mai_2018!$D$47),"ISLA",IF((AND(C3=Mai_2018!$B$48,H3<=Mai_2018!$D$48)),"ISLA",IF((AND(C3=Mai_2018!$B$49,H3<=Mai_2018!$D$49)),"ISLA","OSLA"))) -> ISLA
A4: 3 | B4: 1801X71667 | C4: P1 | D4: SSPO | E4: MyOrange / OBeta | F4: 43102.882 | G4: 43103.316 | H4: 625 | I4: MyOrange | J4: Crash du pare-feu physique | K4: Remplacement du pare-feu physique | L4: SSPO | M4: Clos | O4: =IF(AND(C4=Mai_2018!$B$47,H4<=Mai_2018!$D$47),"ISLA",IF((AND(C4=Mai_2018!$B$48,H4<=Mai_2018!$D$48)),"ISLA",IF((AND(C4=Mai_2018!$B$49,H4<=Mai_2018!$D$49)),"ISLA","OSLA"))) -> OSLA
A5: 4 | B5: 1801X71882 | C5: P1 | D5: SSPO | E5: AppsOrange | F5: 43102.882 | G5: 43103.358 | H5: 685 | I5: AppsOrange | J5: Crash du pare-feu physique | K5: Remplacement du pare-feu physique | L5: SSPO | M5: Clos | O5: =IF(AND(C5=Mai_2018!$B$47,H5<=Mai_2018!$D$47),"ISLA",IF((AND(C5=Mai_2018!$B$48,H5<=Mai_2018!$D$48)),"ISLA",IF((AND(C5=Mai_2018!$B$49,H5<=Mai_2018!$D$49)),"ISLA","OSLA"))) -> OSLA
A6: 5 | B6: 1801X71866 | C6: P2 | D6: SSPO | E6: Orange Money add-on / Web Payment | F6: 43102.868 | G6: 43103.31 | H6: 637 | I6: Orange Money add-on / Web Payment | J6: Crash du pare-feu physique | K6: Remplacement du pare-feu physique | L6: SSPO | M6: Clos | O6: =IF(AND(C6=Mai_2018!$B$47,H6<=Mai_2018!$D$47),"ISLA",IF((AND(C6=Mai_2018!$B$48,H6<=Mai_2018!$D$48)),"ISLA",IF((AND(C6=Mai_2018!$B$49,H6<=Mai_2018!$D$49)),"ISLA","OSLA"))) -> OSLA
A7: 6 | B7: 1801Y04958 | C7: P1 | D7: SSPO | E7: Orange Money add-on / Bank to Wallet / Ecobank | F7: 43103.785 | G7: 43103.826 | H7: 60 | I7: Impossible de faire des transactions bancaire via OM | J7: Perte de connexion avec le partenaire Ecobank | K7: Retablissement de la connexion | L7: SSPO | M7: Clos | O7: =IF(AND(C7=Mai_2018!$B$47,H7<=Mai_2018!$D$47),"ISLA",IF((AND(C7=Mai_2018!$B$48,H7<=Mai_2018!$D$48)),"ISLA",IF((AND(C7=Mai_2018!$B$49,H7<=Mai_2018!$D$49)),"ISLA","OSLA"))) -> ISLA
A8: 7 | B8: 1801Y34694 | C8: P1 | D8: Supervision | E8: Mobile TV | F8: 43104.64 | G8: 43104.669 | H8: 42 | I8: Indisponibilité des chaines West-Africa, Boom TV, 2STV, RTG | J8: le dongle satellite était down | K8: Reset du dongle | L8: OLS | M8: Clos | O8: =IF(AND(C8=Mai_2018!$B$47,H8<=Mai_2018!$D$47),"ISLA",IF((AND(C8=Mai_2018!$B$48,H8<=Mai_2018!$D$48)),"ISLA",IF((AND(C8=Mai_2018!$B$49,H8<=Mai_2018!$D$49)),"ISLA","OSLA"))) -> ISLA
A9: 8 | B9: 1801Z31688 | C9: P1 | D9: SSPO | E9: Orange Money add-on / Bank to Wallet / Ecobank | F9: 43108.796 | G9: 43108.838 | H9: 60 | I9: Impossible de faire des transactions bancaire via OM | J9: Perte de connexion avec le partenaire Ecobank | K9: Retablissement de la connexion | L9: SSPO | M9: Clos | O9: =IF(AND(C9=Mai_2018!$B$47,H9<=Mai_2018!$D$47),"ISLA",IF((AND(C9=Mai_2018!$B$48,H9<=Mai_2018!$D$48)),"ISLA",IF((AND(C9=Mai_2018!$B$49,H9<=Mai_2018!$D$49)),"ISLA","OSLA"))) -> ISLA
A10: 9 | B10: 1801Z34552 | C10: P1 | D10: Supervision | E10: FFC | F10: 43109.014 | G10: 43109.4 | H10: 556 | I10: FootBall Fans CluB (*191#) | J10: Plantage du processus frontal USSD | K10: Redémarrage du processus frontal USSD | L10: ASPIDER | M10: Clos | O10: =IF(AND(C10=Mai_2018!$B$47,H10<=Mai_2018!$D$47),"ISLA",IF((AND(C10=Mai_2018!$B$48,H10<=Mai_2018!$D$48)),"ISLA",IF((AND(C10=Mai_2018!$B$49,H10<=Mai_2018!$D$49)),"ISLA","OSLA"))) -> OSLA
A11: 10 | B11: 1801Z70090 | C11: P1 | D11: SSPO | E11: MyOrange / Orange Beta | F11: 43110.301 | G11: 43110.369 | H11: 97 | I11: MyOrange | J11: indisponibilité du WT pour certaines des filiales due à des mauvaises configurations lors d'une opération | K11: Correction manuelle du problème de configuration du côté WT.COM | L11: SSPO | M11: Clos | O11: =IF(AND(C11=Mai_2018!$B$47,H11<=Mai_2018!$D$47),"ISLA",IF((AND(C11=Mai_2018!$B$48,H11<=Mai_2018!$D$48)),"ISLA",IF((AND(C11=Mai_2018!$B$49,H11<=Mai_2018!$D$49)),"ISLA","OSLA"))) -> ISLA
A12: 11 | B12: 1801Z71927 | C12: P1 | D12: SSPO | E12: Orange Money add-on / Bank to Wallet / Ecobank | F12: 43110.34 | G12: 43110.377 | H12: 53 | I12: Impossible de faire des transactions bancaire via OM | J12: Opération planifiée(impact non prévu) | K12: Roll back | L12: SSPO | M12: Clos | O12: =IF(AND(C12=Mai_2018!$B$47,H12<=Mai_2018!$D$47),"ISLA",IF((AND(C12=Mai_2018!$B$48,H12<=Mai_2018!$D$48)),"ISLA",IF((AND(C12=Mai_2018!$B$49,H12<=Mai_2018!$D$49)),"ISLA","OSLA"))) -> ISLA
A13: 12 | B13: 1801A10964 | C13: P1 | D13: SSPO | E13: Orange Money | F13: 43111.46 | G13: 43111.465 | H13: 6 | I13: Impossibilité d'effectuer des transactions pendant un intervalle d'environ 6 minutes | J13: Dû à un APT côté DIF (T801042519) | K13: aucune | L13: SSPO | M13: Clos | O13: =IF(AND(C13=Mai_2018!$B$47,H13<=Mai_2018!$D$47),"ISLA",IF((AND(C13=Mai_2018!$B$48,H13<=Mai_2018!$D$48)),"ISLA",IF((AND(C13=Mai_2018!$B$49,H13<=Mai_2018!$D$49)),"ISLA","OSLA"))) -> ISLA
A14: 13 | B14: 1801A25215 | C14: P1 | D14: Supervision | E14: Nomad | F14: 43111.625 | G14: 43111.763 | H14: 199 | I14: Indisponibilité à la page Nomad | J14: Saturation du répertoire /opt/application/nomadsubscription | K14: Purge du répertoire | L14: GOS | M14: Clos | O14: =IF(AND(C14=Mai_2018!$B$47,H14<=Mai_2018!$D$47),"ISLA",IF((AND(C14=Mai_2018!$B$48,H14<=Mai_2018!$D$48)),"ISLA",IF((AND(C14=Mai_2018!$B$49,H14<=Mai_2018!$D$49)),"ISLA","OSLA"))) -> OSLA
... A32: 31 | B32: 1801E68898 | C32: P1 | D32: Supervision | E32: Consultation de solde data (*222*5#) | F32: 43129.556 | G32: 43129.649 | H32: 135 | I32: Impossible de consulter le solde data avec *222*5*#. Service indisponible | J32: Bagotement réseau sur l'environnement virtuel de Sonfonia | K32: Aucune | L32: ASBD | M32: Clos | O32: =IF(AND(C32=Mai_2018!$B$47,H32<=Mai_2018!$D$47),"ISLA",IF((AND(C32=Mai_2018!$B$48,H32<=Mai_2018!$D$48)),"ISLA",IF((AND(C32=Mai_2018!$B$49,H32<=Mai_2018!$D$49)),"ISLA","OSLA"))) -> OSLA
B47: P1 | C47: 2h | D47: 120
B48: P2 | C48: 4h | D48: 240
B49: P3 | C49: 2jr | D49: =1440*2 -> 2880
B50: P4 | C50: 3jr | D50: =3*1440 -> 4320

Sheet Février_2018
A1: N° | B1: N°ticket | C1: Priorité | D1: Origine | E1: Nom Service | F1: Date & heure de début | G1: Date & heure de fin | H1: Durée (mn) | I1: Description | J1: Cause de l'incident | K1: Actions correctives | L1: TMC | M1: Statut | N1: Observation | O1: SLA
A2: 1 | B2: 1802F56763 | C2: P1 | D2: GOS | E2: Gameloft, Myorange, CMS, SMS_API, OTAP, MegaWin | F2: 43132.505 | G2: 43132.533 | H2: 40 | I2: instabilité/indisponibilité Gameloft, Myorange, CMS, SMS_API, OTAP, MegaWin | J2: Hausse de charge CPU a été observé sur la VM opsdpgosumscl02 | K2: Déplacement de la VM vers une autre LAME et redémarrage | L2: GOS | M2: Clos | O2: =IF(AND(C2=$B$47,H2<=$D$47),"ISLA",IF((AND(C2=$B$48,H2<=$D$48)),"ISLA",IF((AND(C2=$B$49,H2<=$D$49)),"ISLA","OSLA"))) -> ISLA
A3: 2 | B3: 1802F67855 | C3: P1 | D3: GNOC | E3: Roaming data | F3: 43132.726 | G3: 43133.427 | H3: 1010 | I3: Probable dysfonctionnement du service data Roaming | J3: Indisponibilité du Serveur eDNS de sonfonia | K3: Redémarrage du Serveur | L3: GNOC | M3: Clos | O3: =IF(AND(C3=$B$47,H3<=$D$47),"ISLA",IF((AND(C3=$B$48,H3<=$D$48)),"ISLA",IF((AND(C3=$B$49,H3<=$D$49)),"ISLA","OSLA"))) -> OSLA
A4: 3 | B4: 1802G21518 | C4: P2 | D4: Supervision | E4: Webtop | F4: 43135.911 | G4: 43136.017 | H4: 153 | I4: Indisponibilité de la page Webtop | J4: Débordement régulier du filesystem suite à l'augmentation du trafic et donc du volume journalier de log. | K4: Réduction en moitié la consommation de log en supprimant le logging du champ User-Agent | L4: GOS | M4: Clos | O4: =IF(AND(C4=$B$47,H4<=$D$47),"ISLA",IF((AND(C4=$B$48,H4<=$D$48)),"ISLA",IF((AND(C4=$B$49,H4<=$D$49)),"ISLA","OSLA"))) -> ISLA
A5: 4 | B5: 1802G53210 | C5: P1 | D5: SSPO | E5: Orange Money add-on / Bank to Wallet / Ecobank | F5: 43137.038 | G5: 43137.066 | H5: 40 | I5: Impossible d'effectuer des transactions bancaires via OM | J5: Perte de connexion avec le partenaire Ecobank | K5: Retablissement de la connexion | L5: SSPO | M5: Clos | O5: =IF(AND(C5=$B$47,H5<=$D$47),"ISLA",IF((AND(C5=$B$48,H5<=$D$48)),"ISLA",IF((AND(C5=$B$49,H5<=$D$49)),"ISLA","OSLA"))) -> ISLA
A6: 5 | B6: 1802G55044 | C6: P1 | D6: GOS | E6: Otap | F6: 43137.273 | G6: 43137.308 | H6: 51 | I6: Non détection de nouveaux abonnés et non envoie des settings | J6: Arrêt du serveur de transfert de fichier (Axway) | K6: Redemarage du serveur Axway | L6: GOS | M6: Clos | O6: =IF(AND(C6=$B$47,H6<=$D$47),"ISLA",IF((AND(C6=$B$48,H6<=$D$48)),"ISLA",IF((AND(C6=$B$49,H6<=$D$49)),"ISLA","OSLA"))) -> ISLA
A7: 6 | B7: 1802G59297 | C7: P2 | D7: GOS | E7: MyOrange, megawin, agrobusiness, facebook ussd, otap, gameloft, cms, smsapi | F7: 43137.378 | G7: 43137.654 | H7: 397 | I7: Dégradations des services au-dessus du SDP | J7: Instabilité sur la machine virtuelle(VM) du module ESB NUMERO 3 du SDP | K7: Migration de la VM ‘’opsdpgosesbcl03’’ d’un ESXi à un autre moins sollicité et changement du DataStore | L7: GOS | M7: Clos | O7: =IF(AND(C7=$B$47,H7<=$D$47),"ISLA",IF((AND(C7=$B$48,H7<=$D$48)),"ISLA",IF((AND(C7=$B$49,H7<=$D$49)),"ISLA","OSLA"))) -> OSLA
A8: 7 | B8: 1802G83087 | C8: P1 | D8: Supervision | E8: Facebook_USSD | F8: 43138.454 | G8: 43138.503 | H8: 70 | I8: Impossibilité pour les clients de souscrire au service | J8: Surcharge de capacité au niveau du gestionnaire de souscriptions | K8: Augmentation de la capacité du gestionnaire de souscriptions | L8: Myriad | M8: Clos | O8: =IF(AND(C8=$B$47,H8<=$D$47),"ISLA",IF((AND(C8=$B$48,H8<=$D$48)),"ISLA",IF((AND(C8=$B$49,H8<=$D$49)),"ISLA","OSLA"))) -> ISLA
A9: 8 | B9: 1802H38701 | C9: P1 | D9: SSPO | E9: Orange Money add-on / Bank to Wallet / Ecobank | F9: 43139.774 | G9: 43139.804 | H9: 44 | I9: Impossible d'effectuer des transactions bancaires via OM | J9: Perte de connexion avec le partenaire Ecobank | K9: Retablissement de la connexion | L9: SSPO | M9: Clos | O9: =IF(AND(C9=$B$47,H9<=$D$47),"ISLA",IF((AND(C9=$B$48,H9<=$D$48)),"ISLA",IF((AND(C9=$B$49,H9<=$D$49)),"ISLA","OSLA"))) -> ISLA
A10: 9 | B10: 1802H67539 | C10: P1 | D10: Supervision | E10: E-recharge | F10: 43140.85 | G10: 43140.936 | H10: 124 | I10: Echec élevé des transactions E-recharge/IN (20%) | J10: seuil de connexion petit par rapport à la demande | K10: Aucune action faite | L10: GNOC | M10: Clos | O10: =IF(AND(C10=$B$47,H10<=$D$47),"ISLA",IF((AND(C10=$B$48,H10<=$D$48)),"ISLA",IF((AND(C10=$B$49,H10<=$D$49)),"ISLA","OSLA"))) -> OSLA
A11: 10 | B11: 1802H67849 | C11: P1 | D11: Supervision | E11: Consultation de solde data (*222*5#) | F11: 43140.844 | G11: 43140.917 | H11: 105 | I11: Impossibilité de consulté son solde data via le code USSD *222*5# | J11: Plantage du serveur glassfish | K11: Redémarrage du Serveur | L11: ASBD | M11: Clos | O11: =IF(AND(C11=$B$47,H11<=$D$47),"ISLA",IF((AND(C11=$B$48,H11<=$D$48)),"ISLA",IF((AND(C11=$B$49,H11<=$D$49)),"ISLA","OSLA"))) -> ISLA
A12: 11 | B12: 1802I61948 | C12: P1 | D12: Supervision | E12: Orange Money | F12: 43145.476 | G12: 43145.479 | H12: 5 | I12: Indisponibilité de tous les services Orange Money | J12: Problème sur l’interface EJET du réseaux GIN | K12: Investigation en cours | L12: SSPO | M12: Clos | O12: =IF(AND(C12=$B$47,H12<=$D$47),"ISLA",IF((AND(C12=$B$48,H12<=$D$48)),"ISLA",IF((AND(C12=$B$49,H12<=$D$49)),"ISLA","OSLA"))) -> ISLA
A13: 12 | B13: 1802I71797 | C13: P1 | D13: Supervision | E13: OTAP | F13: 43145.69 | G13: 43145.869 | H13: 258 | I13: Impossible d’envoyer des messages de configuration aux abonnés | J13: Problème sur le server de file d’attente(les files d'attente n'étaient pas traitées avec succès) | K13: Redémarrages du serveur de file d’attente | L13: GOS | M13: Clos | O13: =IF(AND(C13=$B$47,H13<=$D$47),"ISLA",IF((AND(C13=$B$48,H13<=$D$48)),"ISLA",IF((AND(C13=$B$49,H13<=$D$49)),"ISLA","OSLA"))) -> OSLA
... A29: 28 | B29: --- | C29: P1 | D29: SONATEL | E29: Internet LAN, tango, right Q, simplissimo | F29: 43159.419 | G29: 43159.634 | H29: 310 | I29: Lenteur Instabilités sur toutes les applications passant par internet Perte de supervision par intermittence via les robots daset | J29: Perte d’un des proxy et l’autre est actuellement surchargé | K29: Restauration du proxy | L29: SONATEL | M29: Clos | O29: =IF(AND(C29=$B$47,H29<=$D$47),"ISLA",IF((AND(C29=$B$48,H29<=$D$48)),"ISLA",IF((AND(C29=$B$49,H29<=$D$49)),"ISLA","OSLA"))) -> OSLA
B47: P1 | C47: 2h | D47: 120
B48: P2 | C48: 4h | D48: 240
B49: P3 | C49: 2jr | D49: =1440*2 -> 2880
B50: P4 | C50: 3jr | D50: =3*1440 -> 4320

Sheet Mars_2018
A1: N° | B1: N°ticket | C1: Priorité | D1: Origine | E1: Nom Service | F1: Date & heure de début | G1: Date & heure de fin | H1: Durée (mn) | I1: Description | J1: Cause de l'incident | K1: Actions correctives | L1: TMC | M1: Statut | N1: Observation | O1: SLA
A2: 1 | B2: 1803M11844 | C2: P1 | D2: Supervision | E2: OTAP | F2: 43160.216 | G2: 43160.374 | H2: 227 | I2: indisponibilté OTAP, report avantage | J2: Plantage du RabbitMQ dû à une partition pleine sur le /var du serveur ADC | K2: Redémarrage du RabbitMQ | L2: GOS | M2: Clos | O2: =IF(AND(C2=$B$47,H2<=$D$47),"ISLA",IF((AND(C2=$B$48,H2<=$D$48)),"ISLA",IF((AND(C2=$B$49,H2<=$D$49)),"ISLA","OSLA"))) -> OSLA
A3: 2 | B3: 1803M17585 | C3: P2 | D3: Supervision | E3: Lenteur sur l'internet | F3: 43160.376 | G3: 43160.671 | H3: 424 | I3: Internet via le LAN, Tango, Right Q, KMC,Robot daset, Oceane, | J3: Perte d’un des proxy et l’autre est actuellement surchargé | K3: Restauration du proxy | L3: SONATEL | M3: Clos | O3: =IF(AND(C3=$B$47,H3<=$D$47),"ISLA",IF((AND(C3=$B$48,H3<=$D$48)),"ISLA",IF((AND(C3=$B$49,H3<=$D$49)),"ISLA","OSLA"))) -> OSLA
A4: 3 | B4: 1803M27052 | C4: P1 | D4: Supervision | E4: Kaabu | F4: 43160.576 | G4: 43161.379 | H4: 1156 | I4: inidsponibilité du service Kaabu | J4: Inconnue | K4: Aucune | L4: OML | M4: Clos | O4: =IF(AND(C4=$B$47,H4<=$D$47),"ISLA",IF((AND(C4=$B$48,H4<=$D$48)),"ISLA",IF((AND(C4=$B$49,H4<=$D$49)),"ISLA","OSLA"))) -> OSLA
A5: 4 | B5: 1803M37387 | C5: P1 | D5: SSPO | E5: Orange Money add-on / Bank to Wallet / Ecobank | F5: 43160.802 | G5: 43160.915 | H5: 162 | I5: Impossibilité d'effectuer des transactions bancaire via Orange Money | J5: Perte de connexion avec le partenaire Ecobank | K5: Rétablissement de la connexion | L5: SSPO | M5: Clos | O5: =IF(AND(C5=$B$47,H5<=$D$47),"ISLA",IF((AND(C5=$B$48,H5<=$D$48)),"ISLA",IF((AND(C5=$B$49,H5<=$D$49)),"ISLA","OSLA"))) -> OSLA
A6: 5 | B6: 1803M43264 | C6: P1 | D6: SSPO | E6: Orange Money add-on / Bank to Wallet / Ecobank | F6: 43161.306 | G6: 43161.357 | H6: 74 | I6: Impossibilité d'effectuer des transactions bancaire via Orange Money | J6: Perte de connexion avec le partenaire Ecobank | K6: retablissement de la connexion avec le partenaire ECOBANK | L6: SSPO | M6: Clos | O6: =IF(AND(C6=$B$47,H6<=$D$47),"ISLA",IF((AND(C6=$B$48,H6<=$D$48)),"ISLA",IF((AND(C6=$B$49,H6<=$D$49)),"ISLA","OSLA"))) -> ISLA
A7: 6 | B7: 1803M81364 | C7: P1 | D7: Supervision | E7: E-recharge | F7: 43162.674 | G7: 43162.778 | H7: 150 | I7: Echecs des transactions E-recharge | J7: Les sessions du pare-feu (Firewall) IN ZTE étaient surchargées, de sorte que les nouvelles attributions de sessions échouaient | K7: Redémarrage du firewall et suppression manuelle | L7: SSPO | M7: Clos | O7: =IF(AND(C7=$B$47,H7<=$D$47),"ISLA",IF((AND(C7=$B$48,H7<=$D$48)),"ISLA",IF((AND(C7=$B$49,H7<=$D$49)),"ISLA","OSLA"))) -> OSLA
A8: 7 | B8: 1803M81797 | C8: P1 | D8: Supervision | E8: Consultation de solde data (*222*5#) | F8: 43162.673 | G8: 43162.743 | H8: 101 | I8: Impossibilité de consulter le solde data via USSD (*222*5#) | J8: Plantage du serveur glassfish | K8: Redémarrage du serveur | L8: ASBD | M8: Clos | O8: =IF(AND(C8=$B$47,H8<=$D$47),"ISLA",IF((AND(C8=$B$48,H8<=$D$48)),"ISLA",IF((AND(C8=$B$49,H8<=$D$49)),"ISLA","OSLA"))) -> ISLA
A9: 8 | B9: 1803M82159 | C9: P2 | D9: SSPO | E9: MyOrange/Orange et Moi | F9: 43162.733 | G9: 43162.767 | H9: 49 | I9: Echec de 50% des opérations de consultation de solde via l'application | J9: meme cause que l'incident N°4. Les sessions du pare-feu (Firewall) IN ZTE étaient surchargées, de sorte que les nouvelles attributions de sessions échouaient | K9: Redémarrage du firewall et suppression manuelle | L9: SSPO | M9: Clos | O9: =IF(AND(C9=$B$47,H9<=$D$47),"ISLA",IF((AND(C9=$B$48,H9<=$D$48)),"ISLA",IF((AND(C9=$B$49,H9<=$D$49)),"ISLA","OSLA"))) -> ISLA
A10: 9 | B10: 1803M89735 | C10: P1 | D10: SSPO | E10: Orange Money add-on / canal + | F10: 43163.443 | G10: 43164.012 | H10: 820 | I10: Impossible de renouveler les abonnements canal + via OM | J10: congestion "table size" de la base de donnée | K10: extension "table size" de la base de donnée | L10: SSPO | M10: Clos | O10: =IF(AND(C10=$B$47,H10<=$D$47),"ISLA",IF((AND(C10=$B$48,H10<=$D$48)),"ISLA",IF((AND(C10=$B$49,H10<=$D$49)),"ISLA","OSLA"))) -> OSLA
A11: 10 | B11: 1803O13726 | C11: P1 | D11: Supervision | E11: CMS | F11: 43164.5 | G11: 43164.576 | H11: 109 | I11: Non réception du contenu après souscription (*111# ou 8036) au service | J11: Nombre de TPS configuré atteint ce qui a créé une file d’attente | K11: Aucune | L11: GOS | M11: Clos | O11: =IF(AND(C11=$B$47,H11<=$D$47),"ISLA",IF((AND(C11=$B$48,H11<=$D$48)),"ISLA",IF((AND(C11=$B$49,H11<=$D$49)),"ISLA","OSLA"))) -> ISLA
A12: 11 | B12: 1803N17551 | C12: P2 | D12: Supervision | E12: Nomad | F12: 43164.616 | G12: 43164.696 | H12: 115 | I12: Impossible de valider les contrats | J12: Remplissage de la partition /var du serveur d’application à 100%. | K12: Purge de la partition /var du serveur d’application | L12: GOS | M12: Clos | O12: =IF(AND(C12=$B$47,H12<=$D$47),"ISLA",IF((AND(C12=$B$48,H12<=$D$48)),"ISLA",IF((AND(C12=$B$49,H12<=$D$49)),"ISLA","OSLA"))) -> ISLA
A13: 12 | B13: 1803N23237 | C13: P1 | D13: SSPO | E13: Orange Money add-on / Bank to Wallet / Ecobank | F13: 43164.722 | G13: 43164.76 | H13: 55 | I13: Impossibilité d'effectuer des transactions bancaire via Orange Money | J13: Perte de connexion avec le partenaire Ecobank | K13: retablissement de la connexion avec le partenaire ECOBANK | L13: SSPO | M13: Clos | O13: =IF(AND(C13=$B$47,H13<=$D$47),"ISLA",IF((AND(C13=$B$48,H13<=$D$48)),"ISLA",IF((AND(C13=$B$49,H13<=$D$49)),"ISLA","OSLA"))) -> ISLA
... A41: 40 | B41: 1803T56563 | C41: P2 | D41: Supervision | E41: Data mobile | F41: 43190.84 | G41: 43190.882 | H41: 60 | I41: Baisse du trafic sur les deux STM16 de la Sonatel | J41: Inconnue | K41: Aucune | L41: GNOC | M41: Clos | O41: =IF(AND(C41=$B$47,H41<=$D$47),"ISLA",IF((AND(C41=$B$48,H41<=$D$48)),"ISLA",IF((AND(C41=$B$49,H41<=$D$49)),"ISLA","OSLA"))) -> ISLA
B47: P1 | C47: 2h | D47: 120
B48: P2 | C48: 4h | D48: 240
B49: P3 | C49: 2jr | D49: =1440*2 -> 2880
B50: P4 | C50: 3jr | D50: =3*1440 -> 4320

Sheet Avril_2018
A1: N° | B1: N°ticket | C1: Priorité | D1: Origine | E1: Nom Service | F1: Date & heure de début | G1: Date & heure de fin | H1: Durée (mn) | I1: Description | J1: Cause de l'incident | K1: Actions correctives | L1: TMC | M1: Statut | N1: Observation | O1: SLA
A2: 1 | B2: 1804U07005/1804U07552 | C2: P2 | D2: SSPO | E2: E-recharge | F2: 43193.86 | G2: 43193.924 | H2: 92 | I2: Echec des transactions E-recharge | J2: Problème de disque dur sur L'ocs5 | K2: Service rétabli sans action / Action éffectué après (Basculement du service sur OCS6 et redemarage de OCS5) | L2: GNOC | M2: Clos | O2: =IF(AND(C2=$B$47,H2<=$D$47),"ISLA",IF((AND(C2=$B$48,H2<=$D$48)),"ISLA",IF((AND(C2=$B$49,H2<=$D$49)),"ISLA","OSLA"))) -> ISLA
A3: 2 | B3: 1804U28648 | C3: P1 | D3: SSPO | E3: Orange Money add-on / Bank to Wallet / Ecobank | F3: 43194.574 | G3: 43194.614 | H3: 58 | I3: Impossible d’effectuer des transactions bancaires via OM | J3: Perte de connexion avec le partenaire Ecobank | K3: Rétablissement de la connexion avec le partenaire | L3: SSPO | M3: Clos | O3: =IF(AND(C3=$B$47,H3<=$D$47),"ISLA",IF((AND(C3=$B$48,H3<=$D$48)),"ISLA",IF((AND(C3=$B$49,H3<=$D$49)),"ISLA","OSLA"))) -> ISLA
A4: 3 | B4: 1804U37282 | C4: P3 | D4: Supervision | E4: Orange Money | F4: 43194.823 | G4: 43194.938 | H4: 165 | I4: Instabilités des services | J4: Echecs des requetes push USSD avec le code HTTP 408 | K4: Aucune | L4: GNOC | M4: Clos | O4: =IF(AND(C4=$B$47,H4<=$D$47),"ISLA",IF((AND(C4=$B$48,H4<=$D$48)),"ISLA",IF((AND(C4=$B$49,H4<=$D$49)),"ISLA","OSLA"))) -> ISLA
A5: 4 | B5: 1804U55095 | C5: P1 | D5: Supervision | E5: Facebook_USSD | F5: 43195.501 | G5: 43195.536 | H5: 51 | I5: Impossible d’accéder au menu *444# | J5: Probleme de connectivité entre le MS et les Cellgate de Myriad | K5: Aucune | L5: Myriad | M5: Clos | O5: =IF(AND(C5=$B$47,H5<=$D$47),"ISLA",IF((AND(C5=$B$48,H5<=$D$48)),"ISLA",IF((AND(C5=$B$49,H5<=$D$49)),"ISLA","OSLA"))) -> ISLA
A6: 5 | B6: 1804U63093 | C6: P1 | D6: Supervision | E6: Orange Money | F6: 43195.67 | G6: 43195.701 | H6: 45 | I6: Indisponibilité Orange Money | J6: Indisponibilité Orange infa ( les actions de troubleshooting (redemarrage du firewall) ont impactées OM) / Suppression de ports 1-2 et 9-10 dans la mise à jour du vlan 1100 dans le cadre des configurations des nouvelles lames qui est chargé du management du HA | K6: Service rétabli après redemarrage du FW / Action éffectué après (Correction du vlan 1100 avec ajout des ports 1-2 , 5-10 et 15-16) | L6: ASBD/GOS | M6: Clos | O6: =IF(AND(C6=$B$47,H6<=$D$47),"ISLA",IF((AND(C6=$B$48,H6<=$D$48)),"ISLA",IF((AND(C6=$B$49,H6<=$D$49)),"ISLA","OSLA"))) -> ISLA
A7: 6 | B7: 1804U97805 | C7: P2 | D7: SSPO | E7: E-recharge | F7: 43197.333 | G7: 43197.481 | H7: 212 | I7: Echec des rechargements via OM (Achat de credit) | J7: Non rechargement du compte tango | K7: Rechargement du compte tango | L7: OGN | M7: Clos | O7: =IF(AND(C7=$B$47,H7<=$D$47),"ISLA",IF((AND(C7=$B$48,H7<=$D$48)),"ISLA",IF((AND(C7=$B$49,H7<=$D$49)),"ISLA","OSLA"))) -> ISLA
A8: 7 | B8: 18004V33104 | C8: P1 | D8: Supervision | E8: SMS_API | F8: 43199.515 | G8: 43199.566 | H8: 73 | I8: Echec d’activation du service | J8: Inconnue | K8: Aucune | L8: GOS | M8: Clos | O8: =IF(AND(C8=$B$47,H8<=$D$47),"ISLA",IF((AND(C8=$B$48,H8<=$D$48)),"ISLA",IF((AND(C8=$B$49,H8<=$D$49)),"ISLA","OSLA"))) -> ISLA
A9: 8 | B9: 1804V44000 | C9: P1 | D9: Supervision | E9: Nomad | F9: 43199.729 | G9: 43200.615 | H9: 1275 | I9: Impossibilité d'importer des contrats et pieces d'identité | J9: Inconnue | K9: Aucune | L9: GOS | M9: Clos | O9: =IF(AND(C9=$B$47,H9<=$D$47),"ISLA",IF((AND(C9=$B$48,H9<=$D$48)),"ISLA",IF((AND(C9=$B$49,H9<=$D$49)),"ISLA","OSLA"))) -> OSLA
A10: 9 | B10: 1804V63292 | C10: P2 | D10: Supervision | E10: Orange Money | F10: 43200.508 | G10: 43200.511 | H10: 5 | I10: Indisponibilité Orange Money | J10: Problèmes de réseau entre les serveurs USSD et Revers Proxy | K10: Aucune | L10: SSPO | M10: Clos | O10: =IF(AND(C10=$B$47,H10<=$D$47),"ISLA",IF((AND(C10=$B$48,H10<=$D$48)),"ISLA",IF((AND(C10=$B$49,H10<=$D$49)),"ISLA","OSLA"))) -> ISLA
A11: 10 | B11: 1804W83161 | C11: P2 | D11: SONATEL | E11: Messagerie electronique | F11: 43200.417 | G11: 43200.458 | H11: 60 | I11: Lenteur sur la messagerie | J11: Une base exchange ne delivre pas convenablement les mails | K11: Synchronisation des bases | L11: SONATEL | M11: Clos | O11: =IF(AND(C11=$B$47,H11<=$D$47),"ISLA",IF((AND(C11=$B$48,H11<=$D$48)),"ISLA",IF((AND(C11=$B$49,H11<=$D$49)),"ISLA","OSLA"))) -> ISLA
A12: 11 | B12: 1804V77306 | C12: P1 | D12: SSPO | E12: Orange Money add-on / Bank to Wallet / Ecobank | F12: 43201.018 | G12: 43201.058 | H12: 58 | I12: Impossible d’effectuer des transactions bancaires via OM | J12: Perte de connexion avec le partenaire Ecobank | K12: Rétablissement de la connexion avec le partenaire | L12: SSPO | M12: Clos | O12: =IF(AND(C12=$B$47,H12<=$D$47),"ISLA",IF((AND(C12=$B$48,H12<=$D$48)),"ISLA",IF((AND(C12=$B$49,H12<=$D$49)),"ISLA","OSLA"))) -> ISLA
A13: 12 | B13: 1804W04453 | C13: P1 | D13: Supervision | E13: Data mobile,CMS,gameloft,Otap,Sms_API | F13: 43201.816 | G13: 43202.547 | H13: 1052 | I13: Perte de trafic entre Kipe-Sonfonia | J13: Coupure de la fibre | K13: Soudure de la fibre | L13: GNOC | M13: Clos | O13: =IF(AND(C13=$B$47,H13<=$D$47),"ISLA",IF((AND(C13=$B$48,H13<=$D$48)),"ISLA",IF((AND(C13=$B$49,H13<=$D$49)),"ISLA","OSLA"))) -> OSLA
... A44: 44 | B44: 1804A38394 | C44: P1 | D44: SSPO | E44: Orange Money add-on / Bank to Wallet / Ecobank | F44: 43220.605 | G44: 43220.646 | H44: 59 | I44: Impossible d’effectuer des transactions bancaires via OM | J44: Perte de connexion avec le partenaire Ecobank | K44: Rétablissement de la connexion avec le partenaire | L44: SSPO | M44: Clos | O44: =IF(AND(C44=$B$47,H44<=$D$47),"ISLA",IF((AND(C44=$B$48,H44<=$D$48)),"ISLA",IF((AND(C44=$B$49,H44<=$D$49)),"ISLA","OSLA"))) -> ISLA
B47: P1 | C47: 2h | D47: 120
B48: P2 | C48: 4h | D48: 240
B49: P3 | C49: 2jr | D49: =1440*2 -> 2880
B50: P4 | C50: 3jr | D50: =3*1440 -> 4320

Sheet Mai_2018
A1: N° | B1: N°ticket | C1: Priorité | D1: Origine | E1: Nom Service | F1: Date & heure de début | G1: Date & heure de fin | H1: Durée (mn) | I1: Description | J1: Cause de l'incident | K1: Actions correctives | L1: TMC | M1: Statut | N1: Observation | O1: SLA
A2: 1 | B2: 1805A68580/1805A68841 | C2: P1 | D2: Supervision | E2: E-recharge | F2: 43222.447 | G2: 43222.5 | H2: 76 | I2: Echec de 15% des transactions E-recharge | J2: Inconnue | K2: Aucune | L2: GNOC | M2: Clos | O2: =IF(AND(C2=$B$47,H2<=$D$47),"ISLA",IF((AND(C2=$B$48,H2<=$D$48)),"ISLA",IF((AND(C2=$B$49,H2<=$D$49)),"ISLA","OSLA"))) -> ISLA
A3: 2 | B3: 1805A80476 | C3: P1 | D3: SSPO | E3: Orange Money add-on / Bank to wallet / Ecobank | F3: 43222.691 | G3: 43222.719 | H3: 40 | I3: Impossible d’effectuer des transactions bancaires via OM | J3: Perte de connexion avec le partenaire Ecobank | K3: Rétablissement de la connexion | L3: SSPO | M3: Clos | O3: =IF(AND(C3=$B$47,H3<=$D$47),"ISLA",IF((AND(C3=$B$48,H3<=$D$48)),"ISLA",IF((AND(C3=$B$49,H3<=$D$49)),"ISLA","OSLA"))) -> ISLA
A4: 3 | B4: 1805B12326 | C4: P1 | D4: SSPO | E4: Orange Money add-on / Bank to wallet / Ecobank | F4: 43223.945 | G4: 43223.978 | H4: 48 | I4: Impossible d’effectuer des transactions bancaires via OM | J4: Perte de connexion avec le partenaire Ecobank | K4: Rétablissement de la connexion | L4: SSPO | M4: Clos | O4: =IF(AND(C4=$B$47,H4<=$D$47),"ISLA",IF((AND(C4=$B$48,H4<=$D$48)),"ISLA",IF((AND(C4=$B$49,H4<=$D$49)),"ISLA","OSLA"))) -> ISLA
A5: 4 | B5: 1805B56426 | C5: P1 | D5: Supervision | E5: Navigations internet,Robot Daset,Lien Tango | F5: 43224.355 | G5: 43224.476 | H5: 174 | I5: Lenteurs sur Internet | J5: Perte d'un Proxy | K5: Mise en service de l'un des anciens proxy | L5: SONATEL | M5: Clos | O5: =IF(AND(C5=$B$47,H5<=$D$47),"ISLA",IF((AND(C5=$B$48,H5<=$D$48)),"ISLA",IF((AND(C5=$B$49,H5<=$D$49)),"ISLA","OSLA"))) -> OSLA
A6: 5 | B6: 1805B27734 | C6: P1 | D6: Supervision | E6: CMS,Otap,Gameloft,Agrobusiness,Sms_Api,Vpn IS,Facebook_USSD_Report_avantage | F6: 43224.386 | G6: 43224.993 | H6: 874 | I6: Coupure du circuit CON-DAK_1S/0004 | J6: En attente du retour de RAFIA | K6: En attente du rapport d’incident | L6: SONATEL | M6: Clos | O6: =IF(AND(C6=$B$47,H6<=$D$47),"ISLA",IF((AND(C6=$B$48,H6<=$D$48)),"ISLA",IF((AND(C6=$B$49,H6<=$D$49)),"ISLA","OSLA"))) -> OSLA
A7: 6 | B7: 1805B37008 | C7: P1 | D7: Supervision | E7: E-recharge | F7: 43224.816 | G7: 43224.882 | H7: 95 | I7: Echec de 13,46% des transactions E-recharge | J7: En attente du retour de GNOC | K7: En attente du rapport d’incident | L7: GNOC | M7: Clos | O7: =IF(AND(C7=$B$47,H7<=$D$47),"ISLA",IF((AND(C7=$B$48,H7<=$D$48)),"ISLA",IF((AND(C7=$B$49,H7<=$D$49)),"ISLA","OSLA"))) -> ISLA
A8: 7 | B8: 1805B36863 | C8: P2 | D8: SSPO | E8: E-recharge | F8: 43224.83 | G8: 43225.597 | H8: 1105 | I8: Echec de 12% des rechargements via OM (Achat de credit) | J8: Non rechargement du compte tango | K8: Rechargement du compte et réinitialisation du comteur dans la base de donnée | L8: SSPO | M8: Clos | O8: =IF(AND(C8=$B$47,H8<=$D$47),"ISLA",IF((AND(C8=$B$48,H8<=$D$48)),"ISLA",IF((AND(C8=$B$49,H8<=$D$49)),"ISLA","OSLA"))) -> OSLA
A9: 8 | B9: 1805B66647 | C9: P1 | D9: SSPO | E9: Orange Money add-on / Bank to wallet / Ecobank | F9: 43227.379 | G9: 43227.416 | H9: 53 | I9: Impossible d’effectuer des transactions bancaires via OM | J9: Perte de connexion avec le partenaire Ecobank | K9: Rétablissement de la connexion avec le partenaire | L9: SSPO | M9: Clos | O9: =IF(AND(C9=$B$47,H9<=$D$47),"ISLA",IF((AND(C9=$B$48,H9<=$D$48)),"ISLA",IF((AND(C9=$B$49,H9<=$D$49)),"ISLA","OSLA"))) -> ISLA
A10: 9 | B10: 1805C48606 | C10: P1 | D10: SSPO | E10: Orange Money add-on / Canal + | F10: 43230.917 | G10: 43230.941 | H10: 35 | I10: Impossible d’effectuer des réabonnements canal via OM | J10: Perte des paramètres du noyau pour le transfert d'adresse IP suite à ATP de OpenWatt ( redemarrage du VPN ) | K10: Reconfiguration du noyau | L10: SSPO | M10: Clos | O10: =IF(AND(C10=$B$47,H10<=$D$47),"ISLA",IF((AND(C10=$B$48,H10<=$D$48)),"ISLA",IF((AND(C10=$B$49,H10<=$D$49)),"ISLA","OSLA"))) -> ISLA
A11: 10 | B11: 1805C51721 | C11: P1 | D11: SSPO | E11: Orange Money add-on / Bank to wallet / Ecobank | F11: 43231.262 | G11: 43231.306 | H11: 63 | I11: Impossible d’effectuer des transactions bancaires via OM | J11: Perte de connexion avec le partenaire Ecobank | K11: Rétablissement de la connexion avec le partenaire | L11: SSPO | M11: Clos | O11: =IF(AND(C11=$B$47,H11<=$D$47),"ISLA",IF((AND(C11=$B$48,H11<=$D$48)),"ISLA",IF((AND(C11=$B$49,H11<=$D$49)),"ISLA","OSLA"))) -> ISLA
A12: 11 | B12: 1805C59123 | C12: P1 | D12: Supervision | E12: Report-Avantage | F12: 43231.372 | G12: 43231.44 | H12: 98 | I12: Impossible de recevoir ses avantages à partir de *118*1# | J12: Plantage du serveur Glassfish | K12: Redemarrage du serveur | L12: ASBD | M12: Clos | O12: =IF(AND(C12=$B$47,H12<=$D$47),"ISLA",IF((AND(C12=$B$48,H12<=$D$48)),"ISLA",IF((AND(C12=$B$49,H12<=$D$49)),"ISLA","OSLA"))) -> ISLA
A13: 12 | B13: 1805C67456 | C13: P2 | D13: SONATEL | E13: Les applications passant par Internet ne sont pas disponibles (CRM, PRETUPS, NOMAD, TANGO, SUPERVISION DASET), | F13: 43231.374 | G13: 43231.4 | H13: 38 | I13: Lenteurs sur Internet | J13: Perte d'un Proxy | K13: Restauration du proxy | L13: SONATEL | M13: Clos | O13: =IF(AND(C13=$B$47,H13<=$D$47),"ISLA",IF((AND(C13=$B$48,H13<=$D$48)),"ISLA",IF((AND(C13=$B$49,H13<=$D$49)),"ISLA","OSLA"))) -> ISLA
... A30: 29 | B30: 1805H36601 | C30: P1 | D30: SSPO | E30: Orange Money add-on / Bank to wallet / Ecobank | F30: 43251.402 | G30: 43251.438 | H30: 52 | I30: Impossible d’effectuer des transactions bancaires via OM | J30: Perte de connexion avec le partenaire Ecobank | K30: Rétablissement de la connexion | L30: SSPO | M30: Clos | O30: =IF(AND(C30=$B$47,H30<=$D$47),"ISLA",IF((AND(C30=$B$48,H30<=$D$48)),"ISLA",IF((AND(C30=$B$49,H30<=$D$49)),"ISLA","OSLA"))) -> ISLA
B47: P1 | C47: 2h | D47: 120
B48: P2 | C48: 4h | D48: 240
B49: P3 | C49: 2jr | D49: =1440*2 -> 2880
B50: P4 | C50: 3jr | D50: =3*1440 -> 4320

Sheet Juin_2018
A1: N° | B1: N°ticket | C1: Priorité | D1: Origine | E1: Nom Service | F1: Date & heure de début | G1: Date & heure de fin | H1: Durée (mn) | I1: Description | J1: Cause de l'incident | K1: Actions correctives | L1: TMC | M1: Statut | N1: Observation | O1: SLA
A2: 1 | B2: 1806I12109 | C2: P1 | D2: Supervision | E2: LAN, Internet, Right Q, Tango, supervision via robot, CIS, Simplissimo, messagerie | F2: 43252.38 | G2: 43252.583 | H2: 293 | I2: Dysfonctionnement sur le LAN. Perte des services navigation internet, Robot de supervision, Right Q, Tango, CIS, Simplissimo, Messagerie …. | J2: Perte d’un des proxy | K2: Restauration du proxy | L2: SONATEL | M2: Clos | O2: =IF(AND(C2=$B$47,H2<=$D$47),"ISLA",IF((AND(C2=$B$48,H2<=$D$48)),"ISLA",IF((AND(C2=$B$49,H2<=$D$49)),"ISLA","OSLA"))) -> OSLA
A3: 2 | B3: 1806H94694 | C3: P1 | D3: Supervision | E3: Sos-crédit/paie pour moi | F3: 43253.597 | G3: 43253.665 | H3: 97 | I3: Indisponibilité des services Sos crédit et paie pour moi | J3: Indisponibilité du serveur SMP SVR1 | K3: Basculement des services sur le second serveur SMP SVR2 et Restauration du serveur SMP SVR1 | L3: GNOC | M3: Clos | O3: =IF(AND(C3=$B$47,H3<=$D$47),"ISLA",IF((AND(C3=$B$48,H3<=$D$48)),"ISLA",IF((AND(C3=$B$49,H3<=$D$49)),"ISLA","OSLA"))) -> ISLA
A4: 3 | B4: 1806I12144 | C4: P1 | D4: Supervision | E4: Perturbation Réseau LAN | F4: 43253.701 | G4: 43254.388 | H4: 989 | I4: Navigation internet, Robot de supervision, Right Q, Tango, CIS, Simplissimo, …. | J4: perte d'un proxy | K4: Restauration du proxy | L4: SONATEL | M4: Clos | O4: =IF(AND(C4=$B$47,H4<=$D$47),"ISLA",IF((AND(C4=$B$48,H4<=$D$48)),"ISLA",IF((AND(C4=$B$49,H4<=$D$49)),"ISLA","OSLA"))) -> OSLA
A5: 4 | B5: 1806I08339 | C5: P1 | D5: SSPO | E5: E-recharge | F5: 43254.663 | G5: 43254.674 | H5: 16 | I5: Echec à 50% dans la réception des notifications après des transactions d’achat de crédit via E-Recharge | J5: Déconnexion entre ZEBRA et SMSC | K5: Aucune | L5: GNOC/SSPO | M5: Clos | N5: pour identifier la root cause et apporté une correction definitive, ce dysfonctionnement est traité en dans le ticket problème N°1806I34048 | O5: =IF(AND(C5=$B$47,H5<=$D$47),"ISLA",IF((AND(C5=$B$48,H5<=$D$48)),"ISLA",IF((AND(C5=$B$49,H5<=$D$49)),"ISLA","OSLA"))) -> ISLA
A6: 5 | B6: 1806I08339 | C6: P2 | D6: SSPO | E6: E-recharge | F6: 43254.699 | G6: 43254.735 | H6: 52 | I6: Echec à 50% dans la réception des notifications après des transactions d’achat de crédit via E-Recharge | J6: Déconnexion entre ZEBRA et SMSC | K6: Aucune | L6: GNOC/SSPO | M6: Clos | N6: pour identifier la root cause et apporté une correction definitive, ce dysfonctionnement est traité en dans le ticket problème N°1806I34048 | O6: =IF(AND(C6=$B$47,H6<=$D$47),"ISLA",IF((AND(C6=$B$48,H6<=$D$48)),"ISLA",IF((AND(C6=$B$49,H6<=$D$49)),"ISLA","OSLA"))) -> ISLA
A7: 6 | B7: 1806I09967 | C7: P1 | D7: SSPO | E7: Orange Money add-on / Bank to wallet / Ecobank | F7: 43254.792 | G7: 43254.812 | H7: 28 | I7: Impossible d’effectuer des transactions bancaires via OM | J7: Perte de connexion avec le partenaire Ecobank | K7: Rétablissement de la connexion | L7: SSPO | M7: Clos | O7: =IF(AND(C7=$B$47,H7<=$D$47),"ISLA",IF((AND(C7=$B$48,H7<=$D$48)),"ISLA",IF((AND(C7=$B$49,H7<=$D$49)),"ISLA","OSLA"))) -> ISLA
A8: 7 | B8: 1606I12492 | C8: P1 | D8: Supervision | E8: Sos-crédit/paie pour moi | F8: 43255.13 | G8: 43255.451 | H8: 463 | I8: Indisponibilité des services Sos crédit et paie pour moi | J8: Défaut de disque | K8: Correction de filesystem et Remplacement du disque | L8: GNOC | M8: Clos | O8: =IF(AND(C8=$B$47,H8<=$D$47),"ISLA",IF((AND(C8=$B$48,H8<=$D$48)),"ISLA",IF((AND(C8=$B$49,H8<=$D$49)),"ISLA","OSLA"))) -> OSLA
A9: 8 | B9: 1806I13598 | C9: P2 | D9: Supervision | E9: E-recharge | F9: 43255.24 | G9: 43255.416 | H9: 254 | I9: Echec de 4% des rechargements via OM (Achat de crédit) | J9: Non rechargement du compte tango | K9: Rechargement du compte tango | L9: SSPO | M9: Clos | O9: =IF(AND(C9=$B$47,H9<=$D$47),"ISLA",IF((AND(C9=$B$48,H9<=$D$48)),"ISLA",IF((AND(C9=$B$49,H9<=$D$49)),"ISLA","OSLA"))) -> OSLA
A10: 9 | B10: 1806I96235 | C10: P1 | D10: SSPO | E10: Orange Money add-on / Bank to wallet / Ecobank | F10: 43257.517 | G10: 43257.552 | H10: 50 | I10: Impossible d’effectuer des transactions bancaires via OM | J10: Perte de connexion avec le partenaire Ecobank | K10: Rétablissement de la connexion | L10: SSPO | M10: Clos | O10: =IF(AND(C10=$B$47,H10<=$D$47),"ISLA",IF((AND(C10=$B$48,H10<=$D$48)),"ISLA",IF((AND(C10=$B$49,H10<=$D$49)),"ISLA","OSLA"))) -> ISLA
A11: 10 | B11: 1806J11266 | C11: P1 | D11: Supervision | E11: Sos-crédit/paie pour moi | F11: 43258.153 | G11: 43258.875 | H11: 1040 | I11: Indisponibilité des services Sos crédit et paie pour moi | J11: Défaut du filesystem | K11: Correction du filesystem et Restauration de la Base de Données | L11: GNOC | M11: Clos | O11: =IF(AND(C11=$B$47,H11<=$D$47),"ISLA",IF((AND(C11=$B$48,H11<=$D$48)),"ISLA",IF((AND(C11=$B$49,H11<=$D$49)),"ISLA","OSLA"))) -> OSLA
A12: 11 | B12: 1806J41441 | C12: P1 | D12: SSPO | E12: Orange Money add-on / Bank to wallet / Ecobank | F12: 43258.908 | G12: 43258.947 | H12: 57 | I12: Impossible d’effectuer des transactions bancaires via OM | J12: Perte de connexion avec le partenaire Ecobank | K12: Rétablissement de la connexion | L12: SSPO | M12: Clos | O12: =IF(AND(C12=$B$47,H12<=$D$47),"ISLA",IF((AND(C12=$B$48,H12<=$D$48)),"ISLA",IF((AND(C12=$B$49,H12<=$D$49)),"ISLA","OSLA"))) -> ISLA
A13: 12 | B13: 1806J49631 | C13: P2 | D13: SSPO | E13: Orange Money add-on / Bank to wallet / Ecobank | F13: 43259.349 | G13: 43259.385 | H13: 52 | I13: Impossible d’effectuer des transactions bancaires via OM | J13: Perte de connexion avec le partenaire Ecobank | K13: Rétablissement de la connexion | L13: SSPO | M13: Clos | O13: =IF(AND(C13=$B$47,H13<=$D$47),"ISLA",IF((AND(C13=$B$48,H13<=$D$48)),"ISLA",IF((AND(C13=$B$49,H13<=$D$49)),"ISLA","OSLA"))) -> ISLA
A14: 13 | B14: 1806J71580 | C14: P1 | D14: GOS | E14: Nomad | F14: 43260.19 | G14: 43260.577 | H14: 557 | I14: Impossible de faire des acquisitions et de procéder à des identifications | J14: Erreur dans le déploiement du web service par OGN. En effet, le web service doit être déployé sur le port 83 mais pendant l’opération et au moment du roll back, il a été déployé sur le port 80 | K14: Reconfiguration du web service sur le port 83 par l’équipe OGN | L14: GOS | M14: Clos | O14: =IF(AND(C14=$B$47,H14<=$D$47),"ISLA",IF((AND(C14=$B$48,H14<=$D$48)),"ISLA",IF((AND(C14=$B$49,H14<=$D$49)),"ISLA","OSLA"))) -> OSLA
A15: 14 | B15: 1806J93458 | C15: P2 | D15: SSPO | E15: E-recharge | F15: 43261.419 | G15: 43261.772 | H15: 509 | I15: Echec à 50% dans la réception des notifications après des transactions d’achat de crédit via E-Recharge | J15: Déconnexion entre ZEBRA et SMSC | K15: Aucune | L15: GNOC/SSPO | M15: Clos | N15: pour identifier la root cause et apporté une correction definitive, ce dysfonctionnement est traité en dans le ticket problème N°1806I34048 | O15: =IF(AND(C15=$B$47,H15<=$D$47),"ISLA",IF((AND(C15=$B$48,H15<=$D$48)),"ISLA",IF((AND(C15=$B$49,H15<=$D$49)),"ISLA","OSLA"))) -> OSLA
A16: 15 | B16: 1806K22728 | C16: P1 | D16: Supervision | E16: Agrobusiness | F16: 43262.434 | G16: 43265.347 | H16: 4195 | I16: Indisponibilité du service Agrobusiness | J16: expiration de l'hebergement de la plateforme du fournisseur | K16: Renouvellement de l'hebergement | L16: Bankitech | M16: Clos | O16: =IF(AND(C16=$B$47,H16<=$D$47),"ISLA",IF((AND(C16=$B$48,H16<=$D$48)),"ISLA",IF((AND(C16=$B$49,H16<=$D$49)),"ISLA","OSLA"))) -> OSLA
A17: 16 | B17: 1806K22955 | C17: P2 | D17: Supervision | E17: Perturbation Réseau LAN | F17: 43262.462 | G17: 43262.559 | H17: 140 | I17: Indisponibilité de l’internet sur le LAN | J17: Perte du proxy de Médina | K17: Restauration de la machine virtuel MESVPROXYSG02 | L17: SONATEL | M17: Clos | O17: =IF(AND(C17=$B$47,H17<=$D$47),"ISLA",IF((AND(C17=$B$48,H17<=$D$48)),"ISLA",IF((AND(C17=$B$49,H17<=$D$49)),"ISLA","OSLA"))) -> ISLA
A18: 17 | B18: 1806K21800 | C18: P1 | D18: SSPO | E18: Orange Money add-on / Bank to wallet / Ecobank | F18: 43262.553 | G18: 43263.771 | H18: 1754 | I18: Impossible d’effectuer des transactions bancaires via OM | J18: Perte de connexion avec le partenaire Ecobank | K18: Retablissement de la connexion | L18: SSPO | M18: Clos | O18: =IF(AND(C18=$B$47,H18<=$D$47),"ISLA",IF((AND(C18=$B$48,H18<=$D$48)),"ISLA",IF((AND(C18=$B$49,H18<=$D$49)),"ISLA","OSLA"))) -> OSLA
A19: 18 | B19: 1006K50454 | C19: P1 | D19: Supervision | E19: Internet (LAN) | F19: 43263.461 | G19: 43263.476 | H19: 511 | I19: Instabilité de l’internet sur le LAN | J19: Perte du CE internet de Medina | K19: En attente du rapport d'incident | L19: SONATEL | M19: Clos | O19: =IF(AND(C19=$B$47,H19<=$D$47),"ISLA",IF((AND(C19=$B$48,H19<=$D$48)),"ISLA",IF((AND(C19=$B$49,H19<=$D$49)),"ISLA","OSLA"))) -> OSLA
A20: 19 | B20: 1806K67237 | C20: P1 | D20: SSPO | E20: Orange Money add-on / Bank to wallet / Ecobank | F20: 43264.089 | G20: 43264.124 | H20: 512 | I20: Impossible d’effectuer des transactions bancaires via OM | J20: Perte de connexion avec le partenaire Ecobank | K20: Retablissement de la connexion | L20: SSPO | M20: Clos | O20: =IF(AND(C20=$B$47,H20<=$D$47),"ISLA",IF((AND(C20=$B$48,H20<=$D$48)),"ISLA",IF((AND(C20=$B$49,H20<=$D$49)),"ISLA","OSLA"))) -> OSLA
A21: 20 | B21: 1806K79275 | C21: P1 | D21: GOS | E21: KMC | F21: 43264.424 | G21: 43264.492 | H21: 97 | I21: Indisponibilité du service KMC | J21: Problème d’inconsistance sur file système du serveur de base de données | K21: Le redémarrage de la base de données | L21: GOS | M21: Clos | O21: =IF(AND(C21=$B$47,H21<=$D$47),"ISLA",IF((AND(C21=$B$48,H21<=$D$48)),"ISLA",IF((AND(C21=$B$49,H21<=$D$49)),"ISLA","OSLA"))) -> ISLA
A22: 21 | B22: 1806K85037 | C22: P2 | D22: SSPO | E22: E-recharge | F22: 43264.532 | G22: 43264.666 | H22: 193 | I22: Echec à 50% dans la réception des notifications après des transactions d’achat de crédit via E-Recharge | J22: Déconnexion entre ZEBRA et SMSC | K22: Aucune | L22: GNOC/SSPO | M22: Clos | N22: pour identifier la root cause et apporté une correction definitive, ce dysfonctionnement est traité en dans le ticket problème N°1806I34048 | O22: =IF(AND(C22=$B$47,H22<=$D$47),"ISLA",IF((AND(C22=$B$48,H22<=$D$48)),"ISLA",IF((AND(C22=$B$49,H22<=$D$49)),"ISLA","OSLA"))) -> ISLA
A23: 22 | B23: 1806L12006 | C23: P2 | D23: Supervision | E23: Mobile TV | F23: 43265.042 | G23: 43275.638 | H23: 15259 | I23: Indisponibilité de la chaine West Africa | J23: problème de transcodage | K23: upgrade des mémoires | L23: ASBD/OLS | M23: Clos | O23: =IF(AND(C23=$B$47,H23<=$D$47),"ISLA",IF((AND(C23=$B$48,H23<=$D$48)),"ISLA",IF((AND(C23=$B$49,H23<=$D$49)),"ISLA","OSLA"))) -> OSLA
A24: 23 | B24: 1806L36795 | C24: P1 | D24: SSPO | E24: Orange Money add-on / Canal+ | F24: 43266.352 | G24: 43266.403 | H24: 74 | I24: Impossible d’effectuer des réabonnements Canal+ via OM | J24: Perte de la connectivité avec le VPN | K24: Restauration du vpn | L24: SSPO | M24: Clos | O24: =IF(AND(C24=$B$47,H24<=$D$47),"ISLA",IF((AND(C24=$B$48,H24<=$D$48)),"ISLA",IF((AND(C24=$B$49,H24<=$D$49)),"ISLA","OSLA"))) -> ISLA
A25: 24 | B25: 1806M04459 | C25: P1 | D25: Supervision | E25: Orange Money addon / Web Payment | F25: 43267.823 | G25: 43271.75 | H25: 5655 | I25: Impossible d’effectuer des payements en ligne via OM | J25: Le server d’application était chargé et il n’arrivait plus à traiter le nombre de requêtes | K25: réinstallation du server d’applications | L25: SSPO | M25: Clos | O25: =IF(AND(C25=$B$47,H25<=$D$47),"ISLA",IF((AND(C25=$B$48,H25<=$D$48)),"ISLA",IF((AND(C25=$B$49,H25<=$D$49)),"ISLA","OSLA"))) -> OSLA
A26: 25 | B26: 1806L73130 | C26: P1 | D26: Supervision | E26: VOIX, DATA, E-Recharge, SMS | F26: 43268.531 | G26: 43268.58 | H26: 70 | I26: Indisponibilité des services voix, data, sms et E-recharge pour certains PQ (622 et 627) | J26: Indisponibilité du serveur OCS2 et de l’OCS1 dû au non réplication de données entre les deux noeuds | K26: Arrêt des process de réplication entre les deux nœud et remise en service de l'OCS2 | L26: GNOC | M26: Clos | O26: =IF(AND(C26=$B$47,H26<=$D$47),"ISLA",IF((AND(C26=$B$48,H26<=$D$48)),"ISLA",IF((AND(C26=$B$49,H26<=$D$49)),"ISLA","OSLA"))) -> ISLA
A27: 26 | B27: 1806M03667 | C27: P1 | D27: SSPO | E27: Orange Money add-on / Bank to wallet / Ecobank | F27: 43269.665 | G27: 43269.701 | H27: 52 | I27: Impossible d’effectuer des transactions bancaires via OM | J27: Perte de connexion avec le partenaire Ecobank | K27: Retablissement de la connexion | L27: SSPO | M27: Clos | O27: =IF(AND(C27=$B$47,H27<=$D$47),"ISLA",IF((AND(C27=$B$48,H27<=$D$48)),"ISLA",IF((AND(C27=$B$49,H27<=$D$49)),"ISLA","OSLA"))) -> ISLA
A28: 27 | B28: 1806M04132 | C28: P1 | D28: Supervision | E28: Consultation des frais de Retrait OM | F28: 43269.671 | G28: 43269.701 | H28: 44 | I28: Impossible de consulter les frais de retraits OM | J28: Erreur de connectivité du web service | K28: Redéploiement du web service | L28: DevOps | M28: Clos | O28: =IF(AND(C28=$B$47,H28<=$D$47),"ISLA",IF((AND(C28=$B$48,H28<=$D$48)),"ISLA",IF((AND(C28=$B$49,H28<=$D$49)),"ISLA","OSLA"))) -> ISLA
A29: 28 | B29: 1806M24965 | C29: P1 | D29: Supervision | E29: Consultation de solde data (*222*5#) | F29: 43270.507 | G29: 43270.748 | H29: 347 | I29: Impossible de consulter son solde Data via *222*5# | J29: Plantage du serveur GlassFish | K29: Redemarrege du serveur | L29: ASBD | M29: Clos | O29: =IF(AND(C29=$B$47,H29<=$D$47),"ISLA",IF((AND(C29=$B$48,H29<=$D$48)),"ISLA",IF((AND(C29=$B$49,H29<=$D$49)),"ISLA","OSLA"))) -> OSLA
A30: 29 | B30: 1806M56292 | C30: P1 | D30: Sonatel | E30: Voix | F30: 43271.588 | G30: 43271.628 | H30: 58 | I30: Congestion et dégradation de la voix entre OGC et OCI | J30: Décablage du site Lumière côté Côte d'ivoire | K30: Recablage sur le site | L30: GNOC | M30: Clos | O30: =IF(AND(C30=$B$47,H30<=$D$47),"ISLA",IF((AND(C30=$B$48,H30<=$D$48)),"ISLA",IF((AND(C30=$B$49,H30<=$D$49)),"ISLA","OSLA"))) -> ISLA
A31: 30 | B31: 1806N17495 | C31: P1 | D31: Supervision | E31: Perturbation Réseau LAN | F31: 43271.597 | G31: 43271.628 | H31: 45 | I31: Indisponibilité Internet via LAN et services | J31: Perte du proxy | K31: redémarrage du proxy de technopôle | L31: Sonatel | M31: Clos | O31: =IF(AND(C31=$B$47,H31<=$D$47),"ISLA",IF((AND(C31=$B$48,H31<=$D$48)),"ISLA",IF((AND(C31=$B$49,H31<=$D$49)),"ISLA","OSLA"))) -> ISLA
A32: 31 | B32: 1806M65488 | C32: P1 | D32: Supervision | E32: Nomad | F32: 43271.708 | G32: 43272.771 | H32: 1530 | I32: Impossible de vérifier le statut du msisdn dans le CRM | J32: Mauvais formatage de la Date côté CRM | K32: Correction du format de date | L32: GOS | M32: Clos | O32: =IF(AND(C32=$B$47,H32<=$D$47),"ISLA",IF((AND(C32=$B$48,H32<=$D$48)),"ISLA",IF((AND(C32=$B$49,H32<=$D$49)),"ISLA","OSLA"))) -> OSLA
A33: 32 | B33: 1806M85112 | C33: P1 | D33: SSPO | E33: Orange Money add-on / Bank to wallet / Ecobank | F33: 43272.494 | G33: 43272.531 | H33: 53 | I33: Impossible d’effectuer des transactions bancaires via OM | J33: Perte de connexion avec le partenaire Ecobank | K33: Retablissement de la connexion | L33: SSPO | M33: Clos | O33: =IF(AND(C33=$B$47,H33<=$D$47),"ISLA",IF((AND(C33=$B$48,H33<=$D$48)),"ISLA",IF((AND(C33=$B$49,H33<=$D$49)),"ISLA","OSLA"))) -> ISLA
A34: 33 | B34: 1806M91992 | C34: P1 | D34: SSPO | E34: Orange Money add-on / Bank to wallet / Ecobank | F34: 43272.608 | G34: 43272.642 | H34: 49 | I34: Impossible d’effectuer des transactions bancaires via OM | J34: Perte de connexion avec le partenaire Ecobank | K34: Retablissement de la connexion | L34: SSPO | M34: Clos | O34: =IF(AND(C34=$B$47,H34<=$D$47),"ISLA",IF((AND(C34=$B$48,H34<=$D$48)),"ISLA",IF((AND(C34=$B$49,H34<=$D$49)),"ISLA","OSLA"))) -> ISLA
A35: 34 | B35: 1806M99692 | C35: P1 | D35: SSPO | E35: Orange Money add-on / Canal+ | F35: 43272.885 | G35: 43272.9 | H35: 21 | I35: Impossible d’effectuer le réabonnement canal+ via OM | J35: Indisponibilité du serveur proxy du partenaire | K35: Retablissement du serveur proxy | L35: SSPO | M35: Clos | O35: =IF(AND(C35=$B$47,H35<=$D$47),"ISLA",IF((AND(C35=$B$48,H35<=$D$48)),"ISLA",IF((AND(C35=$B$49,H35<=$D$49)),"ISLA","OSLA"))) -> ISLA
A36: 35 | B36: 1806N21871 | C36: P1 | D36: Supervision | E36: Transfert Data | F36: 43273.349 | G36: 43280.385 | H36: =(G36-F36)*1440 -> 10132 | I36: Impossible de transférer des pass aux abonnés (*222*8#) | J36: Indisponibilité du serveur d'application | K36: Réinstallation du serveur d’application, Redéploiement et configuration du web Service pour formatage des réponses (Xml) des requêtes | L36: DevOps | M36: Clos | O36: =IF(AND(C36=$B$47,H36<=$D$47),"ISLA",IF((AND(C36=$B$48,H36<=$D$48)),"ISLA",IF((AND(C36=$B$49,H36<=$D$49)),"ISLA","OSLA"))) -> OSLA
A37: 36 | B37: 1806N07560 | C37: P2 | D37: Supervision | E37: E-recharge | F37: 43273.349 | G37: 43273.372 | H37: 32 | I37: Echec de 4% des rechargements via OM (Achat de crédit) | J37: Non rechargement du compte Tango | K37: rechargement du compte Tango | L37: SSPO | M37: Clos | O37: =IF(AND(C37=$B$47,H37<=$D$47),"ISLA",IF((AND(C37=$B$48,H37<=$D$48)),"ISLA",IF((AND(C37=$B$49,H37<=$D$49)),"ISLA","OSLA"))) -> ISLA
A38: 37 | B38: 1806N22002 | C38: P1 | D38: Supervision | E38: Nomad | F38: 43273.461 | G38: 43293.535 | H38: 28906 | I38: Probleme de reception de notification après vente de sur l’état d’activation du numéro | J38: Investigations en cours | K38: Inconnue | L38: GOS | M38: Clos | O38: =IF(AND(C38=$B$47,H38<=$D$47),"ISLA",IF((AND(C38=$B$48,H38<=$D$48)),"ISLA",IF((AND(C38=$B$49,H38<=$D$49)),"ISLA","OSLA"))) -> OSLA
A39: 38 | B39: 1806N47146 | C39: P2 | D39: SSPO | E39: E-recharge | F39: 43275.439 | G39: 43275.473 | H39: 49 | I39: Echec de 50% de notifications après transactions E-recharge | J39: Déconnexion entre ZEBRA et SMSC | K39: Aucune | L39: GNOC/SSPO | M39: Clos | N39: pour identifier la root cause et apporté une correction definitive, ce dysfonctionnement est traité en dans le ticket problème N°1806I34048 | O39: =IF(AND(C39=$B$47,H39<=$D$47),"ISLA",IF((AND(C39=$B$48,H39<=$D$48)),"ISLA",IF((AND(C39=$B$49,H39<=$D$49)),"ISLA","OSLA"))) -> ISLA
A40: 39 | B40: 1806N68181 | C40: P2 | D40: SSPO | E40: E-recharge | F40: 43276.476 | G40: 43276.492 | H40: 24 | I40: Echec de 50% de reception de notifications après transactions E-recharge | J40: Déconnexion entre ZEBRA et SMSC | K40: Aucune | L40: GNOC/SSPO | M40: Clos | N40: pour identifier la root cause et apporté une correction definitive, ce dysfonctionnement est traité en dans le ticket problème N°1806I34048 | O40: =IF(AND(C40=$B$47,H40<=$D$47),"ISLA",IF((AND(C40=$B$48,H40<=$D$48)),"ISLA",IF((AND(C40=$B$49,H40<=$D$49)),"ISLA","OSLA"))) -> ISLA
A41: 40 | B41: 1806N83920 | C41: P1 | D41: SSPO | E41: Orange Money add-on / Bank to wallet / Ecobank | F41: 43276.886 | G41: 43276.896 | H41: 14 | I41: Impossible d’effectuer des transactions bancaires via OM | J41: Perte de connexion avec le partenaire Ecobank | K41: Rétablissement de la connexion | L41: SSPO | M41: Clos | O41: =IF(AND(C41=$B$47,H41<=$D$47),"ISLA",IF((AND(C41=$B$48,H41<=$D$48)),"ISLA",IF((AND(C41=$B$49,H41<=$D$49)),"ISLA","OSLA"))) -> ISLA
A42: 41 | B42: 1806O39513 | C42: P1 | D42: Supervision | E42: Voix | F42: 43278.662 | G42: 43278.67 | H42: 11 | I42: Indisponibilité d’émission d’appel via les postes IP | J42: Inconnue | K42: Aucune | L42: ASBD | M42: Clos | O42: =IF(AND(C42=$B$47,H42<=$D$47),"ISLA",IF((AND(C42=$B$48,H42<=$D$48)),"ISLA",IF((AND(C42=$B$49,H42<=$D$49)),"ISLA","OSLA"))) -> ISLA
A43: 42 | B43: 1806O63132 | C43: P2 | D43: Supervision | E43: Consultation des frais de Retrait ,Web payement | F43: 43279.476 | G43: 43279.517 | H43: 60 | I43: Instabilité des services consultation Frais de retrait et webpayment OM | J43: Indisponibilité du Web Service | K43: déploiement du F5 pour le load balancing et migration des services | L43: ASBD | M43: Clos | N43: ticket problème 1807Q15694 | O43: =IF(AND(C43=$B$47,H43<=$D$47),"ISLA",IF((AND(C43=$B$48,H43<=$D$48)),"ISLA",IF((AND(C43=$B$49,H43<=$D$49)),"ISLA","OSLA"))) -> ISLA
A44: 43 | B44: 1806O84440 | C44: P1 | D44: SSPO | E44: Orange Money add-on / Bank to wallet / Ecobank | F44: 43280.338 | G44: 43280.374 | H44: 53 | I44: Impossible d’effectuer des transactions bancaires via OM | J44: Perte de connexion avec le partenaire Ecobank | K44: Retablissement de la connexion | L44: SSPO | M44: Clos | O44: =IF(AND(C44=$B$47,H44<=$D$47),"ISLA",IF((AND(C44=$B$48,H44<=$D$48)),"ISLA",IF((AND(C44=$B$49,H44<=$D$49)),"ISLA","OSLA"))) -> ISLA
A45: 44 | B45: 1806P09016 | C45: P1 | D45: SSPO | E45: Orange Money add-on / Bank to wallet / Ecobank | F45: 43281.355 | G45: 43281.394 | H45: 56 | I45: Impossible d’effectuer des transactions bancaires via OM | J45: Perte de connexion avec le partenaire Ecobank | K45: Retablissement de la connexion | L45: SSPO | M45: Clos | O45: =IF(AND(C45=$B$47,H45<=$D$47),"ISLA",IF((AND(C45=$B$48,H45<=$D$48)),"ISLA",IF((AND(C45=$B$49,H45<=$D$49)),"ISLA","OSLA"))) -> ISLA
B47: P1 | C47: 2h | D47: 120
B48: P2 | C48: 4h | D48: 240
B49: P3 | C49: 2jr | D49: =1440*2 -> 2880
B50: P4 | C50: 3jr | D50: =3*1440 -> 4320

Sheet Juillet_2018
A1: N° | B1: N°ticket | C1: Priorité | D1: Origine | E1: Nom Service | F1: Date & heure de début | G1: Date & heure de fin | H1: Durée (mn) | I1: Description | J1: Cause de l'incident | K1: Actions correctives | L1: TMC | M1: Statut | N1: Observation | O1: SLA
A2: 1 | B2: 1807Q41176 | C2: P1 | D2: Supervision | E2: FFC | F2: 43286.293 | G2: 43286.415 | H2: 176 | I2: Indisponibilité du service Fans Football Club | J2: verrouillage de la base de données | K2: redémarrage du serveur | L2: Support FFC | M2: Clos | O2: =IF(AND(C2=$B$47,H2<=$D$47),"ISLA",IF((AND(C2=$B$48,H2<=$D$48)),"ISLA",IF((AND(C2=$B$49,H2<=$D$49)),"ISLA","OSLA"))) -> OSLA
A3: 2 | B3: 1807Q53313 | C3: P1 | D3: Supervision | E3: Data Mobile | F3: 43286.375 | G3: 43286.826 | H3: 650 | I3: Lenteur de la data mobile | J3: Coupure de fibre côté sonatel entre DIALAKOTO – DIENOUDIALA | K3: Soudure de fibre | L3: GNOC | M3: Clos | O3: =IF(AND(C3=$B$47,H3<=$D$47),"ISLA",IF((AND(C3=$B$48,H3<=$D$48)),"ISLA",IF((AND(C3=$B$49,H3<=$D$49)),"ISLA","OSLA"))) -> OSLA
A4: 3 | B4: 1807R08551 | C4: P1 | D4: Supervision | E4: VOIX, DATA, E-Recharge,SMS,USSD | F4: 43289.031 | G4: 43289.049 | H4: 25 | I4: Indisponibilité des services voix, data, sms, USSD et E-recharge pour certains PQ (622 et 628) | J4: Redemarrage des process de OCS4 | K4: Aucune action faite | L4: GNOC | M4: Clos | O4: =IF(AND(C4=$B$47,H4<=$D$47),"ISLA",IF((AND(C4=$B$48,H4<=$D$48)),"ISLA",IF((AND(C4=$B$49,H4<=$D$49)),"ISLA","OSLA"))) -> ISLA
A5: 4 | B5: 1807R14089 | C5: P1 | D5: SSPO | E5: Orange Money add-on / Bank to wallet / UBA | F5: 43289.551 | G5: 43289.563 | H5: =(G5-F5)*1440 -> 17 | I5: Impossible d’effectuer des transactions bancaires via OM | J5: Perte de connexion avec le partenaire UBA | K5: Retablissement de la connexion | L5: SSPO | M5: Clos | O5: =IF(AND(C5=$B$47,H5<=$D$47),"ISLA",IF((AND(C5=$B$48,H5<=$D$48)),"ISLA",IF((AND(C5=$B$49,H5<=$D$49)),"ISLA","OSLA"))) -> ISLA
A6: 5 | B6: 1806P09016 | C6: P1 | D6: SSPO | E6: Orange Money add-on / Bank to wallet / Ecobank | F6: 43290.417 | G6: 43290.462 | H6: 64 | I6: Impossible d’effectuer des transactions bancaires via OM | J6: Perte de connexion avec le partenaire Ecobank | K6: Rétablissement de la connexion | L6: SSPO | M6: Clos | O6: =IF(AND(C6=$B$47,H6<=$D$47),"ISLA",IF((AND(C6=$B$48,H6<=$D$48)),"ISLA",IF((AND(C6=$B$49,H6<=$D$49)),"ISLA","OSLA"))) -> ISLA
A7: 6 | B7: 1807R58607 | C7: P3 | D7: Mobil Tv | E7: Mobile TV / RTG | F7: 43291.324 | G7: 43291.708 | H7: 554 | I7: Impossible d’accéder à la chaine RTG sur mobile TV | J7: source indisponible | K7: Rétablissement de la source | L7: Mobil Tv | M7: Clos | O7: =IF(AND(C7=$B$47,H7<=$D$47),"ISLA",IF((AND(C7=$B$48,H7<=$D$48)),"ISLA",IF((AND(C7=$B$49,H7<=$D$49)),"ISLA","OSLA"))) -> ISLA
A8: 7 | B8: 1807S32935 | C8: P1 | D8: SSPO | E8: Orange Money add-on / Bank to wallet / Ecobank | F8: 43293.473 | G8: 43293.628 | H8: 223 | I8: Impossible d’effectuer des transactions bancaires via OM | J8: Perte de connexion avec le partenaire Ecobank | K8: Rétablissement de la connexion | L8: SSPO | M8: Clos | O8: =IF(AND(C8=$B$47,H8<=$D$47),"ISLA",IF((AND(C8=$B$48,H8<=$D$48)),"ISLA",IF((AND(C8=$B$49,H8<=$D$49)),"ISLA","OSLA"))) -> OSLA
A9: 8 | B9: 1807S70846 | C9: P1 | D9: Supervision | E9: VOIX, DATA, E-Recharge, SMS, USSD | F9: 43295.201 | G9: 43295.215 | H9: 20 | I9: Indisponibilité des services voix, data, sms et E-recharge pour certains PQ (622, 623 et 628) | J9: Redémarrage des Proccess OCSPRO du serveur OCS4 | K9: Aucune | L9: GNOC | M9: Clos | O9: =IF(AND(C9=$B$47,H9<=$D$47),"ISLA",IF((AND(C9=$B$48,H9<=$D$48)),"ISLA",IF((AND(C9=$B$49,H9<=$D$49)),"ISLA","OSLA"))) -> ISLA
A10: 9 | B10: 1807T96226 | C10: P1 | D10: SSPO | E10: Orange Money add-on / Bank to wallet / Ecobank | F10: 43300.371 | G10: 43300.406 | H10: 50 | I10: Impossible d’effectuer des transactions bancaires via OM | J10: Perte de connexion avec le partenaire Ecobank | K10: Rétablissement de la connexion | L10: SSPO | M10: Clos | O10: =IF(AND(C10=$B$47,H10<=$D$47),"ISLA",IF((AND(C10=$B$48,H10<=$D$48)),"ISLA",IF((AND(C10=$B$49,H10<=$D$49)),"ISLA","OSLA"))) -> ISLA
A11: 10 | B11: 1807U53528 | C11: P1 | D11: Supervision | E11: Simplissimo | F11: 43302.463 | G11: 43302.573 | H11: 158 | I11: Souci d'activation & changements SIM dans SIMPLISSIMO | J11: Plantage de KPSA | K11: Redémarrage de KPSA et resoumission des requêtes en instance | L11: ASBD | M11: Clos | O11: =IF(AND(C11=$B$47,H11<=$D$47),"ISLA",IF((AND(C11=$B$48,H11<=$D$48)),"ISLA",IF((AND(C11=$B$49,H11<=$D$49)),"ISLA","OSLA"))) -> OSLA
A12: 11 | B12: 1807S32935 | C12: P1 | D12: SSPO | E12: Orange Money add-on / Bank to wallet / Ecobank | F12: 43303.734 | G12: 43303.774 | H12: 57 | I12: Impossible d’effectuer des transactions bancaires via OM | J12: Perte de connexion avec le partenaire Ecobank | K12: Rétablissement de la connexion | L12: SSPO | M12: Clos | O12: =IF(AND(C12=$B$47,H12<=$D$47),"ISLA",IF((AND(C12=$B$48,H12<=$D$48)),"ISLA",IF((AND(C12=$B$49,H12<=$D$49)),"ISLA","OSLA"))) -> ISLA
A13: 12 | B13: 1807S32935 | C13: P1 | D13: SSPO | E13: Orange Money add-on / Bank to wallet / Ecobank | F13: 43303.734 | G13: 43303.774 | H13: 57 | I13: Impossible d’effectuer des transactions bancaires via OM | J13: Perte de connexion avec le partenaire Ecobank | K13: Rétablissement de la connexion | L13: SSPO | M13: Clos | O13: =IF(AND(C13=$B$47,H13<=$D$47),"ISLA",IF((AND(C13=$B$48,H13<=$D$48)),"ISLA",IF((AND(C13=$B$49,H13<=$D$49)),"ISLA","OSLA"))) -> ISLA
A14: 13 | B14: 1807V17808/1807V12345 | C14: P1 | D14: Supervision | E14: Orange money | F14: 43305.444 | G14: 43305.478 | H14: 48 | I14: Impossible d’effectuer des transactions OM | J14: Souci sur le commutateur situé entre les serveurs oracle Orange Money et les fichiers de données | K14: Le trafic a été déplacé vers le commutateur de sauvegarde | L14: SSPO | M14: Clos | O14: =IF(AND(C14=$B$47,H14<=$D$47),"ISLA",IF((AND(C14=$B$48,H14<=$D$48)),"ISLA",IF((AND(C14=$B$49,H14<=$D$49)),"ISLA","OSLA"))) -> ISLA
A15: 14 | B15: 1807V25983 | C15: P1 | D15: Supervision | E15: Gameloft | F15: 43305.581 | G15: 43305.661 | H15: 115 | I15: Impossible d’accéder au service via l’accès web et ussd | J15: Problème de réseau dans le centre de données | K15: En attente du rapport d'incident | L15: Gameloft | M15: Clos | O15: =IF(AND(C15=$B$47,H15<=$D$47),"ISLA",IF((AND(C15=$B$48,H15<=$D$48)),"ISLA",IF((AND(C15=$B$49,H15<=$D$49)),"ISLA","OSLA"))) -> ISLA
A16: 15 | B16: 1807V34200 | C16: P1 | D16: Supervision | E16: SOS-Crédit et Paie-pour-moi | F16: 43305.912 | G16: 43305.96 | H16: 68 | I16: Instabilité des services SOS-CREDIT et Paie-pour-moi | J16: Redémarrage des Process Live SMPSVR causant des instabilités sur les services SOS Crédit et P4M | K16: Aucune | L16: GNOC | M16: Clos | O16: =IF(AND(C16=$B$47,H16<=$D$47),"ISLA",IF((AND(C16=$B$48,H16<=$D$48)),"ISLA",IF((AND(C16=$B$49,H16<=$D$49)),"ISLA","OSLA"))) -> ISLA
A17: 16 | B17: 1807W36865 | C17: P1 | D17: Supervision | E17: SOS-Crédit et Paie-pour-moi | F17: 43309.848 | G17: 43409.78 | H17: =(G17-F17)*1440 -> 143901.6 | I17: Instabilité des services SOS-CREDIT et Paie-pour-moi | J17: Disque défectueux et indisponibilité du server SMP | K17: Reset du server SMP à partir de l'interface AO et changement des disk faulty sur SMP server | L17: GNOC | M17: Clos | N17: Le GNOC est confronté à un problème d'accès à distance sur les équipement afin de relever l'incident. | O17: =IF(AND(C17=$B$47,H17<=$D$47),"ISLA",IF((AND(C17=$B$48,H17<=$D$48)),"ISLA",IF((AND(C17=$B$49,H17<=$D$49)),"ISLA","OSLA"))) -> OSLA
B47: P1 | C47: 2h | D47: 120
B48: P2 | C48: 4h | D48: 240
B49: P3 | C49: 2jr | D49: =1440*2 -> 2880
B50: P4 | C50: 3jr | D50: =3*1440 -> 4320

Sheet Aout_2018
A1: N° | B1: N°TICKET | C1: PRIORITE | D1: Origine | E1: NOM Service | F1: DATE & HEURE DEBUT | G1: DATE & HEURE FIN | H1: DUREE (mn) | I1: Description | J1: CAUSE DE L'INCIDENT | K1: ACTIONS CORRECTIVES | L1: TMC | M1: STATUT | N1: Observation | O1: SLA
A2: 1 | B2: 1808X32012 | C2: P1 | D2: SSPO | E2: Orange Money add-on / UBA | F2: 43313.446 | G2: 43313.89 | H2: 340 | I2: Impossible d’effectuer les transactions bancaires via OM | J2: Perte de connexion dû à la migration vers la nouvelle application bancaire | K2: Fin de migration | L2: SSPO | M2: Clos | O2: =IF(AND(C2=$B$47,H2<=$D$47),"ISLA",IF((AND(C2=$B$48,H2<=$D$48)),"ISLA",IF((AND(C2=$B$49,H2<=$D$49)),"ISLA","OSLA"))) -> OSLA
A3: 2 | B3: 1808X29968 | C3: P1 | D3: SSPO | E3: Orange Money add-on / Bank to wallet / Ecobank | F3: 43313.615 | G3: 43313.667 | H3: 76 | I3: Impossible d’effectuer les transactions bancaires via OM | J3: Perte de connexion avec le partenaire Ecobank | K3: Rétablissement de la connexion | L3: SSPO | M3: Clos | O3: =IF(AND(C3=$B$47,H3<=$D$47),"ISLA",IF((AND(C3=$B$48,H3<=$D$48)),"ISLA",IF((AND(C3=$B$49,H3<=$D$49)),"ISLA","OSLA"))) -> ISLA
A4: 3 | B4: 1808Y76531 | C4: P1 | D4: SSPO | E4: Orange Money add-on / Bank to wallet / Ecobank | F4: 43319.728 | G4: 43319.874 | H4: 211 | I4: Impossible d’effectuer les transactions bancaires via OM | J4: Perte de connexion avec le partenaire Ecobank | K4: Rétablissement de la connexion | L4: SSPO | M4: Clos | O4: =IF(AND(C4=$B$47,H4<=$D$47),"ISLA",IF((AND(C4=$B$48,H4<=$D$48)),"ISLA",IF((AND(C4=$B$49,H4<=$D$49)),"ISLA","OSLA"))) -> OSLA
A5: 4 | B5: 1808Z21205 | C5: P1 | D5: SSPO | E5: Orange Money add-on / UBA | F5: 43321.333 | G5: 43321.705 | H5: 535 | I5: Impossible d’effectuer les transactions bancaires via OM | J5: Probleme de configuration dans les paramètres du réseau local du partenaire | K5: Correction des erreurs | L5: SSPO | M5: Clos | O5: =IF(AND(C5=$B$47,H5<=$D$47),"ISLA",IF((AND(C5=$B$48,H5<=$D$48)),"ISLA",IF((AND(C5=$B$49,H5<=$D$49)),"ISLA","OSLA"))) -> OSLA
A6: 5 | B6: 1808Z38184 | C6: P2 | D6: Supervision | E6: Gameloft | F6: 43321.815 | G6: 43323.722 | H6: 2746 | I6: Instabilité du service gameloft via le portail web | J6: Plantage de certains process de gameloft | K6: Redémarrage des process | L6: GOS | M6: Clos | N6: En attente du rapport | O6: =IF(AND(C6=$B$47,H6<=$D$47),"ISLA",IF((AND(C6=$B$48,H6<=$D$48)),"ISLA",IF((AND(C6=$B$49,H6<=$D$49)),"ISLA","OSLA"))) -> OSLA
A7: 6 | B7: 1808A06172 | C7: P1 | D7: SSPO | E7: Orange Money add-on / Bank to wallet / Ecobank | F7: 43325.481 | G7: 43325.511 | H7: 44 | I7: Impossible d’effectuer les transactions bancaires via OM | J7: Perte de connexion avec le partenaire Ecobank | K7: Rétablissement de la connexion | L7: SSPO | M7: Clos | O7: =IF(AND(C7=$B$47,H7<=$D$47),"ISLA",IF((AND(C7=$B$48,H7<=$D$48)),"ISLA",IF((AND(C7=$B$49,H7<=$D$49)),"ISLA","OSLA"))) -> ISLA
A8: 7 | B8: 1808A20321 | C8: P2 | D8: Supervision | E8: Data Mobile | F8: 43325.92 | G8: 43327 | H8: 1555 | I8: Baisse du Trafic Data Dalein -Kédougou | J8: Coupure de la FO à 130km de MAKO vers NIOKO | K8: soudure de la fibre et basculement du trafic | L8: GNOC | M8: Clos | N8: En attente du rapport | O8: =IF(AND(C8=$B$47,H8<=$D$47),"ISLA",IF((AND(C8=$B$48,H8<=$D$48)),"ISLA",IF((AND(C8=$B$49,H8<=$D$49)),"ISLA","OSLA"))) -> OSLA
A9: 8 | B9: 1808A06172 | C9: P1 | D9: SSPO | E9: Orange Money add-on / Bank to wallet / Ecobank | F9: 43327.517 | G9: 43327.567 | H9: 71 | I9: Impossible d’effectuer les transactions bancaires via OM | J9: Perte de connexion avec le partenaire Ecobank | K9: Rétablissement de la connexion | L9: SSPO | M9: Clos | O9: =IF(AND(C9=$B$47,H9<=$D$47),"ISLA",IF((AND(C9=$B$48,H9<=$D$48)),"ISLA",IF((AND(C9=$B$49,H9<=$D$49)),"ISLA","OSLA"))) -> ISLA
A10: 9 | B10: 1808A59264 | C10: P1 | D10: Supervision | E10: FFC | F10: 43327.972 | G10: 43328.249 | H10: 398 | I10: Indisponibilité du service FFC | J10: Cause non identifiée. Le retour du support est que l’interruption de service est probablement due à un problème réseau. | K10: Aucune action faite. | L10: Support FFC | M10: Clos | N10: Ticket problème 1808A98268 pour déterminer la root cause | O10: =IF(AND(C10=$B$47,H10<=$D$47),"ISLA",IF((AND(C10=$B$48,H10<=$D$48)),"ISLA",IF((AND(C10=$B$49,H10<=$D$49)),"ISLA","OSLA"))) -> OSLA
A11: 10 | B11: 1808A68162 | C11: P1 | D11: SSPO | E11: Orange Money add-on / Canal + | F11: 43328.372 | G11: 43328.397 | H11: 36 | I11: Impossible d’effectuer le réabonnement canal via OM | J11: Inconnue | K11: Aucune action faite. | L11: SSPO | M11: Clos | O11: =IF(AND(C11=$B$47,H11<=$D$47),"ISLA",IF((AND(C11=$B$48,H11<=$D$48)),"ISLA",IF((AND(C11=$B$49,H11<=$D$49)),"ISLA","OSLA"))) -> ISLA
A12: 11 | B12: 1808A96701 | C12: P1 | D12: SSPO | E12: Orange Money add-on / Bank to wallet / Ecobank | F12: 43329.419 | G12: 43329.662 | H12: 349 | I12: Impossible d’effectuer les transactions bancaires via OM | J12: Perte de connexion avec le partenaire Ecobank | K12: Retablissement de la connexion | L12: SSPO | M12: Clos | O12: =IF(AND(C12=$B$47,H12<=$D$47),"ISLA",IF((AND(C12=$B$48,H12<=$D$48)),"ISLA",IF((AND(C12=$B$49,H12<=$D$49)),"ISLA","OSLA"))) -> OSLA
A13: 12 | B13: 1808B19572 | C13: P1 | D13: Supervision | E13: Report Avantage | F13: 43330.505 | G13: 43330.563 | H13: 84 | I13: Impossible de recevoir ses avantages à partir du *118*1# | J13: Expiration du mot de passe de l’utilisateur sur la Base de données | K13: Réinitialisation du mot de passe | L13: ASBD | M13: Clos | O13: =IF(AND(C13=$B$47,H13<=$D$47),"ISLA",IF((AND(C13=$B$48,H13<=$D$48)),"ISLA",IF((AND(C13=$B$49,H13<=$D$49)),"ISLA","OSLA"))) -> ISLA
A14: 13 | B14: 1808C55516 | C14: P1 | D14: Etisalat | E14: Roaming Data Out | F14: 43332.529 | G14: 43344 | H14: =(G14-F14)*1440 -> 16517.983 | I14: Certains cliens n'arrivent pas à faire la data sur le reseau ETISALAT (Arabie Saoudite) | J14: Investigations en cours | K14: Investigations en cours | L14: GNOC | M14: Clos | N14: Les adresses 86.51.50.32/28 et 86.51.50.48/28 ne sont pas autorisées par le partenaire. Des actions sont en cours côté Etisalat | O14: =IF(AND(C14=$B$47,H14<=$D$47),"ISLA",IF((AND(C14=$B$48,H14<=$D$48)),"ISLA",IF((AND(C14=$B$49,H14<=$D$49)),"ISLA","OSLA"))) -> OSLA
A15: 14 | B15: 1808B55308 | C15: P1 | D15: Supervision | E15: Consultation de solde data (*222*5#) | F15: 43332.571 | G15: 43332.601 | H15: 44 | I15: Indisponobilité du service consultation_pass | J15: Arrêt du serveur d’application | K15: Redémarrage du serveur | L15: ASBD | M15: Clos | O15: =IF(AND(C15=$B$47,H15<=$D$47),"ISLA",IF((AND(C15=$B$48,H15<=$D$48)),"ISLA",IF((AND(C15=$B$49,H15<=$D$49)),"ISLA","OSLA"))) -> ISLA
A16: 15 | B16: 1808B59783 | C16: P1 | D16: SSPO | E16: Orange Money add-on / Bank to wallet / Ecobank | F16: 43332.69 | G16: 43332.728 | H16: 55 | I16: Impossible d’effectuer les transactions bancaires via OM | J16: Perte de connexion avec le partenaire Ecobank | K16: Retablissement de la connexion | L16: SSPO | M16: Clos | O16: =IF(AND(C16=$B$47,H16<=$D$47),"ISLA",IF((AND(C16=$B$48,H16<=$D$48)),"ISLA",IF((AND(C16=$B$49,H16<=$D$49)),"ISLA","OSLA"))) -> ISLA
A17: 16 | B17: 1808B93985 | C17: P2 | D17: SSPO | E17: Orange Money add-on / Bank to wallet / Ecobank | F17: 43334.292 | G17: 43334.332 | H17: 57 | I17: Impossible d’effectuer des transactions bancaires via OM | J17: Perte de connexion avec le partenaire Ecobank | K17: Retablissement de la connexion | L17: SSPO | M17: Clos | O17: =IF(AND(C17=$B$47,H17<=$D$47),"ISLA",IF((AND(C17=$B$48,H17<=$D$48)),"ISLA",IF((AND(C17=$B$49,H17<=$D$49)),"ISLA","OSLA"))) -> ISLA
A18: 17 | B18: 1808C33514 | C18: P1 | D18: SSPO | E18: Orange Money add-on / Bank to wallet / Ecobank | F18: 43335.549 | G18: 43335.594 | H18: 64 | I18: Impossible d’effectuer des transactions bancaires via OM | J18: Perte de connexion avec le partenaire Ecobank | K18: Retablissement de la connexion | L18: SSPO | M18: Clos | O18: =IF(AND(C18=$B$47,H18<=$D$47),"ISLA",IF((AND(C18=$B$48,H18<=$D$48)),"ISLA",IF((AND(C18=$B$49,H18<=$D$49)),"ISLA","OSLA"))) -> ISLA
A19: 18 | B19: 1808C43210 | C19: P1 | D19: SSPO | E19: Orange Money add-on / Bank to wallet / Ecobank | F19: 43335.947 | G19: 43335.985 | H19: 55 | I19: Impossible d’effectuer des transactions bancaires via OM | J19: Perte de connexion avec le partenaire Ecobank | K19: Retablissement de la connexion | L19: SSPO | M19: Clos | O19: =IF(AND(C19=$B$47,H19<=$D$47),"ISLA",IF((AND(C19=$B$48,H19<=$D$48)),"ISLA",IF((AND(C19=$B$49,H19<=$D$49)),"ISLA","OSLA"))) -> ISLA
A20: 19 | B20: 1808B59783 | C20: P1 | D20: Guinee Games | E20: Orange Money Add-on / Web Payment / Guinee Games | F20: 43341.333 | G20: 43342.358 | H20: 1476 | I20: Impossible pour les parieurs d’effectuer des paiements en ligne via OM | J20: Nombre maximum des transactions mensuelles atteint | K20: Augmentation du seuil de nombre des transactions mensuelles | L20: OFMG | M20: Clos | O20: =IF(AND(C20=$B$47,H20<=$D$47),"ISLA",IF((AND(C20=$B$48,H20<=$D$48)),"ISLA",IF((AND(C20=$B$49,H20<=$D$49)),"ISLA","OSLA"))) -> OSLA
A21: 20 | B21: 1808B55308 | C21: P1 | D21: SSPO | E21: Orange Money add-on / Bank to wallet / Ecobank | F21: 43342.622 | G21: 43343.434 | H21: 1169 | I21: Impossible d’effectuer les transactions bancaires via OM | J21: Perte de connexion avec le partenaire Ecobank | K21: Retablissement de la connexion | L21: SSPO | M21: Clos | O21: =IF(AND(C21=$B$47,H21<=$D$47),"ISLA",IF((AND(C21=$B$48,H21<=$D$48)),"ISLA",IF((AND(C21=$B$49,H21<=$D$49)),"ISLA","OSLA"))) -> OSLA
A22: 21 | B22: 1808E27275 | C22: P1 | D22: SSPO | E22: Orange Money add-on / Bank to wallet / Ecobank | F22: 43343.835 | G22: 43343.844 | H22: 14 | I22: Impossible d’effectuer des transactions bancaires via OM | J22: Perte de connexion avec le partenaire Ecobank | K22: Retablissement de la connexion | L22: SSPO | M22: Clos | O22: =IF(AND(C22=$B$47,H22<=$D$47),"ISLA",IF((AND(C22=$B$48,H22<=$D$48)),"ISLA",IF((AND(C22=$B$49,H22<=$D$49)),"ISLA","OSLA"))) -> ISLA
A23: 22 | B23: 1808E27275 | C23: P1 | D23: SSPO | E23: Orange Money add-on / Bank to wallet / Ecobank | F23: 43343.921 | G23: 43343.962 | H23: 59 | I23: Impossible d’effectuer les transactions bancaires via OM | J23: Perte de connexion avec le partenaire Ecobank | K23: Retablissement de la connexion | L23: SSPO | M23: Clos | O23: =IF(AND(C23=$B$47,H23<=$D$47),"ISLA",IF((AND(C23=$B$48,H23<=$D$48)),"ISLA",IF((AND(C23=$B$49,H23<=$D$49)),"ISLA","OSLA"))) -> ISLA
B47: P1 | C47: 2h | D47: 120
B48: P2 | C48: 4h | D48: 240
B49: P3 | C49: 2jr | D49: =1440*2 -> 2880
B50: P4 | C50: 3jr | D50: =3*1440 -> 4320

Sheet Septembre_2018
A1: N° | B1: N°TICKET | C1: PRIORITE | D1: Origine | E1: NOM SERVICES | F1: DATE & HEURE DEBUT | G1: DATE & HEURE FIN | H1: DUREE (mn) | I1: DESCRIPTION | J1: CAUSE DE L'INCIDENT | K1: ACTIONS CORRECTIVES | L1: TMC | M1: Statut | N1: Observation | O1: SLA
A2: 1 | B2: 1809E30255 | C2: P1 | D2: SSPO | E2: Orange Money add-on / Bank to wallet / Ecobank | F2: 43344.158 | G2: 43344.194 | H2: 53 | I2: Impossible d’effectuer les transactions bancaires via OM | J2: Perte de connexion avec le partenaire Ecobank | K2: Retablissement de la connexion | L2: SSPO | M2: Clos | O2: =IF(AND(C2=$B$47,H2<=$D$47),"ISLA",IF((AND(C2=$B$48,H2<=$D$48)),"ISLA",IF((AND(C2=$B$49,H2<=$D$49)),"ISLA","OSLA"))) -> ISLA
A3: 2 | B3: 1809E48651 | C3: P1 | D3: Supervision | E3: Data mobile | F3: 43345.406 | G3: 43347.587 | H3: 3140 | I3: Chute du trafic internet Dalein Kedougou | J3: Fortes dégradations à 56km sur une fibre de la paire entre DIENOUDIALA et MAKO | K3: Correction des inversions sur les paires libres et Mutation sur une paire saine entre DIENOUDIALA-NIOKO1 et NIOKO1-MAKO | L3: GNOC | M3: Clos | O3: =IF(AND(C3=$B$47,H3<=$D$47),"ISLA",IF((AND(C3=$B$48,H3<=$D$48)),"ISLA",IF((AND(C3=$B$49,H3<=$D$49)),"ISLA","OSLA"))) -> OSLA
A4: 3 | B4: 1809F40565 | C4: P1 | D4: SSPO | E4: Paddock Services / Billing - Wrapper | F4: 43349.043 | G4: 43349.075 | H4: 46 | I4: Impossible d'acheter les applications via le mode de paiement par Operateur | J4: Indisponibilité du module d'interface du pays (CIM) | K4: Redémarrage des services Nginx | L4: SSPO | M4: Clos | O4: =IF(AND(C4=$B$47,H4<=$D$47),"ISLA",IF((AND(C4=$B$48,H4<=$D$48)),"ISLA",IF((AND(C4=$B$49,H4<=$D$49)),"ISLA","OSLA"))) -> ISLA
A5: 4 | B5: 1809G26770 | C5: P1 | D5: SSPO | E5: PADDOCK / SMSC | F5: 43353.25 | G5: 43353.27 | H5: 29 | I5: Impossible d’utiliser les fonctionnalités SMS PADDOCK | J5: Inconnue | K5: Aucune | L5: SSPO | M5: Clos | O5: =IF(AND(C5=$B$47,H5<=$D$47),"ISLA",IF((AND(C5=$B$48,H5<=$D$48)),"ISLA",IF((AND(C5=$B$49,H5<=$D$49)),"ISLA","OSLA"))) -> ISLA
A6: 5 | B6: 1809G45782 | C6: P1 | D6: SSPO | E6: Orange Money add-on / Canal+ | F6: 43353.428 | G6: 43353.447 | H6: 26 | I6: Impossible d’effectuer le réabonnement canal+ via OM | J6: Inconnue | K6: Aucune | L6: SSPO | M6: Clos | O6: =IF(AND(C6=$B$47,H6<=$D$47),"ISLA",IF((AND(C6=$B$48,H6<=$D$48)),"ISLA",IF((AND(C6=$B$49,H6<=$D$49)),"ISLA","OSLA"))) -> ISLA
A7: 6 | B7: 1809G91082 | C7: P1 | D7: Supervision | E7: Simplissimo | F7: 43354.517 | G7: 43355.428 | H7: 1312 | I7: SOUCI AJOUT NOUVEL ABONNEMENT | J7: Erreur sur la mise en production de la Modification du Profil ADV_Entreprise | K7: Rollback | L7: DevOps | M7: Clos | O7: =IF(AND(C7=$B$47,H7<=$D$47),"ISLA",IF((AND(C7=$B$48,H7<=$D$48)),"ISLA",IF((AND(C7=$B$49,H7<=$D$49)),"ISLA","OSLA"))) -> OSLA
A8: 7 | B8: 1809H11114 | C8: P1 | D8: SSPO | E8: Orange Money add-on / Canal+ | F8: 43355.935 | G8: 43355.956 | H8: 30 | I8: Impossible d’effectuer le réabonnement canal+ via OM | J8: Problème de performance du logiciel strongswan | K8: Mise en place d'une solution de contournement | L8: SSPO | M8: Clos | O8: =IF(AND(C8=$B$47,H8<=$D$47),"ISLA",IF((AND(C8=$B$48,H8<=$D$48)),"ISLA",IF((AND(C8=$B$49,H8<=$D$49)),"ISLA","OSLA"))) -> ISLA
A9: 8 | B9: 1809H27183 | C9: P2 | D9: Supervision | E9: Navigation internet , Right Q , Oceane, Robot DASET | F9: 43356.503 | G9: 43356.524 | H9: 30 | I9: Internet via le LAN | J9: Dysfonctionnement sur un ESX | K9: désactivation de l’authentification AD au niveau du proxy | L9: SONATEL | M9: Clos | O9: =IF(AND(C9=$B$47,H9<=$D$47),"ISLA",IF((AND(C9=$B$48,H9<=$D$48)),"ISLA",IF((AND(C9=$B$49,H9<=$D$49)),"ISLA","OSLA"))) -> ISLA
A10: 9 | B10: 1809H50210 | C10: P1 | D10: Supervision | E10: Data Mobile | F10: 43357.419 | G10: 43357.422 | H10: 5 | I10: Chute du Trafic sur la sortie Dalein-Kedougou | J10: Coupure de fibre à 08Km de NIOKO vers MAKO | K10: Soudure de la fibre | L10: GNOC | M10: Clos | O10: =IF(AND(C10=$B$47,H10<=$D$47),"ISLA",IF((AND(C10=$B$48,H10<=$D$48)),"ISLA",IF((AND(C10=$B$49,H10<=$D$49)),"ISLA","OSLA"))) -> ISLA
A11: 10 | B11: 1809H87358 | C11: P2 | D11: Supervision | E11: Report Avantage | F11: 43328.471 | G11: 43328.688 | H11: 312 | I11: Impossible de recevoir ses avantages à partir du *118*1# | J11: Plantage du serveur d’application glass Fish | K11: Réinstallation du serveur d’application, Redéploiement du web service | L11: ASBD | M11: Clos | O11: =IF(AND(C11=$B$47,H11<=$D$47),"ISLA",IF((AND(C11=$B$48,H11<=$D$48)),"ISLA",IF((AND(C11=$B$49,H11<=$D$49)),"ISLA","OSLA"))) -> OSLA
A12: 11 | B12: 1809H84583 | C12: P2 | D12: SSPO | E12: MyOrange/Orange et moi | F12: 43359.333 | G12: 43359.358 | H12: 36 | I12: Impossible d'effectuer des operation de consultation de solde via l'application mobile Orange et moi | J12: Inconnue | K12: Aucune | L12: SSPO | M12: Clos | O12: =IF(AND(C12=$B$47,H12<=$D$47),"ISLA",IF((AND(C12=$B$48,H12<=$D$48)),"ISLA",IF((AND(C12=$B$49,H12<=$D$49)),"ISLA","OSLA"))) -> ISLA
A13: 12 | B13: 1809I21005 | C13: P1 | D13: SSPO | E13: Orange Money add-on / Bank to wallet / Ecobank | F13: 43360.884 | G13: 43360.93 | H13: 66 | I13: Impossible d’effectuer des transactions bancaires via OM | J13: Perte de connexion avec le partenaire Ecobank | K13: Rétablissement de la connexion | L13: SSPO | M13: Clos | O13: =IF(AND(C13=$B$47,H13<=$D$47),"ISLA",IF((AND(C13=$B$48,H13<=$D$48)),"ISLA",IF((AND(C13=$B$49,H13<=$D$49)),"ISLA","OSLA"))) -> ISLA
... A16: 15 | B16: 1809K99566 | C16: P1 | D16: Supervision | E16: Data Mobile | F16: 43371.899 | G16: 43371.913 | H16: 20 | I16: Chute du Trafic sur la sortie Dalein-Kedougou | J16: Inconnue | K16: Aucune | L16: GNOC | M16: Clos | O16: =IF(AND(C16=$B$47,H16<=$D$47),"ISLA",IF((AND(C16=$B$48,H16<=$D$48)),"ISLA",IF((AND(C16=$B$49,H16<=$D$49)),"ISLA","OSLA"))) -> ISLA
B47: P1 | C47: 2h | D47: 120
B48: P2 | C48: 4h | D48: 240
B49: P3 | C49: 2jr | D49: =1440*2 -> 2880
B50: P4 | C50: 3jr | D50: =3*1440 -> 4320

Sheet Octobre_2018
A1: N° | B1: N°TICKET | C1: PRIORITE | D1: Origine | E1: NOM SERVICES | F1: DATE & HEURE DEBUT | G1: DATE & HEURE FIN | H1: DUREE (mn) | I1: DESCRIPTION | J1: CAUSE DE L'INCIDENT | K1: ACTIONS CORRECTIVES | L1: TMC | M1: Statut | N1: Observation | O1: SLA
A2: 1 | B2: 1810L54442 | C2: P1 | D2: SSPO | E2: Orange Money add-on / Bank to wallet / Ecobank | F2: 43374.935 | G2: 43374.975 | H2: 58 | I2: Impossible d’effectuer des transactions bancaires via OM | J2: Perte de connexion avec le partenaire Ecobank | K2: Retablissement de la connexion | L2: SSPO | M2: Clos | O2: =IF(AND(C2=$B$48,H2<=$D$48),"ISLA",IF((AND(C2=$B$49,H2<=$D$49)),"ISLA",IF((AND(C2=$B$50,H2<=$D$50)),"ISLA","OSLA"))) -> ISLA
A3: 2 | B3: 1810L67181 | C3: P1 | D3: SSPO | E3: Orange Money add-on / Bank to wallet / Ecobank | F3: 43375.424 | G3: 43375.458 | H3: 49 | I3: Impossible d’effectuer des transactions bancaires via OM | J3: Perte de connexion avec le partenaire Ecobank | K3: Retablissement de la connexion | L3: SSPO | M3: Clos | O3: =IF(AND(C3=$B$48,H3<=$D$48),"ISLA",IF((AND(C3=$B$49,H3<=$D$49)),"ISLA",IF((AND(C3=$B$50,H3<=$D$50)),"ISLA","OSLA"))) -> ISLA
A4: 3 | B4: 1810L54442 | C4: P1 | D4: SSPO | E4: Orange Money add-on / Bank to wallet / Ecobank | F4: 43375.893 | G4: 43375.939 | H4: 66 | I4: Impossible d’effectuer des transactions bancaires via OM | J4: Perte de connexion avec le partenaire Ecobank | K4: Retablissement de la connexion | L4: SSPO | M4: Clos | O4: =IF(AND(C4=$B$48,H4<=$D$48),"ISLA",IF((AND(C4=$B$49,H4<=$D$49)),"ISLA",IF((AND(C4=$B$50,H4<=$D$50)),"ISLA","OSLA"))) -> ISLA
A5: 4 | B5: 1810L93817 | C5: P1 | D5: SSPO | E5: Orange Money add-on / Bank to wallet / Ecobank | F5: 43376.171 | G5: 43376.268 | H5: 140 | I5: Impossible d’effectuer des transactions bancaires via OM | J5: Perte de connexion avec le partenaire Ecobank | K5: Retablissement de la connexion | L5: SSPO | M5: Clos | O5: =IF(AND(C5=$B$48,H5<=$D$48),"ISLA",IF((AND(C5=$B$49,H5<=$D$49)),"ISLA",IF((AND(C5=$B$50,H5<=$D$50)),"ISLA","OSLA"))) -> OSLA
A6: 5 | B6: 1810M10095 | C6: P1 | D6: Supervision | E6: CMS (*111#), Achat de Pass via USSD (*222#), FFC (*191#), Consultation de pass (*222*5#), Orange Money (*144#, *142#, *143#) 10% d’Erecharge, report avantage (*118*1#), gameloft USSD (*111*6#), Transfert Data (*222*8#), MyOrange | F6: 43376.503 | G6: 43376.566 | H6: 90 | I6: Indisponibilté des services passant par le USSD | J6: Le Port VSI a été débranché du commutateur de Sonfonia GIN | K6: Reconnexion du câble | L6: ASBD | M6: Clos | O6: =IF(AND(C6=$B$48,H6<=$D$48),"ISLA",IF((AND(C6=$B$49,H6<=$D$49)),"ISLA",IF((AND(C6=$B$50,H6<=$D$50)),"ISLA","OSLA"))) -> ISLA
A7: 6 | B7: 1810M24633 | C7: P1 | D7: SSPO | E7: Paddock Services | F7: 43377.208 | G7: 43377.226 | H7: 26 | I7: Impossible d’utiliser les fonctionnalités SMS PADDOCK | J7: Inconnue | K7: Aucune | L7: SSPO | M7: Clos | O7: =IF(AND(C7=$B$48,H7<=$D$48),"ISLA",IF((AND(C7=$B$49,H7<=$D$49)),"ISLA",IF((AND(C7=$B$50,H7<=$D$50)),"ISLA","OSLA"))) -> ISLA
A8: 7 | B8: 1810M26542 | C8: P1 | D8: Supervision | E8: FFC | F8: 43377.278 | G8: 43377.319 | H8: 60 | I8: Indisponibilité du service Football Fans Club | J8: Indisponibilité du VPN OFC | K8: Aucune | L8: Support FFC | M8: Clos | O8: =IF(AND(C8=$B$48,H8<=$D$48),"ISLA",IF((AND(C8=$B$49,H8<=$D$49)),"ISLA",IF((AND(C8=$B$50,H8<=$D$50)),"ISLA","OSLA"))) -> ISLA
A9: 8 | B9: 1810O31583 | C9: P1 | D9: Sonatel | E9: Simplissimo | F9: 43378.324 | G9: 43378.453 | H9: 187 | I9: Dysfonctionnement sur le réseau | J9: F5 inaccessible : Investigations en cours pour la root cause | K9: Investigations en cours | L9: Sonatel | M9: Clos | O9: =IF(AND(C9=$B$48,H9<=$D$48),"ISLA",IF((AND(C9=$B$49,H9<=$D$49)),"ISLA",IF((AND(C9=$B$50,H9<=$D$50)),"ISLA","OSLA"))) -> OSLA
A10: 9 | B10: 1810M61840 | C10: P1 | D10: SSPO | E10: Paddock Services | F10: 43378.438 | G10: 43378.463 | H10: 37 | I10: Impossible d’utiliser les fonctionnalités SMS PADDOCK | J10: Inconnue | K10: Aucune | L10: SSPO | M10: Clos | O10: =IF(AND(C10=$B$48,H10<=$D$48),"ISLA",IF((AND(C10=$B$49,H10<=$D$49)),"ISLA",IF((AND(C10=$B$50,H10<=$D$50)),"ISLA","OSLA"))) -> ISLA
A11: 10 | B11: 1810L93817 | C11: P1 | D11: SSPO | E11: Orange Money add-on / Bank to wallet / Ecobank | F11: 43378.631 | G11: 43378.669 | H11: 56 | I11: Impossible d’effectuer des transactions bancaires via OM | J11: Perte de connexion avec le partenaire Ecobank | K11: Retablissement de la connexion | L11: SSPO | M11: Clos | O11: =IF(AND(C11=$B$48,H11<=$D$48),"ISLA",IF((AND(C11=$B$49,H11<=$D$49)),"ISLA",IF((AND(C11=$B$50,H11<=$D$50)),"ISLA","OSLA"))) -> ISLA
A12: 11 | B12: 1810M76373 | C12: P1 | D12: SSPO | E12: Paddock Services | F12: 43379.006 | G12: 43379.108 | H12: 147 | I12: Impossible d’utiliser les fonctionnalités SMS PADDOCK | J12: Inconnue | K12: Aucune | L12: SSPO | M12: Clos | O12: =IF(AND(C12=$B$48,H12<=$D$48),"ISLA",IF((AND(C12=$B$49,H12<=$D$49)),"ISLA",IF((AND(C12=$B$50,H12<=$D$50)),"ISLA","OSLA"))) -> OSLA
A13: 12 | B13: 1810M96636 | C13: P1 | D13: SSPO | E13: Orange Money add-on / Bank to wallet / Ecobank | F13: 43380.524 | G13: 43380.555 | H13: 45 | I13: Impossible d’effectuer des transactions bancaires via OM | J13: Perte de connexion avec le partenaire Ecobank | K13: Retablissement de la connexion | L13: SSPO | M13: Clos | O13: =IF(AND(C13=$B$48,H13<=$D$48),"ISLA",IF((AND(C13=$B$49,H13<=$D$49)),"ISLA",IF((AND(C13=$B$50,H13<=$D$50)),"ISLA","OSLA"))) -> ISLA
... A29: 28 | B29: 1810Q12441 | C29: P2 | D29: Supervision | E29: Data Mobile | F29: 43392.514 | G29: 43392.528 | H29: 20 | I29: Légère dégradation de la data mobile | J29: Plantage des switchs Sonfonia et Camayenne | K29: Redemarrage des switchs | L29: ASBD | M29: Clos | O29: =IF(AND(C29=$B$48,H29<=$D$48),"ISLA",IF((AND(C29=$B$49,H29<=$D$49)),"ISLA",IF((AND(C29=$B$50,H29<=$D$50)),"ISLA","OSLA"))) -> ISLA
A30: 29 | B30: 1810Q39527 | C30: P1 | D30: SSPO | E30: E-recharge | F30: 43394.325 | G30: 43394.332 | H30: 10 | I30: Echecs de 50% des notifications après transactions E-recharge | J30: Problème de connectivité de la plateforme Zebra et SMSC | K30: Aucune | L30: SSPO | M30: Clos | N30: Un ticket Probleme est en cours pour identifier et corriger cet incident recurrent | O30: =IF(AND(C30=$B$48,H30<=$D$48),"ISLA",IF((AND(C30=$B$49,H30<=$D$49)),"ISLA",IF((AND(C30=$B$50,H30<=$D$50)),"ISLA","OSLA"))) -> ISLA
A31: 30 | B31: 1810Q57364 | C31: P1 | D31: Supervision | E31: Consultation Frais retrait(*144*7*4*3#) & Transfert DATA | F31: 43395.389 | G31: 43395.604 | H31: 310 | I31: Consultation Frais retrait(*144*7*4*3#) & Transfert DATA | J31: Crash du serveur d’application suite à l’ajout d’un WS | K31: Redéploiement de Glassfish et des fichiers WAR | L31: ASBD | M31: Clos | O31: =IF(AND(C31=$B$48,H31<=$D$48),"ISLA",IF((AND(C31=$B$49,H31<=$D$49)),"ISLA",IF((AND(C31=$B$50,H31<=$D$50)),"ISLA","OSLA"))) -> OSLA
A32: 31 | B32: 1810Q81449 | C32: P2 | D32: Supervision | E32: E-Recharge ( C2S ) | F32: 43396.278 | G32: 43396.344 | H32: 95 | I32: Impossible d’effectuer les rechargements de crédit via le C2S (*200#) dans la zone de Matam et Kaloum | J32: souci de configuration de carte groupe dans la zone de Matam et Kaloum dû à un ATP | K32: Reconfiguration des cartes groupes | L32: CRPFS | M32: Clos | O32: =IF(AND(C32=$B$48,H32<=$D$48),"ISLA",IF((AND(C32=$B$49,H32<=$D$49)),"ISLA",IF((AND(C32=$B$50,H32<=$D$50)),"ISLA","OSLA"))) -> ISLA
A33: 32 | B33: 1810Q87419 | C33: P1 | D33: SSPO | E33: Orange Money add-on / Bank to Wallet / UBA | F33: 43396.399 | G33: 43396.622 | H33: 321 | I33: Impossible d’effectuer des transactions bancaires via OM | J33: Perte de connexion avec le partenaire UBA | K33: Rétablissement de la connexion | L33: SSPO | M33: Clos | O33: =IF(AND(C33=$B$48,H33<=$D$48),"ISLA",IF((AND(C33=$B$49,H33<=$D$49)),"ISLA",IF((AND(C33=$B$50,H33<=$D$50)),"ISLA","OSLA"))) -> OSLA
A34: 33 | B34: 1810R04923 | C34: P1 | D34: Supervision | E34: Agrobusiness | F34: 43396.92 | G34: 43397.014 | H34: 135 | I34: Menu *113# indisponible | J34: ATP (maintenance du serveur) | K34: Fin ATP | L34: Bankitech | M34: Clos | O34: =IF(AND(C34=$B$48,H34<=$D$48),"ISLA",IF((AND(C34=$B$49,H34<=$D$49)),"ISLA",IF((AND(C34=$B$50,H34<=$D$50)),"ISLA","OSLA"))) -> OSLA
A35: 34 | B35: 1810R55643 | C35: P1 | D35: SSPO | E35: Orange Money add-on / Bank to wallet / Ecobank | F35: 43398.637 | G35: 43398.678 | H35: 59 | I35: Impossible d’effectuer des transactions bancaires via OM | J35: Perte de connexion avec le partenaire Ecobank | K35: Rétablissement de la connexion | L35: SSPO | M35: Clos | O35: =IF(AND(C35=$B$48,H35<=$D$48),"ISLA",IF((AND(C35=$B$49,H35<=$D$49)),"ISLA",IF((AND(C35=$B$50,H35<=$D$50)),"ISLA","OSLA"))) -> ISLA
A36: 35 | B36: 1810R70619 | C36: P1 | D36: Guinee Games | E36: Orange Money add-on / Web payment Guineegames | F36: 43398.535 | G36: 43399.455 | H36: 1325 | I36: Acces impossible à la page www.webpayement.orange-money.com | J36: Instance de sécurité Mod inactive | K36: Activation de l’instance de sécurité Mod | L36: SSPO | M36: Clos | O36: =IF(AND(C36=$B$48,H36<=$D$48),"ISLA",IF((AND(C36=$B$49,H36<=$D$49)),"ISLA",IF((AND(C36=$B$50,H36<=$D$50)),"ISLA","OSLA"))) -> OSLA
A37: 36 | B37: 1810S06267 | C37: P2 | D37: Supervision | E37: SMS | F37: 43399.966 | G37: 43401.25 | H37: =(G37-F37)*1440 -> 1849 | I37: Légère dégradation dans la réception des notifications sms après opérations OM Cash IN / Cash OUT | J37: Dysfonctionnements enregistrés sur le serveur USSD1 de Sonfonia (deconnexion du serveur AS USSD1 au UGS) | K37: Correction des erreurs MYSQL, suppression des vielles données et redemarrage du USSD Server et du SMS Server | L37: GNOC | M37: Clos | O37: =IF(AND(C37=$B$48,H37<=$D$48),"ISLA",IF((AND(C37=$B$49,H37<=$D$49)),"ISLA",IF((AND(C37=$B$50,H37<=$D$50)),"ISLA","OSLA"))) -> OSLA
A38: 37 | B38: 1810S04241 | C38: P1 | D38: GOS | E38: OTAP | F38: 43401.201 | G38: 43401.349 | H38: =(G38-F38)*1440 -> 213 | I38: Impossible d’envoyer les paramètres de configuration aux abonnés | J38: Perte de connexion entre SMSC et ADC GOS (Dû à un ATP ) | K38: Finalisation de l'ATP | L38: GOS | M38: Clos | O38: =IF(AND(C38=$B$48,H38<=$D$48),"ISLA",IF((AND(C38=$B$49,H38<=$D$49)),"ISLA",IF((AND(C38=$B$50,H38<=$D$50)),"ISLA","OSLA"))) -> OSLA
A39: 38 | B39: 1810S33825 | C39: P1 | D39: SSPO | E39: Orange Money add-on / Canal+ | F39: 43402.596 | G39: 43402.613 | H39: 24 | I39: Impossible d’effectuer de réabonnement canal via OM | J39: Inconnue | K39: En attente du retour de SSPO | L39: SSPO | M39: OK
A40: 39 | B40: 1810S99842 | C40: P1 | D40: SSPO | E40: Orange et Moi | F40: 43404.633 | G40: 43404.669 | H40: =(G40-F40)*1440 -> 52 | I40: Impossible de consulter son solde via l’application Orange et Moi | J40: En attente du retour du GOS | K40: En attente du retour du GOS | L40: GOS | M40: Clos | O40: =IF(AND(C40=$B$48,H40<=$D$48),"ISLA",IF((AND(C40=$B$49,H40<=$D$49)),"ISLA",IF((AND(C40=$B$50,H40<=$D$50)),"ISLA","OSLA"))) -> ISLA
A41: 40 | B41: 1810S91015 | C41: P2 | D41: SSPO | E41: E-recharge | F41: 43404.47 | G41: 43404.501 | H41: =(G41-F41)*1440 -> 45 | I41: Echecs de 50% des notifications après transactions E-recharge | J41: Problème de connectivité de la plateforme Zebra et SMSC | K41: Aucune | L41: GNOC | M41: Clos | N41: Un ticket Probleme est en cours pour identifier et corriger cet incident recurrent | O41: =IF(AND(C41=$B$48,H41<=$D$48),"ISLA",IF((AND(C41=$B$49,H41<=$D$49)),"ISLA",IF((AND(C41=$B$50,H41<=$D$50)),"ISLA","OSLA"))) -> ISLA
B48: P1 | C48: 2h | D48: 120
B49: P2 | C49: 4h | D49: 240
B50: P3 | C50: 2jr | D50: =1440*2 -> 2880
B51: P4 | C51: 3jr | D51: =3*1440 -> 4320

Sheet Novembre_2018
A1: N° | B1: N°TICKET | C1: PRIORITE | D1: Origine | E1: NOM SERVICES | F1: DATE & HEURE DEBUT | G1: DATE & HEURE FIN | H1: DUREE (mn) | I1: DESCRIPTION | J1: CAUSE DE L'INCIDENT | K1: ACTIONS CORRECTIVES | L1: TMC | M1: Statut | N1: Observation | O1: SLA
A2: 1 | B2: 1811T13512 | C2: P1 | D2: Supervision | E2: Consultation Frais retrait OM (*144*7*4*3*Montant#) | F2: 43405.44 | G2: 43405.462 | H2: 31 | I2: Indisponibilité du service Consultation Frais Retrait OM | J2: Indisponibilité du Web service | K2: Aucune | L2: ASBD | M2: Clos | O2: =IF(AND(C2=$B$51,H2<=$D$51),"ISLA",IF((AND(C2=$B$52,H2<=$D$52)),"ISLA",IF((AND(C2=$B$53,H2<=$D$53)),"ISLA","OSLA"))) -> ISLA
A3: 2 | B3: 1811T21378 | C3: P1 | D3: SSPO | E3: Orange et Moi | F3: 43405.856 | G3: 43405.891 | H3: 50 | I3: Impossible de consulter son solde via l’application MyOrange | J3: En attente du retour du GOS | K3: En attente du retour du GOS | L3: GOS | M3: Clos | O3: =IF(AND(C3=$B$51,H3<=$D$51),"ISLA",IF((AND(C3=$B$52,H3<=$D$52)),"ISLA",IF((AND(C3=$B$53,H3<=$D$53)),"ISLA","OSLA"))) -> ISLA
A4: 3 | B4: 1811T47021(1811T45839 |1811T41002) | C4: P1 | D4: Supervision | E4: USSD | F4: 43406.628 | G4: 43406.896 | H4: 192 | I4: Impossible d’accéder aux services qui passe par le canal USSD | J4: Augmentation du taux d'echec"Time out"sur la plateforme USSD qui à causé une perturbation sur les services | K4: Aucune | L4: GNOC | M4: Clos | O4: =IF(AND(C4=$B$51,H4<=$D$51),"ISLA",IF((AND(C4=$B$52,H4<=$D$52)),"ISLA",IF((AND(C4=$B$53,H4<=$D$53)),"ISLA","OSLA"))) -> OSLA
A5: 4 | B5: 1811T67588 | C5: P1 | D5: SSPO | E5: Orange Money add-on / Bank to wallet / Ecobank | F5: 43408.549 | G5: 43408.585 | H5: 52 | I5: Impossible d’effectuer des transactions bancaires via OM | J5: Perte de connexion avec le partenaire | K5: Rétablissement de connexion | L5: SSPO | M5: Clos | O5: =IF(AND(C5=$B$51,H5<=$D$51),"ISLA",IF((AND(C5=$B$52,H5<=$D$52)),"ISLA",IF((AND(C5=$B$53,H5<=$D$53)),"ISLA","OSLA"))) -> ISLA
A6: 5 | B6: 1811U15675 | C6: P1 | D6: Supervision | E6: Orange Money(*144#, *142#, *143#) | F6: 43410.446 | G6: 43410.449 | H6: 5 | I6: Impossible d’effectuer des transactions Orange Money | J6: Augmentation du taux d'echec"Time out"sur la plateforme USSD qui à causer une perturbation sur les services | K6: Aucune | L6: SSPO | M6: Clos | O6: =IF(AND(C6=$B$51,H6<=$D$51),"ISLA",IF((AND(C6=$B$52,H6<=$D$52)),"ISLA",IF((AND(C6=$B$53,H6<=$D$53)),"ISLA","OSLA"))) -> ISLA
A7: 6 | B7: 1811U17195 | C7: P1 | D7: SSPO | E7: Orange Money add-on / Bank to wallet / Ecobank | F7: 43410.472 | G7: 43410.533 | H7: 88 | I7: Impossible d’effectuer des transactions bancaires via OM | J7: Perte de connexion avec le partenaire | K7: Rétablissement de la connexion | L7: SSPO | M7: Clos | O7: =IF(AND(C7=$B$51,H7<=$D$51),"ISLA",IF((AND(C7=$B$52,H7<=$D$52)),"ISLA",IF((AND(C7=$B$53,H7<=$D$53)),"ISLA","OSLA"))) -> ISLA
A8: 7 | B8: 1811U41019 | C8: P1 | D8: Supervision | E8: Orange Money(*144#, *142#, *143#) | F8: 43411.368 | G8: 43411.406 | H8: 55 | I8: Impossible d’effectuer des transactions Orange Money | J8: souci réseau, indisponibilité Firewall GIN | K8: Redemarrage du firewall GIN de camayenne | L8: ASBD | M8: Clos | O8: =IF(AND(C8=$B$51,H8<=$D$51),"ISLA",IF((AND(C8=$B$52,H8<=$D$52)),"ISLA",IF((AND(C8=$B$53,H8<=$D$53)),"ISLA","OSLA"))) -> ISLA
A9: 8 | B9: 1811U65670/1811U66370 | C9: P1 | D9: Supervision | E9: Orange Money add-on / Canal + | F9: 43412.26 | G9: 43412.355 | H9: 136 | I9: Impossible d’effectuer de réabonnement canal via OM | J9: Travaux planifiés non maitrisés sur l’infrastructure OpenWatt | K9: RollBack | L9: SSPO | M9: Clos | O9: =IF(AND(C9=$B$51,H9<=$D$51),"ISLA",IF((AND(C9=$B$52,H9<=$D$52)),"ISLA",IF((AND(C9=$B$53,H9<=$D$53)),"ISLA","OSLA"))) -> OSLA
A10: 9 | B10: 1811U65670/1811U66561 | C10: P1 | D10: Supervision | E10: Orange Money add-on / Bank to wallet / UBA | F10: 43412.26 | G10: 43412.355 | H10: 136 | I10: Indisponibilité du service Bank to wallet/UBA | J10: Travaux planifiés non maitrisés sur l’infrastructure OpenWatt | K10: RollBack | L10: SSPO | M10: Clos | O10: =IF(AND(C10=$B$51,H10<=$D$51),"ISLA",IF((AND(C10=$B$52,H10<=$D$52)),"ISLA",IF((AND(C10=$B$53,H10<=$D$53)),"ISLA","OSLA"))) -> OSLA
A11: 10 | B11: 1811U65670 | C11: P1 | D11: SSPO | E11: Orange Money add-on / WebPayment | F11: 43412.26 | G11: 43412.355 | H11: 136 | I11: Indisponibilité du service WebPayement | J11: Travaux planifiés non maitrisés sur l’infrastructure OpenWatt | K11: RollBack | L11: SSPO | M11: Clos | O11: =IF(AND(C11=$B$51,H11<=$D$51),"ISLA",IF((AND(C11=$B$52,H11<=$D$52)),"ISLA",IF((AND(C11=$B$53,H11<=$D$53)),"ISLA","OSLA"))) -> OSLA
A12: 11 | B12: 1811U65670 | C12: P1 | D12: Supervision | E12: MyOrange | F12: 43412.26 | G12: 43412.355 | H12: 136 | I12: Indisponibilité du service MyOrange | J12: Travaux planifiés non maitrisés sur l’infrastructure OpenWatt | K12: RollBack | L12: SSPO | M12: Clos | O12: =IF(AND(C12=$B$51,H12<=$D$51),"ISLA",IF((AND(C12=$B$52,H12<=$D$52)),"ISLA",IF((AND(C12=$B$53,H12<=$D$53)),"ISLA","OSLA"))) -> OSLA
A13: 12 | B13: 1811U77203 | C13: P2 | D13: SSPO | E13: AppsOrange | F13: 43412.26 | G13: 43412.355 | H13: 136 | I13: Impossible de rafraichir le catalogue de l’application AppsOrange | J13: Travaux planifiés non maitrisés sur l’infrastructure OpenWatt | K13: RollBack | L13: SSPO | M13: Clos | O13: =IF(AND(C13=$B$51,H13<=$D$51),"ISLA",IF((AND(C13=$B$52,H13<=$D$52)),"ISLA",IF((AND(C13=$B$53,H13<=$D$53)),"ISLA","OSLA"))) -> ISLA
... A28: 27 | B28: 1811X08560 | C28: P1 | D28: SSPO | E28: Orange Money add-on / Bank to wallet / Ecobank | F28: 43422.053 | G28: 43422.066 | H28: 18 | I28: Impossible d’effectuer des transactions bancaires via OM | J28: Perte de connexion avec le partenaire | K28: Rétablissement de connexion avec le partenaire | L28: SSPO | M28: Clos | O28: =IF(AND(C28=$B$51,H28<=$D$51),"ISLA",IF((AND(C28=$B$52,H28<=$D$52)),"ISLA",IF((AND(C28=$B$53,H28<=$D$53)),"ISLA","OSLA"))) -> ISLA
A29: 28 | B29: 1811X15286 | C29: P2 | D29: GOS | E29: CMS | F29: 43422.521 | G29: 43422.578 | H29: =(G29-F29)*1440 -> 83 | I29: Instabilité dans la souscription au service et la réception des contenus (*111#) | J29: Réception de requêtes https sur l’interface du SDP entrainant le redémarrage du module AGW. | K29: Une reconfiguration a été faite pour empêcher la réception des requêtes https sur l’interface du SDP | L29: GOS | M29: Clos | O29: =IF(AND(C29=$B$51,H29<=$D$51),"ISLA",IF((AND(C29=$B$52,H29<=$D$52)),"ISLA",IF((AND(C29=$B$53,H29<=$D$53)),"ISLA","OSLA"))) -> ISLA
A30: 29 | B30: 1811X17891 | C30: P1 | D30: SSPO | E30: Orange Money add-on / Bank to wallet / Ecobank | F30: 43422.742 | G30: 43425.76 | H30: =(G30-F30)*1440 -> 4346 | I30: Impossible d’effectuer des transactions bancaires via OM | J30: Perte de connexion dû à la migration de l’application bancaire principale du partenaire | K30: Rétablissement de connexion avec le partenaire | L30: SSPO | M30: Clos | O30: =IF(AND(C30=$B$51,H30<=$D$51),"ISLA",IF((AND(C30=$B$52,H30<=$D$52)),"ISLA",IF((AND(C30=$B$53,H30<=$D$53)),"ISLA","OSLA"))) -> OSLA
A31: 30 | B31: 1811X19595 | C31: P1 | D31: SSPO | E31: E-recharge | F31: 43422.895 | G31: 43422.944 | H31: =(G31-F31)*1440 -> 70 | I31: Echec de 50% des notifications après transactions E-recharge | J31: Problème de connectivité de la plateforme Zebra et SMSC | K31: Aucune | L31: GNOC | M31: Clos | O31: =IF(AND(C31=$B$51,H31<=$D$51),"ISLA",IF((AND(C31=$B$52,H31<=$D$52)),"ISLA",IF((AND(C31=$B$53,H31<=$D$53)),"ISLA","OSLA"))) -> ISLA
A32: 31 | B32: 1811Y00263 | C32: P1 | D32: SSPO | E32: E-recharge | F32: 43425.655 | G32: 43425.675 | H32: =(G32-F32)*1440 -> 29 | I32: Echec de 50% de réception de notifications après transactions E-recharge | J32: Problème de connectivité de la plateforme Zebra et SMSC | K32: Aucune | L32: GNOC | M32: Clos | O32: =IF(AND(C32=$B$51,H32<=$D$51),"ISLA",IF((AND(C32=$B$52,H32<=$D$52)),"ISLA",IF((AND(C32=$B$53,H32<=$D$53)),"ISLA","OSLA"))) -> ISLA
A33: 32 | B33: 1811Y20305 | C33: P1 | D33: Supervision | E33: Orange Money | F33: 43426.494 | G33: 43426.529 | H33: =(G33-F33)*1440 -> 50 | I33: Dégradation du service Orange Money | J33: Soucis sur le HA et basculement automatique sur le firewall backup Camayenne. | K33: Rebasculement sur le firewall primaire et reconfiguration du HA | L33: ASBD | M33: Clos | O33: =IF(AND(C33=$B$51,H33<=$D$51),"ISLA",IF((AND(C33=$B$52,H33<=$D$52)),"ISLA",IF((AND(C33=$B$53,H33<=$D$53)),"ISLA","OSLA"))) -> ISLA
A34: 33 | B34: 1811Y20305 | C34: P1 | D34: Supervision | E34: MyOrange | F34: 43426.494 | G34: 43426.529 | H34: =(G34-F34)*1440 -> 50 | I34: Dégradation du service Orange & Moi | J34: Soucis sur le HA et basculement automatique sur le firewall backup Camayenne. | K34: Rebasculement sur le firewall primaire et reconfiguration du HA | L34: ASBD | M34: Clos | O34: =IF(AND(C34=$B$51,H34<=$D$51),"ISLA",IF((AND(C34=$B$52,H34<=$D$52)),"ISLA",IF((AND(C34=$B$53,H34<=$D$53)),"ISLA","OSLA"))) -> ISLA
A35: 34 | B35: 1811Y22022 | C35: P1 | D35: Supervision | E35: Data Mobile, Voix | F35: 43426.538 | G35: 43426.594 | H35: =(G35-F35)*1440 -> 80 | I35: Dégradation de la QOS Data, Voix dans les zones de Labé,Siguiri,Kankan,Kamsar,Nzerekoré | J35: Coupure de la fibre à 42Km de Mako vers NiCloso (Sénégal ) | K35: Basculement de trafic sur Camayenne puis soudure de la fibre | L35: GNOC | M35: Clos | O35: =IF(AND(C35=$B$51,H35<=$D$51),"ISLA",IF((AND(C35=$B$52,H35<=$D$52)),"ISLA",IF((AND(C35=$B$53,H35<=$D$53)),"ISLA","OSLA"))) -> ISLA
A36: 35 | B36: 1811X17891 | C36: P1 | D36: SSPO | E36: Orange Money add-on / Bank to wallet / Ecobank | F36: 43427.603 | G36: 43427.631 | H36: =(G36-F36)*1440 -> 40 | I36: Impossible d’effectuer des transactions bancaires via OM | J36: Perte de connexion dû à la migration de l’application bancaire principale du partenaire | K36: Rétablissement de Connexion avec le partenaire | L36: SSPO | M36: Clos | O36: =IF(AND(C36=$B$51,H36<=$D$51),"ISLA",IF((AND(C36=$B$52,H36<=$D$52)),"ISLA",IF((AND(C36=$B$53,H36<=$D$53)),"ISLA","OSLA"))) -> ISLA
A37: 36 | B37: 1811Y60838 | C37: P1 | D37: SSPO | E37: Orange Money add-on / Bank to wallet / Ecobank | F37: 43427.896 | G37: 43427.972 | H37: =(G37-F37)*1440 -> 110 | I37: Non réception de notifications SMS après transactions Ecobank | J37: Problème de connectivité de la plateforme tango au SMSC | K37: Aucune | L37: SSPO | M37: Clos | O37: =IF(AND(C37=$B$51,H37<=$D$51),"ISLA",IF((AND(C37=$B$52,H37<=$D$52)),"ISLA",IF((AND(C37=$B$53,H37<=$D$53)),"ISLA","OSLA"))) -> ISLA
A38: 37 | B38: 1811Y60839 | C38: P1 | D38: SSPO | E38: Orange Money add-on / Bank to wallet / UBA | F38: 43427.896 | G38: 43427.972 | H38: =(G38-F38)*1440 -> 110 | I38: Non réception de notifications SMS après transactions UBA | J38: Problème de connectivité de la plateforme tango au SMSC | K38: Aucune | L38: SSPO | M38: Clos | O38: =IF(AND(C38=$B$51,H38<=$D$51),"ISLA",IF((AND(C38=$B$52,H38<=$D$52)),"ISLA",IF((AND(C38=$B$53,H38<=$D$53)),"ISLA","OSLA"))) -> ISLA
A39: 38 | B39: 1811Y60838 | C39: P1 | D39: Supervision | E39: Orange Money P2P | F39: 43427.896 | G39: 43427.972 | H39: =(G39-F39)*1440 -> 110 | I39: Non réception de notifications SMS après transfert d'argent | J39: Problème de connectivité de la plateforme tango au SMSC | K39: Aucune | L39: GNOC/SSPO | M39: Clos | O39: =IF(AND(C39=$B$51,H39<=$D$51),"ISLA",IF((AND(C39=$B$52,H39<=$D$52)),"ISLA",IF((AND(C39=$B$53,H39<=$D$53)),"ISLA","OSLA"))) -> ISLA
A40: 39 | B40: 1811Y62863 | C40: P1 | D40: Supervision | E40: E-recharge | F40: 43428.135 | G40: 43428.158 | H40: =(G40-F40)*1440 -> 33 | I40: Echec de 50% des notifications après transactions E-recharge | J40: Problème de connectivité de la plateforme Zebra au SMSC | K40: Aucune | L40: GNOC | M40: Clos | O40: =IF(AND(C40=$B$51,H40<=$D$51),"ISLA",IF((AND(C40=$B$52,H40<=$D$52)),"ISLA",IF((AND(C40=$B$53,H40<=$D$53)),"ISLA","OSLA"))) -> ISLA
... A42: 41 | B42: 1811Y64748 | C42: P1 | D42: Supervision | E42: E-recharge | F42: 43428.397 | G42: 43428.402 | H42: =(G42-F42)*1440 -> 7 | I42: Echec de 50% des notifications après transactions E-recharge | J42: Problème de connectivité de la plateforme Zebra au SMSC | K42: Aucune | L42: GNOC | M42: Clos | O42: =IF(AND(C42=$B$51,H42<=$D$51),"ISLA",IF((AND(C42=$B$52,H42<=$D$52)),"ISLA",IF((AND(C42=$B$53,H42<=$D$53)),"ISLA","OSLA"))) -> ISLA
A43: 42 | B43: 1811Y88207 | C43: P1 | D43: Supervision | E43: Orange Money add-on / StarTimes | F43: 43430.008 | G43: 43430.266 | H43: 371 | I43: Impossible d’effectuer le réabonnement StarTimes via OM | J43: L'indisponibilité était due à un ATP coté StarTimes | K43: Fin de l'ATP | L43: SUPPORT STARTIMES | M43: Clos | O43: =IF(AND(C43=$B$51,H43<=$D$51),"ISLA",IF((AND(C43=$B$52,H43<=$D$52)),"ISLA",IF((AND(C43=$B$53,H43<=$D$53)),"ISLA","OSLA"))) -> OSLA
A44: 43 | B44: 1811Z21149 | C44: P1 | D44: Supervision | E44: Agrobusiness | F44: 43430.734 | G44: 43433.692 | H44: 4259 | I44: Indisponibilité du service Agrobusiness (*113#) | J44: Non renouvellement de l’hébergement du Service | K44: renouvellement de l’hébergement | L44: BANKITECH | M44: Clos | O44: =IF(AND(C44=$B$51,H44<=$D$51),"ISLA",IF((AND(C44=$B$52,H44<=$D$52)),"ISLA",IF((AND(C44=$B$53,H44<=$D$53)),"ISLA","OSLA"))) -> OSLA
A45: 44 | B45: 1811Z21149 | C45: P1 | D45: Supervision | E45: Voix, Data, SMS, USSD, E-Recharge | F45: 43431.299 | G45: 43431.316 | H45: 25 | I45: Indisponibilité des services Voix, Data, Sms et Ussd pour les PQ suivants : 628,626,6205 à 6209,6297 à 6299 et quelque numéro du personnelle | J45: Redémarrage de la base TT de l’OCS3 | K45: Aucune | L45: GNOC | M45: Clos | O45: =IF(AND(C45=$B$51,H45<=$D$51),"ISLA",IF((AND(C45=$B$52,H45<=$D$52)),"ISLA",IF((AND(C45=$B$53,H45<=$D$53)),"ISLA","OSLA"))) -> ISLA
A46: 45 | B46: 1811A17835 | C46: P1 | D46: Supervision | E46: Gameloft | F46: 43434.457 | G46: 43438.551 | H46: 5896 | I46: Indisponibilité du service Gameloft (*111*6#) | J46: Des changements récents dans la redirection selon MCO ont affecté plusieurs portails, dont OGN USSD. | K46: Correction des changements éffectués | L46: GAMELOFT | M46: Clos | O46: =IF(AND(C46=$B$51,H46<=$D$51),"ISLA",IF((AND(C46=$B$52,H46<=$D$52)),"ISLA",IF((AND(C46=$B$53,H46<=$D$53)),"ISLA","OSLA"))) -> OSLA
A47: 46 | B47: 1811A28820 | C47: P2 | D47: SSPO | E47: E-recharge | F47: 43434.826 | G47: 43434.947 | H47: =(G47-F47)*1440 -> 173 | I47: 3% d'Echecs sur les transactions E-recharge | J47: Temps de réponse élevé entre Zébra et IN | K47: Aucune | L47: GNOC | M47: Clos | O47: =IF(AND(C47=$B$51,H47<=$D$51),"ISLA",IF((AND(C47=$B$52,H47<=$D$52)),"ISLA",IF((AND(C47=$B$53,H47<=$D$53)),"ISLA","OSLA"))) -> ISLA
A48: 47 | B48: 1811A29160 | C48: P1 | D48: Supervision | E48: Transfert Data & Report Avantage | F48: 43434.841 | G48: 43434.938 | H48: =(G48-F48)*1440 -> 140 | I48: Instabilités sur les services transfert data(*222*8#) et report avantage(*118*1#) | J48: Instabilité du Serveur WS | K48: Aucune | L48: ASBD | M48: Clos | O48: =IF(AND(C48=$B$51,H48<=$D$51),"ISLA",IF((AND(C48=$B$52,H48<=$D$52)),"ISLA",IF((AND(C48=$B$53,H48<=$D$53)),"ISLA","OSLA"))) -> OSLA
B51: P1 | C51: 2h | D51: 120
B52: P2 | C52: 4h | D52: 240
B53: P3 | C53: 2jr | D53: =1440*2 -> 2880
B54: P4 | C54: 3jr | D54: =3*1440 -> 4320

Sheet Decembre_2018
A1: N° | B1: N°TICKET | C1: PRIORITE | D1: Origine | E1: NOM SERVICES | F1: DATE & HEURE DEBUT | G1: DATE & HEURE FIN | H1: DUREE (mn) | I1: DESCRIPTION | J1: CAUSE DE L'INCIDENT | K1: ACTIONS CORRECTIVES | L1: TMC | M1: Statut | N1: Observation | O1: SLA
A2: 1 | B2: 1812A26878 | C2: P1 | D2: Supervision | E2: Orange Money , Otap, MyOrange ,MFM, webtop | F2: 43435.427 | G2: 43435.5 | H2: =(G2-F2)*1440 -> 105 | I2: Indisponibilité de la Plateforme Orange Infra | J2: Hausse de température dans la salle hébergeant la plateforme orange infra à Sonfonia provoquant ainsi l’arrêt des serveurs de la plateforme | K2: Redémarrage des serveurs arrêtés / Redémarrage des VMs de chaque service impacté / Remise en ligne des différents services | L2: GOS | M2: Clos | O2: =IF(AND(C2=$B$58,H2<=$D$58),"ISLA",IF((AND(C2=$B$59,H2<=$D$59)),"ISLA",IF((AND(C2=$B$60,H2<=$D$60)),"ISLA","OSLA"))) -> ISLA
A3: 2 | B3: 1812A26878 | C3: P1 | D3: Supervision | E3: Nomad | F3: 43435.427 | G3: 43435.958 | H3: =(G3-F3)*1440 -> 764 | I3: Indisponibilité de la Plateforme Orange Infra | J3: Hausse de température dans la salle hébergeant la plateforme orange infra à Sonfonia provoquant ainsi l’arrêt des serveurs de la plateforme | K3: Redémarrage des serveurs arrêtés / Redémarrage des VMs de chaque service impacté / Remise en marche du serveur tomcat | L3: GOS | M3: Clos | O3: =IF(AND(C3=$B$58,H3<=$D$58),"ISLA",IF((AND(C3=$B$59,H3<=$D$59)),"ISLA",IF((AND(C3=$B$60,H3<=$D$60)),"ISLA","OSLA"))) -> OSLA
A4: 3 | B4: 1812A55704 | C4: P1 | D4: Supervision | E4: E-recharge | F4: 43436.625 | G4: 43436.635 | H4: 15 | I4: Echec des transactions E-Recharge avec un impact de 100% | J4: Temps de réponse élevé entre Zébra et IN | K4: Aucune | L4: GNOC | M4: Clos | O4: =IF(AND(C4=$B$58,H4<=$D$58),"ISLA",IF((AND(C4=$B$59,H4<=$D$59)),"ISLA",IF((AND(C4=$B$60,H4<=$D$60)),"ISLA","OSLA"))) -> ISLA
A5: 4 | B5: 1812A88731 | C5: P1 | D5: OLS | E5: Mobile TV | F5: 43437.413 | G5: 43438.506 | H5: 1573 | I5: Indisponibilité de la chaine RTG sur Mobile TV | J5: Perte du signal de la chaîne | K5: Aucune | L5: ASBD | M5: Clos | O5: =IF(AND(C5=$B$58,H5<=$D$58),"ISLA",IF((AND(C5=$B$59,H5<=$D$59)),"ISLA",IF((AND(C5=$B$60,H5<=$D$60)),"ISLA","OSLA"))) -> OSLA
A6: 5 | B6: 1812A79547 | C6: P1 | D6: SSPO | E6: Orange Money add-on / Bank to wallet / Ecobank | F6: 43437.486 | G6: 43437.522 | H6: 51 | I6: Impossible d’effectuer des transactions bancaires via OM | J6: Perte de connexion avec le partenaire | K6: Rétablissement de la connexion avec le partenaire | L6: SSPO | M6: Clos | O6: =IF(AND(C6=$B$58,H6<=$D$58),"ISLA",IF((AND(C6=$B$59,H6<=$D$59)),"ISLA",IF((AND(C6=$B$60,H6<=$D$60)),"ISLA","OSLA"))) -> ISLA
A7: 6 | B7: 1812A64463 | C7: P1 | D7: SSPO | E7: Orange Money add-on / Bank to wallet / Ecobank | F7: 43437.736 | G7: 43437.772 | H7: 52 | I7: Impossible d’effectuer des transactions bancaires via OM | J7: Perte de connexion avec le partenaire | K7: Rétablissement de la connexion avec le partenaire | L7: SSPO | M7: Clos | O7: =IF(AND(C7=$B$58,H7<=$D$58),"ISLA",IF((AND(C7=$B$59,H7<=$D$59)),"ISLA",IF((AND(C7=$B$60,H7<=$D$60)),"ISLA","OSLA"))) -> ISLA
A8: 7 | B8: 1812A97593 | C8: P1 | D8: SSPO | E8: Orange Money add-on / Bank to wallet / Ecobank | F8: 43437.926 | G8: 43437.966 | H8: 57 | I8: Impossible d’effectuer des transactions bancaires via OM | J8: Perte de connexion avec le partenaire | K8: Rétablissement de la connexion avec le partenaire | L8: SSPO | M8: Clos | O8: =IF(AND(C8=$B$58,H8<=$D$58),"ISLA",IF((AND(C8=$B$59,H8<=$D$59)),"ISLA",IF((AND(C8=$B$60,H8<=$D$60)),"ISLA","OSLA"))) -> ISLA
A9: 8 | B9: 1812B51272/1812B50786 | C9: P1 | D9: SSPO | E9: Orange Money add-on / Canal+ | F9: 43439.51 | G9: 43439.601 | H9: 130 | I9: Impossible d’effectuer son réabonnement canal+ via OM | J9: Perte de connexion dû à un probleme de Firewall du partenaire Canal | K9: Redemarrage du Firewall | L9: SSPO | M9: Clos | O9: =IF(AND(C9=$B$58,H9<=$D$58),"ISLA",IF((AND(C9=$B$59,H9<=$D$59)),"ISLA",IF((AND(C9=$B$60,H9<=$D$60)),"ISLA","OSLA"))) -> OSLA
A10: 9 | B10: 1812B58089 | C10: P1 | D10: GOS | E10: KMC | F10: 43439.623 | G10: 43439.689 | H10: =(G10-F10)*1440 -> 95 | I10: Impossible d’accéder à l’interface WEB de l’outil de gestion des contenus centralisés | J10: Inconsistance file system sur la Vm de base de données | K10: Redémarrage des Vms et la BD | L10: GOS | M10: Clos | O10: =IF(AND(C10=$B$58,H10<=$D$58),"ISLA",IF((AND(C10=$B$59,H10<=$D$59)),"ISLA",IF((AND(C10=$B$60,H10<=$D$60)),"ISLA","OSLA"))) -> ISLA
A11: 10 | B11: 1812C04414 | C11: P1 | D11: SSPO | E11: Orange Money add-on / Bank to wallet / Ecobank | F11: 43441.211 | G11: 43441.248 | H11: =(G11-F11)*1440 -> 53 | I11: Impossible d’effectuer des transactions bancaires via OM | J11: Perte de connexion avec le partenaire | K11: Rétablissement de la connexion avec le partenaire | L11: SSPO | M11: Clos | O11: =IF(AND(C11=$B$58,H11<=$D$58),"ISLA",IF((AND(C11=$B$59,H11<=$D$59)),"ISLA",IF((AND(C11=$B$60,H11<=$D$60)),"ISLA","OSLA"))) -> ISLA
A12: 11 | B12: 1812C31681/1812C33416 | C12: P1 | D12: SSPO | E12: E-recharge | F12: 43441.803 | G12: 43441.889 | H12: =(G12-F12)*1440 -> 124 | I12: Echecs à 30% des Transactions E-recharge | J12: Problème de connectivité en la plateforme IN & Zebra | K12: Redémarrage du processus smpp de transfère de demandes ws à olc | L12: ZTE | M12: Clos | O12: =IF(AND(C12=$B$58,H12<=$D$58),"ISLA",IF((AND(C12=$B$59,H12<=$D$59)),"ISLA",IF((AND(C12=$B$60,H12<=$D$60)),"ISLA","OSLA"))) -> OSLA
A13: 12 | B13: 1812C52212 | C13: P1 | D13: Supervision | E13: Orange Money add-on / Bank to wallet / Ecobank & UBA | F13: 43445.708 | G13: 43445.865 | H13: 225 | I13: indisponibilité du code ussd *144*5# | J13: Inconnue | K13: Aucune | L13: GNOC/DevOps | M13: Clos | O13: =IF(AND(C13=$B$58,H13<=$D$58),"ISLA",IF((AND(C13=$B$59,H13<=$D$59)),"ISLA",IF((AND(C13=$B$60,H13<=$D$60)),"ISLA","OSLA"))) -> OSLA
A14: 13 | B14: 1812D42531 | C14: P1 | D14: SSPO | E14: Orange Money add-on / Bank to wallet / Ecobank | F14: 43445.949 | G14: 43445.99 | H14: 58 | I14: Impossible d’effectuer des transactions bancaires via OM | J14: Perte de connexion avec le partenaire | K14: Rétablissement de la connexion avec le partenaire | L14: SSPO | M14: Clos | O14: =IF(AND(C14=$B$58,H14<=$D$58),"ISLA",IF((AND(C14=$B$59,H14<=$D$59)),"ISLA",IF((AND(C14=$B$60,H14<=$D$60)),"ISLA","OSLA"))) -> ISLA
A15: 14 | B15: 1812D45264 | C15: P1 | D15: SSPO | E15: Orange Money add-on / Bank to wallet / Ecobank | F15: 43446.179 | G15: 43446.206 | H15: 39 | I15: Impossible d’effectuer des transactions bancaires via OM | J15: Perte de connexion avec le partenaire | K15: Rétablissement de la connexion avec le partenaire | L15: SSPO | M15: Clos | O15: =IF(AND(C15=$B$58,H15<=$D$58),"ISLA",IF((AND(C15=$B$59,H15<=$D$59)),"ISLA",IF((AND(C15=$B$60,H15<=$D$60)),"ISLA","OSLA"))) -> ISLA
A16: 15 | B16: 1812D78355 | C16: P2 | D16: SSPO | E16: E-recharge | F16: 43447.113 | G16: 43447.233 | H16: 174 | I16: 50% d’Echec de réception de notifications après transactions E-recharge | J16: Problème de connectivité de la plateforme Zebra et SMSC | K16: Aucune | L16: GNOC | M16: Clos | O16: =IF(AND(C16=$B$58,H16<=$D$58),"ISLA",IF((AND(C16=$B$59,H16<=$D$59)),"ISLA",IF((AND(C16=$B$60,H16<=$D$60)),"ISLA","OSLA"))) -> ISLA
A17: 16 | B17: 1812D79652 | C17: P1 | D17: SSPO | E17: Orange Money add-on / Bank to wallet / Ecobank | F17: 43447.21 | G17: 43447.236 | H17: 37 | I17: Impossible d’effectuer des transactions bancaires via OM | J17: Perte de connexion avec le partenaire | K17: Rétablissement de la connexion avec le partenaire | L17: SSPO | M17: Clos | O17: =IF(AND(C17=$B$58,H17<=$D$58),"ISLA",IF((AND(C17=$B$59,H17<=$D$59)),"ISLA",IF((AND(C17=$B$60,H17<=$D$60)),"ISLA","OSLA"))) -> ISLA
A18: 17 | B18: 1812E10413 | C18: P1 | D18: Supervision | E18: DATA Mobile | F18: 43447.941 | G18: 43448.816 | H18: =(G18-F18)*1440 -> 1260 | I18: Perte de trafic sur le lien KIPE-CAMAYENNE | J18: Coupure de fibre du lien Kipé-Camayenne à taouyah, à 4 Km de Kipé | K18: Soudure de Fibre | L18: HUAWEI | M18: Clos | O18: =IF(AND(C18=$B$58,H18<=$D$58),"ISLA",IF((AND(C18=$B$59,H18<=$D$59)),"ISLA",IF((AND(C18=$B$60,H18<=$D$60)),"ISLA","OSLA"))) -> OSLA
A19: 18 | B19: 1812E13564 | C19: P1 | D19: SSPO | E19: Orange Money add-on / Bank to wallet / Ecobank | F19: 43448.246 | G19: 43448.274 | H19: =(G19-F19)*1440 -> 41 | I19: Impossible d’effectuer des transactions bancaires via OM | J19: Perte de connexion avec le partenaire | K19: Rétablissement de la connexion avec le partenaire | L19: SSPO | M19: Clos | O19: =IF(AND(C19=$B$58,H19<=$D$58),"ISLA",IF((AND(C19=$B$59,H19<=$D$59)),"ISLA",IF((AND(C19=$B$60,H19<=$D$60)),"ISLA","OSLA"))) -> ISLA
A20: 19 | B20: 1812E36137 | C20: P1 | D20: Supervision | E20: Report avantage(*118*1#) | F20: 43448.778 | G20: 43448.885 | H20: =(G20-F20)*1440 -> 154 | I20: Indisponibilité du service report avantage(*118*1#) | J20: Inconnue | K20: Aucune | L20: ASBD | M20: Clos | O20: =IF(AND(C20=$B$58,H20<=$D$58),"ISLA",IF((AND(C20=$B$59,H20<=$D$59)),"ISLA",IF((AND(C20=$B$60,H20<=$D$60)),"ISLA","OSLA"))) -> OSLA
A21: 20 | B21: 1812E35644 | C21: P1 | D21: Supervision | E21: Transfert Data | F21: 43448.778 | G21: 43465.83 | H21: =(G21-F21)*1440 -> 24554 | I21: Instabilité sur le service Transfert Data | J21: Time out | K21: Augementation du délai de reponse Web Service | L21: DevOps | M21: Clos | O21: =IF(AND(C21=$B$58,H21<=$D$58),"ISLA",IF((AND(C21=$B$59,H21<=$D$59)),"ISLA",IF((AND(C21=$B$60,H21<=$D$60)),"ISLA","OSLA"))) -> OSLA
A22: 21 | B22: 1812E39467 | C22: P1 | D22: SSPO | E22: Orange Money add-on / Bank to wallet / Ecobank | F22: 43449.267 | G22: 43449.299 | H22: =(G22-F22)*1440 -> 45 | I22: Impossible d’effectuer des transactions bancaires via OM | J22: Perte de connexion avec le partenaire | K22: Rétablissement de la connexion avec le partenaire | L22: SSPO | M22: Clos | O22: =IF(AND(C22=$B$58,H22<=$D$58),"ISLA",IF((AND(C22=$B$59,H22<=$D$59)),"ISLA",IF((AND(C22=$B$60,H22<=$D$60)),"ISLA","OSLA"))) -> ISLA
A23: 22 | B23: 1812E42313 | C23: P2 | D23: Supervision | E23: CMS | F23: 43449.412 | G23: 43449.434 | H23: =(G23-F23)*1440 -> 31 | I23: Impossible d’accéder au service CMS via 8036 | J23: Inconnue | K23: Aucune | L23: GOS | M23: Clos | O23: =IF(AND(C23=$B$58,H23<=$D$58),"ISLA",IF((AND(C23=$B$59,H23<=$D$59)),"ISLA",IF((AND(C23=$B$60,H23<=$D$60)),"ISLA","OSLA"))) -> ISLA
A24: 23 | B24: 1812E53356 | C24: P1 | D24: Supervision | E24: Voix & Data mobile | F24: 43450.063 | G24: 43450.076 | H24: =(G24-F24)*1440 -> 19 | I24: Dégradation de la QOS Voix et la data mobile dans la zone de Labé,Siguiri,Kankan,Kamsar,Nzerekoré | J24: Inconnue | K24: Aucune | L24: GNOC | M24: Clos | N24: TQ probleme 1812E57350 | O24: =IF(AND(C24=$B$58,H24<=$D$58),"ISLA",IF((AND(C24=$B$59,H24<=$D$59)),"ISLA",IF((AND(C24=$B$60,H24<=$D$60)),"ISLA","OSLA"))) -> ISLA
A25: 24 | B25: 1812E54986 | C25: P1 | D25: SSPO | E25: Orange Money add-on / Bank to wallet / Ecobank | F25: 43450.297 | G25: 43450.333 | H25: =(G25-F25)*1440 -> 52 | I25: Impossible d’effectuer des transactions bancaires via OM | J25: Perte de connexion avec le partenaire | K25: Rétablissement de la connexion avec le partenaire | L25: SSPO | M25: Clos | O25: =IF(AND(C25=$B$58,H25<=$D$58),"ISLA",IF((AND(C25=$B$59,H25<=$D$59)),"ISLA",IF((AND(C25=$B$60,H25<=$D$60)),"ISLA","OSLA"))) -> ISLA
A26: 25 | B26: 1812E58549 | C26: P1 | D26: Supervision | E26: Orange et moi, Otap,Gameloft,Agrobusiness,CMS, Report avantage | F26: 43450.537 | G26: 43451.718 | H26: =(G26-F26)*1440 -> 1700 | I26: Indisponibilité des services passant par le SDP | J26: Constat d’une disjonction qui a impacté la baie NetApp. | K26: Ré-enclenchement des disjoncteurs, Redémarrage des machines virtuelles et Remise en ligne des différents services | L26: GOS | M26: Clos | O26: =IF(AND(C26=$B$58,H26<=$D$58),"ISLA",IF((AND(C26=$B$59,H26<=$D$59)),"ISLA",IF((AND(C26=$B$60,H26<=$D$60)),"ISLA","OSLA"))) -> OSLA
A27: 26 | B27: 1812E91593 | C27: P1 | D27: Supervision | E27: Report Avantage | F27: 43450.674 | G27: 43452.708 | H27: 2929 | I27: Indisponibilité du service Report avantage(*118*1#) | J27: Liée à l'incident sur KM4 1812E58549 | K27: Liée à l'incident sur KM4 1812E58549 | L27: GOS | M27: Clos | O27: =IF(AND(C27=$B$58,H27<=$D$58),"ISLA",IF((AND(C27=$B$59,H27<=$D$59)),"ISLA",IF((AND(C27=$B$60,H27<=$D$60)),"ISLA","OSLA"))) -> OSLA
A28: 27 | B28: 1812E66781 | C28: P1 | D28: SSPO | E28: Paddock Services | F28: 43451.24 | G28: 43451.305 | H28: 93 | I28: Impossible d’utiliser les fonctionnalités SMS PADDOCK | J28: Panne Réseau | K28: Redémarrage du VPN | L28: SSPO | M28: Clos | O28: =IF(AND(C28=$B$58,H28<=$D$58),"ISLA",IF((AND(C28=$B$59,H28<=$D$59)),"ISLA",IF((AND(C28=$B$60,H28<=$D$60)),"ISLA","OSLA"))) -> ISLA
A29: 28 | B29: 1812E65717 | C29: P1 | D29: Supervision | E29: Navigation Internet, Tango, Right Q, Robot Daset, CIS, Pretups, Uniportal, KYC,Kapptivate | F29: 43451.257 | G29: 43451.295 | H29: 55 | I29: Indisponibilité des services et Outils passant par le LAN | J29: En attente du rapport d'incident de la Sonatel | K29: En attente du rapport d'incident de la Sonatel | L29: Sonatel | M29: Clos | O29: =IF(AND(C29=$B$58,H29<=$D$58),"ISLA",IF((AND(C29=$B$59,H29<=$D$59)),"ISLA",IF((AND(C29=$B$60,H29<=$D$60)),"ISLA","OSLA"))) -> ISLA
A30: 29 | B30: 1812E66354 | C30: P2 | D30: SSPO | E30: Orange Money add-on / Canal+ | F30: 43451.283 | G30: 43451.299 | H30: 22 | I30: Impossible d’effectuer des Réabonnements Canal+ via OM | J30: Saturation du serveur Web de Canal + | K30: Aucune | L30: SSPO | M30: Clos | O30: =IF(AND(C30=$B$58,H30<=$D$58),"ISLA",IF((AND(C30=$B$59,H30<=$D$59)),"ISLA",IF((AND(C30=$B$60,H30<=$D$60)),"ISLA","OSLA"))) -> ISLA
A31: 30 | B31: 1812E69175 | C31: P1 | D31: SSPO | E31: Orange Money add-on / Bank to wallet / Ecobank | F31: 43451.339 | G31: 43451.365 | H31: 37 | I31: Impossible d’effectuer des transactions bancaires via OM | J31: Perte de connexion avec le partenaire | K31: Rétablissement de la connexion avec le partenaire | L31: SSPO | M31: Clos | O31: =IF(AND(C31=$B$58,H31<=$D$58),"ISLA",IF((AND(C31=$B$59,H31<=$D$59)),"ISLA",IF((AND(C31=$B$60,H31<=$D$60)),"ISLA","OSLA"))) -> ISLA
A32: 31 | B32: 1812E82948 | C32: P2 | D32: GOS | E32: KMC | F32: 43451.58 | G32: 43452.656 | H32: 1550 | I32: Dégradation du service KMC | J32: Indisponibilité du moteur de recherche dû au reboot des VMs | K32: Remise des fichiers manquants et redémarrage du service Apache et de la VM (opkmcgosapp02) | L32: GOS | M32: Clos | O32: =IF(AND(C32=$B$58,H32<=$D$58),"ISLA",IF((AND(C32=$B$59,H32<=$D$59)),"ISLA",IF((AND(C32=$B$60,H32<=$D$60)),"ISLA","OSLA"))) -> OSLA
A33: 32 | B33: 1812E91968 | C33: P1 | D33: Supervision | E33: Agrobusiness | F33: 43451.637 | I33: Impossible d’accéder au menu *113# | J33: Retard de renouvellement de l'herbergement | K33: Aucune | L33: BANKITECH | M33: En cours | O33: =IF(AND(C33=$B$58,H33<=$D$58),"ISLA",IF((AND(C33=$B$59,H33<=$D$59)),"ISLA",IF((AND(C33=$B$60,H33<=$D$60)),"ISLA","OSLA"))) -> ISLA
A34: 33 | B34: 1812F00246 | C34: P1 | D34: SSPO | E34: Orange Money add-on / Bank to wallet / Ecobank | F34: 43452.363 | G34: 43452.399 | H34: 53 | I34: Impossible d’effectuer des transactions bancaires via OM | J34: Perte de connexion avec le partenaire | K34: Rétablissement de la connexion avec le partenaire | L34: SSPO | M34: Clos | O34: =IF(AND(C34=$B$58,H34<=$D$58),"ISLA",IF((AND(C34=$B$59,H34<=$D$59)),"ISLA",IF((AND(C34=$B$60,H34<=$D$60)),"ISLA","OSLA"))) -> ISLA
A35: 34 | B35: 1812F30847 | C35: P1 | D35: SSPO | E35: Orange Money add-on / Bank to wallet / Ecobank | F35: 43453.401 | G35: 43453.438 | H35: 52 | I35: Impossible d’effectuer des transactions bancaires via OM | J35: Perte de connexion avec le partenaire | K35: Rétablissement de la connexion avec le partenaire | L35: SSPO | M35: Clos | O35: =IF(AND(C35=$B$58,H35<=$D$58),"ISLA",IF((AND(C35=$B$59,H35<=$D$59)),"ISLA",IF((AND(C35=$B$60,H35<=$D$60)),"ISLA","OSLA"))) -> ISLA
A36: 35 | B36: 1812F59715 | C36: P1 | D36: SSPO | E36: Orange Money add-on / Bank to wallet / Ecobank | F36: 43454.439 | G36: 43454.471 | H36: 46 | I36: Impossible d’effectuer des transactions bancaires via OM | J36: Perte de connexion avec le partenaire | K36: Rétablissement de la connexion avec le partenaire | L36: SSPO | M36: Clos | O36: =IF(AND(C36=$B$58,H36<=$D$58),"ISLA",IF((AND(C36=$B$59,H36<=$D$59)),"ISLA",IF((AND(C36=$B$60,H36<=$D$60)),"ISLA","OSLA"))) -> ISLA
A37: 36 | B37: 1812F74717 | C37: P1 | D37: SSPO | E37: Orange Money add-on / WebPayment | F37: 43454.84 | G37: 43454.865 | H37: 36 | I37: Impossible d’effectuer des payements en ligne via OM | J37: Indisponibilité de la connexion entre le serveur d'application et la base de données dû aux nombres élevé de connexions et de transactions à la base de données | K37: Redémarrage de la base de données | L37: SSPO | M37: Clos | O37: =IF(AND(C37=$B$58,H37<=$D$58),"ISLA",IF((AND(C37=$B$59,H37<=$D$59)),"ISLA",IF((AND(C37=$B$60,H37<=$D$60)),"ISLA","OSLA"))) -> ISLA
A38: 37 | B38: 1812F77757 | C38: P2 | D38: Supervision | E38: Orange Money add-on / Startimes | F38: 43455.115 | G38: 43455.247 | H38: =(G38-F38)*1440 -> 190 | I38: Impossible d’effectuer des Réabonnements Startimes via OM | J38: Inconnue | K38: Aucune | L38: ASBD | M38: Clos | O38: =IF(AND(C38=$B$58,H38<=$D$58),"ISLA",IF((AND(C38=$B$59,H38<=$D$59)),"ISLA",IF((AND(C38=$B$60,H38<=$D$60)),"ISLA","OSLA"))) -> ISLA
A39: 38 | B39: 1812F85714 | C39: P1 | D39: Supervision | E39: Consultation Solde Data [*222*5#] | F39: 43455.438 | G39: 43455.482 | H39: =(G39-F39)*1440 -> 64 | I39: Indisponibilité du service Consultation Solde Data via USSD | J39: En attente de DevOps | K39: En attente de DevOps | L39: DevOps | M39: Clos | O39: =IF(AND(C39=$B$58,H39<=$D$58),"ISLA",IF((AND(C39=$B$59,H39<=$D$59)),"ISLA",IF((AND(C39=$B$60,H39<=$D$60)),"ISLA","OSLA"))) -> ISLA
A40: 39 | B40: 1812F87281 | C40: P1 | D40: SSPO | E40: Orange Money add-on / Bank to wallet / Ecobank | F40: 43455.474 | G40: 43455.507 | H40: =(G40-F40)*1440 -> 48 | I40: Impossible d’effectuer des transactions bancaires via OM | J40: Perte de connexion avec le partenaire | K40: Rétablissement de la connexion avec le partenaire | L40: SSPO | M40: Clos | O40: =IF(AND(C40=$B$58,H40<=$D$58),"ISLA",IF((AND(C40=$B$59,H40<=$D$59)),"ISLA",IF((AND(C40=$B$60,H40<=$D$60)),"ISLA","OSLA"))) -> ISLA
A41: 40 | B41: 1812F33466 | C41: P1 | D41: SSPO | E41: Orange Money | F41: 43455.507 | G41: 43455.511 | H41: =(G41-F41)*1440 -> 6 | I41: Dégradation du service Orange Money [Impact :14%] | J41: Investigations cours entre les équipes SSPO Orange Money, GIN RUN et GIN CORE NETWORK. | K41: Inconnue | L41: SSPO | M41: Clos | O41: =IF(AND(C41=$B$58,H41<=$D$58),"ISLA",IF((AND(C41=$B$59,H41<=$D$59)),"ISLA",IF((AND(C41=$B$60,H41<=$D$60)),"ISLA","OSLA"))) -> ISLA
A42: 41 | B42: 1812F97672|1812G35593 | C42: P1 | D42: Supervision | E42: Report Avantage | F42: 43455.568 | G42: 43460.354 | H42: =(G42-F42)*1440 -> 6892 | I42: Instabilité du service Report avantage(*118*1#) | J42: Souci de connexion entre OTAP er Report Avantage | K42: Aucune | L42: DevOps | M42: Clos | O42: =IF(AND(C42=$B$58,H42<=$D$58),"ISLA",IF((AND(C42=$B$59,H42<=$D$59)),"ISLA",IF((AND(C42=$B$60,H42<=$D$60)),"ISLA","OSLA"))) -> OSLA
A43: 42 | B43: 1812F97508 | C43: P1 | D43: SSPO | E43: Orange Money add-on / Bank to wallet / Ecobank | F43: 43455.708 | G43: 43455.783 | H43: =(G43-F43)*1440 -> 108 | I43: Impossible d’effectuer des transactions bancaires via OM | J43: Perte de connexion avec le partenaire | K43: Rétablissement de la connexion avec le partenaire | L43: SSPO | M43: Clos | O43: =IF(AND(C43=$B$58,H43<=$D$58),"ISLA",IF((AND(C43=$B$59,H43<=$D$59)),"ISLA",IF((AND(C43=$B$60,H43<=$D$60)),"ISLA","OSLA"))) -> ISLA
A44: 43 | B44: 1812G08924 | C44: P1 | D44: SSPO | E44: Orange Money add-on / Bank to wallet / Ecobank | F44: 43456.504 | G44: 43456.558 | H44: =(G44-F44)*1440 -> 78 | I44: Impossible d’effectuer des transactions bancaires via OM | J44: Perte de connexion avec le partenaire | K44: Rétablissement de la connexion avec le partenaire | L44: SSPO | M44: Clos | O44: =IF(AND(C44=$B$58,H44<=$D$58),"ISLA",IF((AND(C44=$B$59,H44<=$D$59)),"ISLA",IF((AND(C44=$B$60,H44<=$D$60)),"ISLA","OSLA"))) -> ISLA
A45: 44 | B45: 1812G21321 | C45: P1 | D45: SSPO | E45: Orange Money add-on / Bank to wallet / Ecobank | F45: 43457.531 | G45: 43457.567 | H45: =(G45-F45)*1440 -> 51 | I45: Impossible d’effectuer des transactions bancaires via OM | J45: Perte de connexion avec le partenaire | K45: Rétablissement de la connexion avec le partenaire | L45: SSPO | M45: Clos | O45: =IF(AND(C45=$B$58,H45<=$D$58),"ISLA",IF((AND(C45=$B$59,H45<=$D$59)),"ISLA",IF((AND(C45=$B$60,H45<=$D$60)),"ISLA","OSLA"))) -> ISLA
A46: 45 | B46: 1812G26499 | C46: P1 | D46: Supervision | E46: CMS | F46: 43457.854 | G46: 43458.401 | H46: =(G46-F46)*1440 -> 788 | I46: Impossible d’accéder au service CMS via le canal USSD et SMS | J46: Les Vms NAG_DS étaient figées | K46: Redémarrage de ces VMs | L46: GOS | M46: Clos | O46: =IF(AND(C46=$B$58,H46<=$D$58),"ISLA",IF((AND(C46=$B$59,H46<=$D$59)),"ISLA",IF((AND(C46=$B$60,H46<=$D$60)),"ISLA","OSLA"))) -> OSLA
A47: 46 | B47: 1812G38476 | C47: P1 | D47: SSPO | E47: Orange Money add-on / Bank to wallet / Ecobank | F47: 43458.566 | G47: 43458.601 | H47: =(G47-F47)*1440 -> 51 | I47: Impossible d’effectuer des transactions bancaires via OM | J47: Perte de connexion avec le partenaire | K47: Rétablissement de la connexion avec le partenaire | L47: SSPO | M47: Clos | O47: =IF(AND(C47=$B$58,H47<=$D$58),"ISLA",IF((AND(C47=$B$59,H47<=$D$59)),"ISLA",IF((AND(C47=$B$60,H47<=$D$60)),"ISLA","OSLA"))) -> ISLA
A48: 47 | B48: 1812G45792 | C48: P1 | D48: SSPO | E48: Orange Money add-on / Bank to wallet / Ecobank | F48: 43459.084 | G48: 43459.811 | H48: =(G48-F48)*1440 -> 1047 | I48: Impossible d’effectuer des transactions bancaires via OM | J48: Perte de connexion avec le partenaire | K48: Rétablissement de la connexion avec le partenaire | L48: SSPO | M48: Clos | O48: =IF(AND(C48=$B$58,H48<=$D$58),"ISLA",IF((AND(C48=$B$59,H48<=$D$59)),"ISLA",IF((AND(C48=$B$60,H48<=$D$60)),"ISLA","OSLA"))) -> OSLA
A49: 48 | B49: 1812G76059 | C49: P1 | D49: SSPO | E49: Orange Money add-on / Bank to wallet / Ecobank | F49: 43460.635 | G49: 43460.667 | H49: =(G49-F49)*1440 -> 45 | I49: Impossible d’effectuer des transactions bancaires via OM | J49: Perte de connexion avec le partenaire | K49: Rétablissement de la connexion avec le partenaire | L49: SSPO | M49: Clos | O49: =IF(AND(C49=$B$58,H49<=$D$58),"ISLA",IF((AND(C49=$B$59,H49<=$D$59)),"ISLA",IF((AND(C49=$B$60,H49<=$D$60)),"ISLA","OSLA"))) -> ISLA
... A54: 53 | B54: 1812H73488 | C54: P1 | D54: SSPO | E54: Orange Money add-on / Bank to wallet / Ecobank | F54: 43465.694 | G54: 43465.888 | H54: =(G54-F54)*1440 -> 280 | I54: Impossible d’effectuer des transactions bancaires via OM | J54: Perte de connexion avec le partenaire | K54: Rétablissement de la connexion avec le partenaire | L54: SSPO | M54: Clos | O54: =IF(AND(C54=$B$58,H54<=$D$58),"ISLA",IF((AND(C54=$B$59,H54<=$D$59)),"ISLA",IF((AND(C54=$B$60,H54<=$D$60)),"ISLA","OSLA"))) -> OSLA
B58: P1 | C58: 2h | D58: 120
B59: P2 | C59: 4h | D59: 240
B60: P3 | C60: 2jr | D60: =1440*2 -> 2880
B61: P4 | C61: 3jr | D61: =3*1440 -> 4320

Sheet Janvier_2019
A1: N° | B1: N°TICKET | C1: PRIORITE | D1: Origine | E1: NOM SERVICES | F1: DATE & HEURE DEBUT | G1: DATE & HEURE FIN | H1: DUREE (mn) | I1: DESCRIPTION | J1: CAUSE DE L'INCIDENT | K1: ACTIONS CORRECTIVES | L1: TMC | M1: Statut | N1: Observation | O1: SLA
A2: 1 | B2: 1901H81767 | C2: P1 | D2: SSPO | E2: Orange Money add-on / Bank to wallet / Ecobank | F2: 43466.799 | G2: 43466.828 | H2: 43 | I2: Impossible d’effectuer des transactions bancaires via OM | J2: Perte de connexion avec le partenaire | K2: Retablissement de la connexion | L2: SSPO | M2: Clos | O2: =IF(AND(C2=$B$51,H2<=$D$51),"ISLA",IF((AND(C2=$B$52,H2<=$D$52)),"ISLA",IF((AND(C2=$B$53,H2<=$D$53)),"ISLA","OSLA"))) -> ISLA
A3: 2 | B3: 1812D46574 | C3: P1 | D3: Supervision | E3: Data Mobile,voix | F3: 43467.201 | G3: 43467.986 | H3: 1130 | I3: Dégradation de service due à des Perte de paquets sur le BB DALEIN to FELLOSORE | J3: Une instabilité due aux conditions climatiques | K3: Aucune | L3: GNOC | M3: Clos | O3: =IF(AND(C3=$B$51,H3<=$D$51),"ISLA",IF((AND(C3=$B$52,H3<=$D$52)),"ISLA",IF((AND(C3=$B$53,H3<=$D$53)),"ISLA","OSLA"))) -> OSLA
A4: 3 | B4: 1812F97672 | C4: P1 | D4: Supervision | E4: Report avantage | F4: 43467.372 | G4: 43471.358 | H4: 5739 | I4: Instabilité sur le service Report avantage(*118*1#) | J4: Soucis de connexion entre OTAP et le serveur report avantage | K4: Aucune | L4: GOS | M4: Clos | O4: =IF(AND(C4=$B$51,H4<=$D$51),"ISLA",IF((AND(C4=$B$52,H4<=$D$52)),"ISLA",IF((AND(C4=$B$53,H4<=$D$53)),"ISLA","OSLA"))) -> OSLA
A5: 4 | B5: 1901I12073 | C5: P1 | D5: SSPO | E5: Orange Money add-on / Bank to wallet / Ecobank | F5: 43467.828 | G5: 43467.863 | H5: 50 | I5: Impossible d’effectuer des transactions bancaires via OM | J5: Perte de connexion avec le partenaire | K5: Retablissement de la connexion | L5: SSPO | M5: Clos | O5: =IF(AND(C5=$B$51,H5<=$D$51),"ISLA",IF((AND(C5=$B$52,H5<=$D$52)),"ISLA",IF((AND(C5=$B$53,H5<=$D$53)),"ISLA","OSLA"))) -> ISLA
A6: 5 | B6: 1901I15698 | C6: P1 | D6: SSPO | E6: Orange Money add-on / Bank to wallet / Ecobank | F6: 43468.153 | G6: 43468.272 | H6: 170 | I6: Impossible d’effectuer des transactions bancaires via OM | J6: Perte de connexion avec le partenaire | K6: Retablissement de la connexion | L6: SSPO | M6: Clos | O6: =IF(AND(C6=$B$51,H6<=$D$51),"ISLA",IF((AND(C6=$B$52,H6<=$D$52)),"ISLA",IF((AND(C6=$B$53,H6<=$D$53)),"ISLA","OSLA"))) -> OSLA
A7: 6 | B7: 1901I22691 | C7: P1 | D7: SSPO | E7: Orange Money add-on / Canal+ | F7: 43468.39 | G7: 43468.433 | H7: 62 | I7: Impossible d’effectuer du réabonnement canal+ via OM | J7: Surcharge des services Web de Canal+ | K7: Aucune action | L7: SSPO | M7: Clos | O7: =IF(AND(C7=$B$51,H7<=$D$51),"ISLA",IF((AND(C7=$B$52,H7<=$D$52)),"ISLA",IF((AND(C7=$B$53,H7<=$D$53)),"ISLA","OSLA"))) -> ISLA
A8: 7 | B8: 1901I43254 | C8: P1 | D8: SSPO | E8: Orange Money add-on / Bank to wallet / Ecobank | F8: 43468.87 | G8: 43468.897 | H8: 38 | I8: Impossible d’effectuer des transactions bancaires via OM | J8: Perte de connexion avec le partenaire | K8: Retablissement de la connexion | L8: SSPO | M8: Clos | O8: =IF(AND(C8=$B$51,H8<=$D$51),"ISLA",IF((AND(C8=$B$52,H8<=$D$52)),"ISLA",IF((AND(C8=$B$53,H8<=$D$53)),"ISLA","OSLA"))) -> ISLA
A9: 8 | B9: 1901I70930 | C9: P1 | D9: SSPO | E9: Orange Money add-on / Bank to wallet / Ecobank | F9: 43469.899 | G9: 43469.927 | H9: 40 | I9: Impossible d’effectuer des transactions bancaires via OM | J9: Perte de connexion avec le partenaire | K9: Retablissement de la connexion | L9: SSPO | M9: Clos | O9: =IF(AND(C9=$B$51,H9<=$D$51),"ISLA",IF((AND(C9=$B$52,H9<=$D$52)),"ISLA",IF((AND(C9=$B$53,H9<=$D$53)),"ISLA","OSLA"))) -> ISLA
A10: 9 | B10: 1901I84069 | C10: P1 | D10: SSPO | E10: Orange Money add-on / Bank to wallet / Ecobank | F10: 43470.931 | G10: 43470.96 | H10: 43 | I10: Impossible d’effectuer des transactions bancaires via OM | J10: Perte de connexion avec le partenaire | K10: Retablissement de la connexion | L10: SSPO | M10: Clos | O10: =IF(AND(C10=$B$51,H10<=$D$51),"ISLA",IF((AND(C10=$B$52,H10<=$D$52)),"ISLA",IF((AND(C10=$B$53,H10<=$D$53)),"ISLA","OSLA"))) -> ISLA
A11: 10 | B11: 1901J19474 | C11: P1 | D11: SSPO | E11: Orange Money add-on / Bank to wallet / Ecobank | F11: 43472.962 | G11: 43472.993 | H11: 45 | I11: Impossible d’effectuer des transactions bancaires via OM | J11: Perte de connexion avec le partenaire | K11: Rétablissement de la connexion | L11: SSPO | M11: Clos | O11: =IF(AND(C11=$B$51,H11<=$D$51),"ISLA",IF((AND(C11=$B$52,H11<=$D$52)),"ISLA",IF((AND(C11=$B$53,H11<=$D$53)),"ISLA","OSLA"))) -> ISLA
A12: 11 | B12: 1901J35803 | C12: P1 | D12: Supervision | E12: Webtop | F12: 43473.526 | G12: 43474.592 | H12: 1536 | I12: Impossible d’accéder au page d’achat pass via le lien http | J12: Inconnue | K12: Aucune | L12: GOS | M12: Clos | O12: =IF(AND(C12=$B$51,H12<=$D$51),"ISLA",IF((AND(C12=$B$52,H12<=$D$52)),"ISLA",IF((AND(C12=$B$53,H12<=$D$53)),"ISLA","OSLA"))) -> OSLA
A13: 12 | B13: 1901J39986 | C13: P1 | D13: SSPO | E13: Orange Money add-on / Canal+ | F13: 43473.593 | G13: 43473.617 | H13: 34 | I13: Impossible d’effectuer du réabonnement canal+ via OM | J13: Perte de connexion avec le partenaire | K13: Rétablissement de la connexion | L13: SSPO | M13: Clos | O13: =IF(AND(C13=$B$51,H13<=$D$51),"ISLA",IF((AND(C13=$B$52,H13<=$D$52)),"ISLA",IF((AND(C13=$B$53,H13<=$D$53)),"ISLA","OSLA"))) -> ISLA
A14: 13 | B14: 1901J50281 | C14: P1 | D14: SSPO | E14: Orange Money add-on / Bank to wallet / Ecobank | F14: 43473.997 | G14: 43474.032 | H14: 51 | I14: Impossible d’effectuer des transactions bancaires via OM | J14: Perte de connexion avec le partenaire | K14: Rétablissement de la connexion | L14: SSPO | M14: Clos | O14: =IF(AND(C14=$B$51,H14<=$D$51),"ISLA",IF((AND(C14=$B$52,H14<=$D$52)),"ISLA",IF((AND(C14=$B$53,H14<=$D$53)),"ISLA","OSLA"))) -> ISLA
A15: 14 | B15: 1901J75680 | C15: P1 | D15: Supervision | E15: Report avantage | F15: 43474.559 | G15: 43475.35 | H15: =(G15-F15)*1440 -> 1139 | I15: Instabilité sur le service Report avantage(*118*1#) | J15: Inconnue | K15: Aucune | L15: GOS | M15: Clos | O15: =IF(AND(C15=$B$51,H15<=$D$51),"ISLA",IF((AND(C15=$B$52,H15<=$D$52)),"ISLA",IF((AND(C15=$B$53,H15<=$D$53)),"ISLA","OSLA"))) -> OSLA
A16: 15 | B16: 1901J82501 | C16: P1 | D16: SSPO | E16: Orange Money add-on / Bank to wallet / Ecobank | F16: 43475.035 | G16: 43475.062 | H16: 40 | I16: Impossible d’effectuer des transactions bancaires via OM | J16: Perte de connexion avec le partenaire | K16: Rétablissement de la connexion | L16: SSPO | M16: Clos | O16: =IF(AND(C16=$B$51,H16<=$D$51),"ISLA",IF((AND(C16=$B$52,H16<=$D$52)),"ISLA",IF((AND(C16=$B$53,H16<=$D$53)),"ISLA","OSLA"))) -> ISLA
A17: 16 | B17: CSD-20970 | C17: P1 | D17: Supervision | E17: FFC | F17: 43475.076 | G17: 43475.501 | H17: 612 | I17: Impossible d’accéder au service FFC via le code *191# | J17: Base de donnée verrouillé | K17: Inconnue | L17: Support FFC | M17: Clos | O17: =IF(AND(C17=$B$51,H17<=$D$51),"ISLA",IF((AND(C17=$B$52,H17<=$D$52)),"ISLA",IF((AND(C17=$B$53,H17<=$D$53)),"ISLA","OSLA"))) -> OSLA
A18: 17 | B18: 1901K17009 | C18: P1 | D18: SSPO | E18: Orange Money add-on / Bank to wallet / Ecobank | F18: 43476.063 | G18: 43476.094 | H18: 44 | I18: Impossible d’effectuer des transactions bancaires via OM | J18: Perte de connexion avec le partenaire | K18: Rétablissement de la connexion | L18: SSPO | M18: Clos | O18: =IF(AND(C18=$B$51,H18<=$D$51),"ISLA",IF((AND(C18=$B$52,H18<=$D$52)),"ISLA",IF((AND(C18=$B$53,H18<=$D$53)),"ISLA","OSLA"))) -> ISLA
A19: 18 | B19: 1901K27666 | C19: P1 | D19: SSPO | E19: Orange Money add-on / Canal+ | F19: 43476.418 | G19: 43476.45 | H19: 46 | I19: Impossible d’effectuer du réabonnement canal+ via OM | J19: Perte de connexion avec le partenaire | K19: Retablissement de la connexion | L19: SSPO | M19: Clos | O19: =IF(AND(C19=$B$51,H19<=$D$51),"ISLA",IF((AND(C19=$B$52,H19<=$D$52)),"ISLA",IF((AND(C19=$B$53,H19<=$D$53)),"ISLA","OSLA"))) -> ISLA
A20: 19 | B20: 1901K50947 | C20: P1 | D20: SSPO | E20: Orange Money add-on / Bank to wallet / Ecobank | F20: 43477.099 | G20: 43477.132 | H20: 48 | I20: Impossible d’effectuer des transactions bancaires via OM | J20: Perte de connexion avec le partenaire | K20: Rétablissement de la connexion | L20: SSPO | M20: Clos | O20: =IF(AND(C20=$B$51,H20<=$D$51),"ISLA",IF((AND(C20=$B$52,H20<=$D$52)),"ISLA",IF((AND(C20=$B$53,H20<=$D$53)),"ISLA","OSLA"))) -> ISLA
A21: 20 | B21: 1901K88575 | C21: P1 | D21: SSPO | E21: Orange Money add-on / Bank to wallet / Ecobank | F21: 43479.163 | G21: 43479.2 | H21: 53 | I21: Impossible d’effectuer des transactions bancaires via OM | J21: Perte de connexion avec le partenaire | K21: Rétablissement de connexion avec le partenaire | L21: SSPO | M21: Clos | O21: =IF(AND(C21=$B$51,H21<=$D$51),"ISLA",IF((AND(C21=$B$52,H21<=$D$52)),"ISLA",IF((AND(C21=$B$53,H21<=$D$53)),"ISLA","OSLA"))) -> ISLA
A22: 21 | B22: 1901L23528 | C22: P1 | D22: SSPO | E22: Orange Money add-on / Bank to wallet / Ecobank | F22: 43480.198 | G22: 43480.231 | H22: 47 | I22: Impossible d’effectuer des transactions bancaires via OM | J22: Perte de connexion avec le partenaire | K22: Rétablissement de connexion avec le partenaire | L22: SSPO | M22: Clos | O22: =IF(AND(C22=$B$51,H22<=$D$51),"ISLA",IF((AND(C22=$B$52,H22<=$D$52)),"ISLA",IF((AND(C22=$B$53,H22<=$D$53)),"ISLA","OSLA"))) -> ISLA
A23: 22 | B23: 1901L46815 | C23: P1 | D23: Supervision | E23: Data Mobile | F23: 43480.649 | G23: 43480.701 | H23: 74 | I23: Baisse de trafic sur la sortie Internet Dalein-Kedougou | J23: Coupure de fibre optique entre MAKO et NIOKO | K23: Soudure de la fibre optique | L23: SONATEL | M23: Clos | O23: =IF(AND(C23=$B$51,H23<=$D$51),"ISLA",IF((AND(C23=$B$52,H23<=$D$52)),"ISLA",IF((AND(C23=$B$53,H23<=$D$53)),"ISLA","OSLA"))) -> ISLA
A24: 23 | B24: 1901L60284 | C24: P1 | D24: SSPO | E24: Orange Money add-on / Bank to wallet / Ecobank | F24: 43481.226 | G24: 43481.26 | H24: 49 | I24: Impossible d’effectuer des transactions bancaires via OM | J24: Perte de connexion avec le partenaire | K24: Rétablissement de connexion avec le partenaire | L24: SSPO | M24: Clos | O24: =IF(AND(C24=$B$51,H24<=$D$51),"ISLA",IF((AND(C24=$B$52,H24<=$D$52)),"ISLA",IF((AND(C24=$B$53,H24<=$D$53)),"ISLA","OSLA"))) -> ISLA
A25: 24 | B25: 1901L85689 | C25: P1 | D25: Supervision | E25: Voix, Data, SMS et USSD | F25: 43481.701 | G25: 43481.842 | H25: 203 | I25: Indisponibilité des services sur la 3G pour les zones couvertes par la RNC6 | J25: Indisponibilité du trafic sur la RNC6 | K25: Investigation en cours | L25: Huawei | M25: Clos | O25: =IF(AND(C25=$B$51,H25<=$D$51),"ISLA",IF((AND(C25=$B$52,H25<=$D$52)),"ISLA",IF((AND(C25=$B$53,H25<=$D$53)),"ISLA","OSLA"))) -> OSLA
A26: 25 | B26: 1901L96648 | C26: P1 | D26: SSPO | E26: Orange Money add-on / Bank to wallet / Ecobank | F26: 43482.264 | G26: 43482.292 | H26: 40 | I26: Impossible d’effectuer des transactions bancaires via OM | J26: Perte de connexion avec le partenaire | K26: Rétablissement de connexion avec le partenaire | L26: SSPO | M26: Clos | O26: =IF(AND(C26=$B$51,H26<=$D$51),"ISLA",IF((AND(C26=$B$52,H26<=$D$52)),"ISLA",IF((AND(C26=$B$53,H26<=$D$53)),"ISLA","OSLA"))) -> ISLA
A27: 26 | B27: 1901M40764 | C27: P1 | D27: SSPO | E27: Orange Money add-on / Bank to wallet / Ecobank | F27: 43483.295 | G27: 43483.319 | H27: 35 | I27: Impossible d’effectuer des transactions bancaires via OM | J27: Perte de connexion avec le partenaire | K27: Rétablissement de connexion avec le partenaire | L27: SSPO | M27: Clos | O27: =IF(AND(C27=$B$51,H27<=$D$51),"ISLA",IF((AND(C27=$B$52,H27<=$D$52)),"ISLA",IF((AND(C27=$B$53,H27<=$D$53)),"ISLA","OSLA"))) -> ISLA
... A38: 37 | B38: 1901O16402 | C38: P1 | D38: SSPO | E38: Orange Money add-on / Bank to wallet / Ecobank | F38: 43490.514 | G38: 43490.543 | H38: 42 | I38: Impossible d’effectuer des transactions bancaires via OM | J38: Perte de connexion avec le partenaire | K38: Rétablissement de connexion avec le partenaire | L38: SSPO | M38: Clos | O38: =IF(AND(C38=$B$51,H38<=$D$51),"ISLA",IF((AND(C38=$B$52,H38<=$D$52)),"ISLA",IF((AND(C38=$B$53,H38<=$D$53)),"ISLA","OSLA"))) -> ISLA
A39: 38 | B39: 1901O48093 | C39: P1 | D39: SSPO | E39: Orange Money add-on / Bank to wallet / Ecobank | F39: 43492.537 | G39: 43492.576 | H39: =(G39-F39)*1440 -> 55 | I39: Impossible d’effectuer des transactions bancaires via OM | J39: Perte de connexion avec le partenaire | K39: Rétablissement de connexion avec le partenaire | L39: SSPO | M39: Clos | O39: =IF(AND(C39=$B$51,H39<=$D$51),"ISLA",IF((AND(C39=$B$52,H39<=$D$52)),"ISLA",IF((AND(C39=$B$53,H39<=$D$53)),"ISLA","OSLA"))) -> ISLA
A40: 39 | B40: 1901O53363 | C40: P1 | D40: SSPO | E40: Orange Money add-on / Bank to wallet / Ecobank | F40: 43493.01 | G40: 43493.399 | H40: 560 | I40: Impossible d’effectuer des transactions bancaires via OM | J40: Perte de connexion avec le partenaire | K40: Rétablissement de connexion avec le partenaire | L40: SSPO | M40: Clos | O40: =IF(AND(C40=$B$51,H40<=$D$51),"ISLA",IF((AND(C40=$B$52,H40<=$D$52)),"ISLA",IF((AND(C40=$B$53,H40<=$D$53)),"ISLA","OSLA"))) -> OSLA
A41: 40 | B41: 1901O72409 | C41: P1 | D41: SSPO | E41: Orange Money add-on / Bank to wallet / Ecobank | F41: 43493.575 | G41: 43493.617 | H41: 60 | I41: Impossible d’effectuer des transactions bancaires via OM | J41: Perte de connexion avec le partenaire | K41: Rétablissement de connexion avec le partenaire | L41: SSPO | M41: Clos | O41: =IF(AND(C41=$B$51,H41<=$D$51),"ISLA",IF((AND(C41=$B$52,H41<=$D$52)),"ISLA",IF((AND(C41=$B$53,H41<=$D$53)),"ISLA","OSLA"))) -> ISLA
A42: 41 | B42: 1901P03709 | C42: P1 | D42: SSPO | E42: Orange Money add-on / Bank to wallet / Ecobank | F42: 43494.615 | G42: 43494.648 | H42: 48 | I42: Impossible d’effectuer des transactions bancaires via OM | J42: Perte de connexion avec le partenaire | K42: Rétablissement de connexion avec le partenaire | L42: SSPO | M42: Clos | O42: =IF(AND(C42=$B$51,H42<=$D$51),"ISLA",IF((AND(C42=$B$52,H42<=$D$52)),"ISLA",IF((AND(C42=$B$53,H42<=$D$53)),"ISLA","OSLA"))) -> ISLA
A43: 42 | B43: 1901P42586 | C43: P1 | D43: SSPO | E43: Orange Money add-on / Bank to wallet / Ecobank | F43: 43495.647 | G43: 43495.678 | H43: 46 | I43: Impossible d’effectuer des transactions bancaires via OM | J43: Perte de connexion avec le partenaire | K43: Rétablissement de connexion avec le partenaire | L43: SSPO | M43: Clos | O43: =IF(AND(C43=$B$51,H43<=$D$51),"ISLA",IF((AND(C43=$B$52,H43<=$D$52)),"ISLA",IF((AND(C43=$B$53,H43<=$D$53)),"ISLA","OSLA"))) -> ISLA
A44: 43 | B44: 1901P73844 | C44: P1 | D44: SSPO | E44: Orange Money add-on / Bank to wallet / Ecobank | F44: 43496.681 | G44: 43496.712 | H44: 44 | I44: Impossible d’effectuer des transactions bancaires via OM | J44: Perte de connexion avec le partenaire | K44: Rétablissement de connexion avec le partenaire | L44: SSPO | M44: Clos | O44: =IF(AND(C44=$B$51,H44<=$D$51),"ISLA",IF((AND(C44=$B$52,H44<=$D$52)),"ISLA",IF((AND(C44=$B$53,H44<=$D$53)),"ISLA","OSLA"))) -> ISLA
B51: P1 | C51: 2h | D51: 120
B52: P2 | C52: 4h | D52: 240
B53: P3 | C53: 2jr | D53: =1440*2 -> 2880
B54: P4 | C54: 3jr | D54: =3*1440 -> 4320

Sheet Février_2019
A1: N° | B1: N°TICKET | C1: PRIORITE | D1: Origine | E1: NOM SERVICES | F1: DATE & HEURE DEBUT | G1: DATE & HEURE FIN | H1: DUREE (mn) | I1: DESCRIPTION | J1: CAUSE DE L'INCIDENT | K1: ACTIONS CORRECTIVES | L1: TMC | M1: Statut | N1: Observation | O1: SLA
A2: 1 | B2: 1902Q03433 | C2: P1 | D2: SSPO | E2: Orange Money add-on / Bank to wallet / Ecobank | F2: 43497.715 | G2: 43497.751 | H2: 51 | I2: Impossible d’effectuer des transactions bancaires via OM | J2: Perte de connexion avec le partenaire | K2: Rétablissement de connexion avec le partenaire | L2: SSPO | M2: Clos | O2: =IF(AND(C2=$B$51,H2<=$D$51),"ISLA",IF((AND(C2=$B$52,H2<=$D$52)),"ISLA",IF((AND(C2=$B$53,H2<=$D$53)),"ISLA","OSLA"))) -> ISLA
A3: 2 | B3: 1902Q20934 | C3: P1 | D3: SSPO | E3: Orange Money add-on / Bank to wallet / Ecobank | F3: 43498.754 | G3: 43498.785 | H3: 45 | I3: Impossible d’effectuer des transactions bancaires via OM | J3: Perte de connexion avec le partenaire | K3: Rétablissement de connexion avec le partenaire | L3: SSPO | M3: Clos | O3: =IF(AND(C3=$B$51,H3<=$D$51),"ISLA",IF((AND(C3=$B$52,H3<=$D$52)),"ISLA",IF((AND(C3=$B$53,H3<=$D$53)),"ISLA","OSLA"))) -> ISLA
A4: 3 | B4: 1902Q32568 | C4: P1 | D4: SSPO | E4: Orange Money add-on / Bank to wallet / Ecobank | F4: 43499.789 | G4: 43499.822 | H4: 48 | I4: Impossible d’effectuer des transactions bancaires via OM | J4: Perte de connexion avec le partenaire | K4: Rétablissement de la connexion avec le partenaire | L4: SSPO | M4: Clos | O4: =IF(AND(C4=$B$51,H4<=$D$51),"ISLA",IF((AND(C4=$B$52,H4<=$D$52)),"ISLA",IF((AND(C4=$B$53,H4<=$D$53)),"ISLA","OSLA"))) -> ISLA
A5: 4 | B5: 1902Q62764 | C5: P1 | D5: SSPO | E5: Orange Money add-on / Bank to wallet / Ecobank | F5: 43500.82 | G5: 43501.015 | H5: 280 | I5: Impossible d’effectuer des transactions bancaires via OM | J5: Perte de connexion avec le partenaire | K5: Rétablissement de la connexion avec le partenaire | L5: SSPO | M5: Clos | O5: =IF(AND(C5=$B$51,H5<=$D$51),"ISLA",IF((AND(C5=$B$52,H5<=$D$52)),"ISLA",IF((AND(C5=$B$53,H5<=$D$53)),"ISLA","OSLA"))) -> OSLA
A6: 5 | B6: 1902Q63911 | C6: P1 | D6: SUPERVISION | E6: Data mobile | F6: 43500.922 | G6: 43501.347 | H6: 612 | I6: Chute de trafic sur la sortie Internet Dalein-Kedougou | J6: coupure de fibre entre Thies MUX3 et Kamberene (Senegal) | K6: Soudure de fibre | L6: SONATEL | M6: Clos | O6: =IF(AND(C6=$B$51,H6<=$D$51),"ISLA",IF((AND(C6=$B$52,H6<=$D$52)),"ISLA",IF((AND(C6=$B$53,H6<=$D$53)),"ISLA","OSLA"))) -> OSLA
A7: 6 | B7: 1902Q69545 | C7: P1 | D7: SSPO | E7: Orange Money add-on / WEB Payments | F7: 43501.25 | G7: 43501.374 | H7: 178 | I7: Impossible d’effectuer des payements en ligne | J7: Due à un ATP de mise à jour de la version du MPayment | K7: Rollback | L7: SSPO | M7: Clos | O7: =IF(AND(C7=$B$51,H7<=$D$51),"ISLA",IF((AND(C7=$B$52,H7<=$D$52)),"ISLA",IF((AND(C7=$B$53,H7<=$D$53)),"ISLA","OSLA"))) -> OSLA
A8: 7 | B8: 1902Q91718 | C8: P1 | D8: SSPO | E8: Orange Money add-on / Bank to wallet / Ecobank | F8: 43501.848 | G8: 43501.878 | H8: 43 | I8: Impossible d’effectuer des transactions bancaires via OM | J8: Perte de connexion avec le partenaire | K8: Rétablissement de la connexion avec le partenaire | L8: SSPO | M8: Clos | O8: =IF(AND(C8=$B$51,H8<=$D$51),"ISLA",IF((AND(C8=$B$52,H8<=$D$52)),"ISLA",IF((AND(C8=$B$53,H8<=$D$53)),"ISLA","OSLA"))) -> ISLA
A9: 8 | B9: 1902R20014 | C9: P1 | D9: SSPO | E9: Orange Money add-on / Bank to wallet / Ecobank | F9: 43502.881 | G9: 43502.907 | H9: 38 | I9: Impossible d’effectuer des transactions bancaires via OM | J9: Perte de connexion avec le partenaire | K9: Rétablissement de la connexion avec le partenaire | L9: SSPO | M9: Clos | O9: =IF(AND(C9=$B$51,H9<=$D$51),"ISLA",IF((AND(C9=$B$52,H9<=$D$52)),"ISLA",IF((AND(C9=$B$53,H9<=$D$53)),"ISLA","OSLA"))) -> ISLA
A10: 9 | B10: 1902R29247 | C10: P1 | D10: SUPERVISION | E10: SMS | F10: 43503.292 | G10: 43504.219 | H10: 1335 | I10: Non réception de notification après des transactions Orange Money | J10: perte de connexion entre le MRE,1 et le SFE,13 sur l'SMSC de Camayenne | K10: Redémarrage des MREs | L10: GNOC | M10: Clos | O10: =IF(AND(C10=$B$51,H10<=$D$51),"ISLA",IF((AND(C10=$B$52,H10<=$D$52)),"ISLA",IF((AND(C10=$B$53,H10<=$D$53)),"ISLA","OSLA"))) -> OSLA
A11: 10 | B11: 1902R48303 | C11: P1 | D11: SSPO | E11: Orange Money add-on / Bank to wallet / Ecobank | F11: 43503.907 | G11: 43503.947 | H11: 57 | I11: Impossible d’effectuer des transactions bancaires via OM | J11: Perte de connexion avec le partenaire | K11: Rétablissement de la connexion avec le partenaire | L11: SSPO | M11: Clos | O11: =IF(AND(C11=$B$51,H11<=$D$51),"ISLA",IF((AND(C11=$B$52,H11<=$D$52)),"ISLA",IF((AND(C11=$B$53,H11<=$D$53)),"ISLA","OSLA"))) -> ISLA
A12: 11 | B12: CSD-21757|P1 | C12: P1 | D12: SUPERVISION | E12: FFC | F12: 43504.075 | G12: 43504.349 | H12: 394 | I12: Impossible d’accéder au service FFC via le code *191# | J12: Verrouillage de session | K12: Suppression du verrou | L12: Support FFC | M12: Clos | O12: =IF(AND(C12=$B$51,H12<=$D$51),"ISLA",IF((AND(C12=$B$52,H12<=$D$52)),"ISLA",IF((AND(C12=$B$53,H12<=$D$53)),"ISLA","OSLA"))) -> OSLA
A13: 12 | B13: 1902R75608 | C13: P1 | D13: SSPO | E13: Orange Money add-on / Bank to wallet / Ecobank | F13: 43504.942 | G13: 43504.968 | H13: 38 | I13: Impossible d’effectuer des transactions bancaires via OM | J13: Perte de connexion avec le partenaire | K13: Rétablissement de la connexion avec le partenaire | L13: SSPO | M13: Clos | O13: =IF(AND(C13=$B$51,H13<=$D$51),"ISLA",IF((AND(C13=$B$52,H13<=$D$52)),"ISLA",IF((AND(C13=$B$53,H13<=$D$53)),"ISLA","OSLA"))) -> ISLA
... A18: 17 | B18: 1902S43275 | C18: P1 | D18: SSPO | E18: Orange Money add-on /Webpayement | F18: 43508.205 | G18: 43508.255 | H18: 72 | I18: Impossible d’effectuer des transactions en ligne | J18: Débordement ATP | K18: Le service est remonté à la fin de l’ATP | L18: SSPO | M18: Clos | O18: =IF(AND(C18=$B$51,H18<=$D$51),"ISLA",IF((AND(C18=$B$52,H18<=$D$52)),"ISLA",IF((AND(C18=$B$53,H18<=$D$53)),"ISLA","OSLA"))) -> ISLA
A19: 18 | B19: 1902S70193 | C19: P1 | D19: SSPO | E19: Orange Money add-on / Bank to wallet / Ecobank | F19: 43509.056 | G19: 43509.095 | H19: =(G19-F19)*1440 -> 56 | I19: Impossible d’effectuer des transactions bancaires via OM | J19: Perte de connexion avec le partenaire | K19: Rétablissement de la connexion avec le partenaire | L19: SSPO | M19: Clos | O19: =IF(AND(C19=$B$51,H19<=$D$51),"ISLA",IF((AND(C19=$B$52,H19<=$D$52)),"ISLA",IF((AND(C19=$B$53,H19<=$D$53)),"ISLA","OSLA"))) -> ISLA
A20: 19 | B20: 1902T08583 | C20: P1 | D20: SSPO | E20: Orange Money add-on / Bank to wallet / UBA | F20: 43510.451 | G20: 43510.494 | H20: 62 | I20: Impossible d’effectuer des transactions bancaires via OM | J20: Dû à un problème de capacité | K20: recréer des instances permettant de disposer de leurs propres ressources | L20: SSPO | M20: Clos | O20: =IF(AND(C20=$B$51,H20<=$D$51),"ISLA",IF((AND(C20=$B$52,H20<=$D$52)),"ISLA",IF((AND(C20=$B$53,H20<=$D$53)),"ISLA","OSLA"))) -> ISLA
A21: 20 | B21: 1902T49473 | C21: P1 | D21: SUPERVISION | E21: Orange Money add-on / Bank to wallet / UBA & ECOBANK | F21: 43512.003 | G21: 43512.757 | H21: =(G21-F21)*1440 -> 1085 | I21: Impossible d’effectuer des transactions bancaires via OM | J21: problème de base de données | K21: Augmentation du nombre maximum de connexions de 500 à 700 et Redémarrage du Cluster de Base de données | L21: SSPO | M21: Clos | O21: =IF(AND(C21=$B$51,H21<=$D$51),"ISLA",IF((AND(C21=$B$52,H21<=$D$52)),"ISLA",IF((AND(C21=$B$53,H21<=$D$53)),"ISLA","OSLA"))) -> OSLA
A22: 21 | B22: 1902T76184 | C22: P1 | D22: SSPO | E22: Orange Money add-on / Canal + | F22: 43514.284 | G22: 43514.299 | H22: 22 | I22: Impossible d’effectuer des Réabonnements Canal+ via OM | J22: Dû à une opération effectuer par le partenaire Canal+ | K22: Le service est remonté à la fin de l’opération | L22: SSPO | M22: Clos | O22: =IF(AND(C22=$B$51,H22<=$D$51),"ISLA",IF((AND(C22=$B$52,H22<=$D$52)),"ISLA",IF((AND(C22=$B$53,H22<=$D$53)),"ISLA","OSLA"))) -> ISLA
A23: 22 | B23: 1902T94777 | C23: P1 | D23: SSPO | E23: Paddock Services | F23: 43514.659 | G23: 43514.667 | H23: 11 | I23: Impossible d’utiliser les fonctionnalités SMS PADDOCK | J23: le trafic SMS était redirigé vers une autre instance de la base de données Redis. | K23: Redirection vers l'instance normale | L23: SSPO | M23: Clos | O23: =IF(AND(C23=$B$51,H23<=$D$51),"ISLA",IF((AND(C23=$B$52,H23<=$D$52)),"ISLA",IF((AND(C23=$B$53,H23<=$D$53)),"ISLA","OSLA"))) -> ISLA
A24: 23 | B24: 1902T99962 | C24: P1 | D24: SSPO | E24: Orange Money add-on / Bank to wallet / Ecobank | F24: 43514.764 | G24: 43514.799 | H24: 50 | I24: Impossible d’effectuer des transactions bancaires via OM | J24: Perte de connexion avec le partenaire | K24: Rétablissement de la connexion avec le partenaire | L24: SSPO | M24: Clos | O24: =IF(AND(C24=$B$51,H24<=$D$51),"ISLA",IF((AND(C24=$B$52,H24<=$D$52)),"ISLA",IF((AND(C24=$B$53,H24<=$D$53)),"ISLA","OSLA"))) -> ISLA
A25: 24 | B25: 1902U28145 | C25: P1 | D25: SSPO | E25: Orange Money add-on / Bank to wallet / Ecobank | F25: 43515.799 | G25: 43515.839 | H25: 57 | I25: Impossible d’effectuer des transactions bancaires via OM | J25: Perte de connexion avec le partenaire | K25: Rétablissement de la connexion avec le partenaire | L25: SSPO | M25: Clos | O25: =IF(AND(C25=$B$51,H25<=$D$51),"ISLA",IF((AND(C25=$B$52,H25<=$D$52)),"ISLA",IF((AND(C25=$B$53,H25<=$D$53)),"ISLA","OSLA"))) -> ISLA
A26: 25 | B26: 1902U37284 | C26: P1 | D26: SSPO | E26: Orange Money add-on / IRT V3 | F26: 43516.229 | G26: 43516.5 | H26: 390 | I26: retard dans le traitement des transactions internationales (Réception d'argent via OM) | J26: Problème de règles de la table IP suite à une augmentation des infrastructures Openswitch | K26: Correction du beug dans la version openvswitch pour minimiser le temps de réponse | L26: SSPO | M26: Clos | O26: =IF(AND(C26=$B$51,H26<=$D$51),"ISLA",IF((AND(C26=$B$52,H26<=$D$52)),"ISLA",IF((AND(C26=$B$53,H26<=$D$53)),"ISLA","OSLA"))) -> OSLA
A27: 26 | B27: 1902U56117 | C27: P1 | D27: SSPO | E27: Orange Money add-on / Bank to wallet / Ecobank | F27: 43516.837 | G27: 43516.868 | H27: 45 | I27: Impossible d’effectuer des transactions bancaires via OM | J27: Perte de connexion avec le partenaire | K27: Rétablissement de la connexion avec le partenaire | L27: SSPO | M27: Clos | O27: =IF(AND(C27=$B$51,H27<=$D$51),"ISLA",IF((AND(C27=$B$52,H27<=$D$52)),"ISLA",IF((AND(C27=$B$53,H27<=$D$53)),"ISLA","OSLA"))) -> ISLA
A28: 27 | B28: 1902U82909 | C28: P1 | D28: SSPO | E28: Orange Money add-on / Bank to wallet / Ecobank | F28: 43517.868 | G28: 43517.917 | H28: 70 | I28: Impossible d’effectuer des transactions bancaires via OM | J28: Perte de connexion avec le partenaire | K28: Rétablissement de la connexion avec le partenaire | L28: SSPO | M28: Clos | O28: =IF(AND(C28=$B$51,H28<=$D$51),"ISLA",IF((AND(C28=$B$52,H28<=$D$52)),"ISLA",IF((AND(C28=$B$53,H28<=$D$53)),"ISLA","OSLA"))) -> ISLA
A29: 28 | B29: 1902V17995 | C29: P1 | D29: SSPO | E29: Orange Money add-on / Bank to wallet / Ecobank | F29: 43518.909 | G29: 43519.483 | H29: 826 | I29: Impossible d’effectuer des transactions bancaires via OM | J29: Perte de connexion avec le partenaire | K29: Rétablissement de la connexion avec le partenaire | L29: SSPO | M29: Clos | O29: =IF(AND(C29=$B$51,H29<=$D$51),"ISLA",IF((AND(C29=$B$52,H29<=$D$52)),"ISLA",IF((AND(C29=$B$53,H29<=$D$53)),"ISLA","OSLA"))) -> OSLA
A30: 29 | B30: 1902V46329 | C30: P1 | D30: SSPO | E30: Orange Money add-on / Bank to wallet / Ecobank | F30: 43520.399 | G30: 43520.433 | H30: 48 | I30: Impossible d’effectuer des transactions bancaires via OM | J30: Perte de connexion avec le partenaire | K30: Rétablissement de la connexion avec le partenaire | L30: SSPO | M30: Clos | O30: =IF(AND(C30=$B$51,H30<=$D$51),"ISLA",IF((AND(C30=$B$52,H30<=$D$52)),"ISLA",IF((AND(C30=$B$53,H30<=$D$53)),"ISLA","OSLA"))) -> ISLA
A31: 30 | B31: 1902V68310 | C31: P1 | D31: SSPO | E31: Orange Money add-on / Bank to wallet / Ecobank | F31: 43521.426 | G31: 43521.487 | H31: 87 | I31: Impossible d’effectuer des transactions bancaires via OM | J31: Perte de connexion avec le partenaire | K31: Rétablissement de la connexion avec le partenaire | L31: SSPO | M31: Clos | O31: =IF(AND(C31=$B$51,H31<=$D$51),"ISLA",IF((AND(C31=$B$52,H31<=$D$52)),"ISLA",IF((AND(C31=$B$53,H31<=$D$53)),"ISLA","OSLA"))) -> ISLA
A32: 31 | B32: 1902W01329 | C32: P1 | D32: SSPO | E32: Orange Money add-on / Bank to wallet / Ecobank | F32: 43522.468 | G32: 43522.499 | H32: 45 | I32: Impossible d’effectuer des transactions bancaires via OM | J32: Perte de connexion avec le partenaire | K32: Rétablissement de la connexion avec le partenaire | L32: SSPO | M32: Clos | O32: =IF(AND(C32=$B$51,H32<=$D$51),"ISLA",IF((AND(C32=$B$52,H32<=$D$52)),"ISLA",IF((AND(C32=$B$53,H32<=$D$53)),"ISLA","OSLA"))) -> ISLA
A33: 32 | B33: 1902W21501 | C33: P1 | D33: SUPERVISION | E33: CMS | F33: 43523.25 | G33: 43524.156 | H33: 1305 | I33: Impossible de souscrire au service CMS (*111#) | J33: activité de travaux planifiée ( Hors délais ) | K33: Le service est rétabli après un roll back effectué par le partenaire IMI | L33: GOS | M33: Clos | O33: =IF(AND(C33=$B$51,H33<=$D$51),"ISLA",IF((AND(C33=$B$52,H33<=$D$52)),"ISLA",IF((AND(C33=$B$53,H33<=$D$53)),"ISLA","OSLA"))) -> OSLA
... A37: 36 | B37: 1902W61594 | C37: P1 | D37: SSPO | E37: Orange Money add-on / Bank to wallet /Ecobank | F37: 43524.535 | G37: 43524.567 | H37: 45 | I37: Impossible d’effectuer des transactions bancaires via OM | J37: Perte de connexion avec le partenaire | K37: Rétablissement de la connexion avec le partenaire | L37: SSPO | M37: Clos | O37: =IF(AND(C37=$B$51,H37<=$D$51),"ISLA",IF((AND(C37=$B$52,H37<=$D$52)),"ISLA",IF((AND(C37=$B$53,H37<=$D$53)),"ISLA","OSLA"))) -> ISLA
B51: P1 | C51: 2h | D51: 120
B52: P2 | C52: 4h | D52: 240
B53: P3 | C53: 2jr | D53: 2880

Sheet Mars_2019
A1: N° | B1: N°TICKET | C1: PRIORITE | D1: Origine | E1: NOM SERVICES | F1: DATE & HEURE DEBUT | G1: DATE & HEURE FIN | H1: DUREE (mn) | I1: DESCRIPTION | J1: CAUSE DE L'INCIDENT | K1: ACTIONS CORRECTIVES | L1: TMC | M1: Statut | N1: Observation | O1: SLA
A2: 1 | B2: 1903W88850 | C2: P1 | D2: SSPO | E2: Orange Money add-on / Bank to wallet / Ecobank | F2: 43525.562 | G2: 43525.599 | H2: =(G2-F2)*1440 -> 53 | I2: Impossible d’effectuer des transactions bancaires via OM | J2: Perte de connexion avec le partenaire | K2: Rétablissement de la connexion avec le partenaire | L2: SSPO | M2: Clos | O2: =IF(AND(C2=$B$60,H2<=$D$60),"ISLA",IF((AND(C2=$B$61,H2<=$D$61)),"ISLA",IF((AND(C2=$B$62,H2<=$D$62)),"ISLA","OSLA"))) -> ISLA
A3: 2 | B3: 1903X11649 | C3: P1 | D3: SSPO | E3: Orange Money add-on / Bank to wallet / Ecobank | F3: 43526.601 | G3: 43526.633 | H3: =(G3-F3)*1440 -> 45 | I3: Impossible d’effectuer des transactions bancaires via OM | J3: Perte de connexion avec le partenaire | K3: Rétablissement de la connexion avec le partenaire | L3: SSPO | M3: Clos | O3: =IF(AND(C3=$B$60,H3<=$D$60),"ISLA",IF((AND(C3=$B$61,H3<=$D$61)),"ISLA",IF((AND(C3=$B$62,H3<=$D$62)),"ISLA","OSLA"))) -> ISLA
A4: 3 | B4: 1903X13906 1903X14387 | C4: P1 | D4: SSPO | E4: E-recharge | F4: 43526.75 | G4: 43526.803 | H4: =(G4-F4)*1440 -> 76 | I4: Echec des transactions E-recharge | J4: surcharge des sessions du firewall de l’IN | K4: Redémarrage du firewall | L4: GNOC | M4: Clos | O4: =IF(AND(C4=$B$60,H4<=$D$60),"ISLA",IF((AND(C4=$B$61,H4<=$D$61)),"ISLA",IF((AND(C4=$B$62,H4<=$D$62)),"ISLA","OSLA"))) -> ISLA
A5: 4 | B5: 1903X16297 | C5: P1 | D5: SUPERVISION | E5: Report Avantage | F5: 43526.847 | G5: 43527.285 | H5: =(G5-F5)*1440 -> 630 | I5: Impossible de recevoir ses avantages à partir du *118*1# | J5: Inconnue | K5: Aucune | L5: ASBD | M5: Clos | O5: =IF(AND(C5=$B$60,H5<=$D$60),"ISLA",IF((AND(C5=$B$61,H5<=$D$61)),"ISLA",IF((AND(C5=$B$62,H5<=$D$62)),"ISLA","OSLA"))) -> OSLA
A6: 5 | B6: 1903X24049 | C6: P1 | D6: SSPO | E6: Orange Money add-on / Bank to wallet / Ecobank | F6: 43527.64 | G6: 43527.666 | H6: 38 | I6: Impossible d’effectuer des transactions bancaires via OM | J6: Perte de connexion avec le partenaire | K6: Rétablissement de la connexion avec le partenaire | L6: SSPO | M6: Clos | O6: =IF(AND(C6=$B$60,H6<=$D$60),"ISLA",IF((AND(C6=$B$61,H6<=$D$61)),"ISLA",IF((AND(C6=$B$62,H6<=$D$62)),"ISLA","OSLA"))) -> ISLA
A7: 6 | B7: 1903X50710 | C7: P1 | D7: SSPO | E7: Orange Money add-on / Bank to wallet / Ecobank | F7: 43528.671 | G7: 43528.703 | H7: 46 | I7: Impossible d’effectuer des transactions bancaires via OM | J7: Perte de connexion avec le partenaire | K7: Rétablissement de la connexion avec le partenaire | L7: SSPO | M7: Clos | O7: =IF(AND(C7=$B$60,H7<=$D$60),"ISLA",IF((AND(C7=$B$61,H7<=$D$61)),"ISLA",IF((AND(C7=$B$62,H7<=$D$62)),"ISLA","OSLA"))) -> ISLA
A8: 7 | B8: 1903X70635 | C8: P1 | D8: SSPO | E8: Orange Cloud @ Google | F8: 43529.465 | G8: 43529.665 | H8: =(G8-F8)*1440 -> 289 | I8: Impossible d’accéder au service Google RCS / Core / Orange Cloud @ Google | J8: ATP realisé le 4 mars sur le serveur ACS Google | K8: RollBack | L8: SSPO | M8: Clos | O8: =IF(AND(C8=$B$60,H8<=$D$60),"ISLA",IF((AND(C8=$B$61,H8<=$D$61)),"ISLA",IF((AND(C8=$B$62,H8<=$D$62)),"ISLA","OSLA"))) -> OSLA
A9: 8 | B9: 1903X81466 | C9: P1 | D9: SSPO | E9: Orange Money add-on / Bank to wallet / Ecobank / OpenWatt | F9: 43529.704 | G9: 43529.738 | H9: =(G9-F9)*1440 -> 48 | I9: Impossible d’effectuer des transactions bancaires via OM | J9: investigation en cours | K9: Rétablissement de la connexion avec le partenaire | L9: SSPO | M9: Clos | O9: =IF(AND(C9=$B$60,H9<=$D$60),"ISLA",IF((AND(C9=$B$61,H9<=$D$61)),"ISLA",IF((AND(C9=$B$62,H9<=$D$62)),"ISLA","OSLA"))) -> ISLA
A10: 9 | B10: 1903X88560 | C10: P1 | D10: SSPO | E10: Myorange | F10: 43530.238 | G10: 43530.279 | H10: 60 | I10: Impossible de consulter son solde où de gérer son compte via l’application Myorange | J10: Débordement ATP | K10: Service remonté à la fin de l'ATP | L10: GOS | M10: Clos | O10: =IF(AND(C10=$B$60,H10<=$D$60),"ISLA",IF((AND(C10=$B$61,H10<=$D$61)),"ISLA",IF((AND(C10=$B$62,H10<=$D$62)),"ISLA","OSLA"))) -> ISLA
A11: 10 | B11: 1903Y08863 | C11: P1 | D11: SSPO | E11: Paddock Services / AAS SMS Gate / SMSW ( impact 100%) | F11: 43530.642 | G11: 43531.108 | H11: =(G11-F11)*1440 -> 671 | I11: Impossible d’utiliser les fonctionnalité SMS | J11: Non identifiée | K11: Aucune | L11: SSPO | M11: Clos | O11: =IF(AND(C11=$B$60,H11<=$D$60),"ISLA",IF((AND(C11=$B$61,H11<=$D$61)),"ISLA",IF((AND(C11=$B$62,H11<=$D$62)),"ISLA","OSLA"))) -> OSLA
A12: 11 | B12: 1903Y13015 | C12: P1 | D12: SSPO | E12: Orange Money add-on / Bank to wallet / Ecobank | F12: 43530.74 | G12: 43530.774 | H12: 50 | I12: Impossible d’effectuer des transactions bancaires via OM | J12: Perte de connexion avec le partenaire | K12: Rétablissement de la connexion avec le partenaire | L12: SSPO | M12: Clos | O12: =IF(AND(C12=$B$60,H12<=$D$60),"ISLA",IF((AND(C12=$B$61,H12<=$D$61)),"ISLA",IF((AND(C12=$B$62,H12<=$D$62)),"ISLA","OSLA"))) -> ISLA
A13: 12 | B13: 1903Y36023 | C13: P1 | D13: SSPO | E13: Orange Money add-on / Bank to wallet / Ecobank | F13: 43531.562 | G13: 43531.609 | H13: 67 | I13: Impossible d’effectuer des transactions bancaires via OM | J13: Perte de connexion avec le partenaire | K13: Rétablissement de la connexion avec le partenaire | L13: SSPO | M13: Clos | O13: =IF(AND(C13=$B$60,H13<=$D$60),"ISLA",IF((AND(C13=$B$61,H13<=$D$61)),"ISLA",IF((AND(C13=$B$62,H13<=$D$62)),"ISLA","OSLA"))) -> ISLA
A14: 13 | B14: 1903Y41775 | C14: P1 | D14: SUPERVISION | E14: CMS,Gameloft,OTAP, Paddock | F14: 43531.696 | G14: 43532.446 | H14: 1080 | I14: Indisponibilité des liens PKIP101 et PSON101 | J14: Coupure de fibre à 12,2499 km dans la zone de WANIDARA | K14: Soudure de la fibre | L14: GNOC | M14: Clos | O14: =IF(AND(C14=$B$60,H14<=$D$60),"ISLA",IF((AND(C14=$B$61,H14<=$D$61)),"ISLA",IF((AND(C14=$B$62,H14<=$D$62)),"ISLA","OSLA"))) -> OSLA
A15: 14 | B15: 1903Y80167 | C15: P1 | D15: SUPERVISION | E15: Data Mobile | F15: 43532.9 | G15: 43532.938 | H15: 54 | I15: Requête sans réponse très élevé sur les DNSs | J15: Taux d’utilisation CPU élevé sur le fire Wall DMZ | K15: Redemarrage du firewall DMZ | L15: ASBD | M15: Clos | O15: =IF(AND(C15=$B$60,H15<=$D$60),"ISLA",IF((AND(C15=$B$61,H15<=$D$61)),"ISLA",IF((AND(C15=$B$62,H15<=$D$62)),"ISLA","OSLA"))) -> ISLA
A16: 15 | B16: 1903Z51379 | C16: P1 | D16: SUPERVISION | E16: Orange Money add-on / Canal + | F16: 43536.403 | G16: 43536.463 | H16: 87 | I16: Impossible d’effectuer des Réabonnements Canal+ via OM | J16: Perte de connexion avec le partenaire Canal+ | K16: Rétablissement de connexion | L16: SSPO | M16: Clos | O16: =IF(AND(C16=$B$60,H16<=$D$60),"ISLA",IF((AND(C16=$B$61,H16<=$D$61)),"ISLA",IF((AND(C16=$B$62,H16<=$D$62)),"ISLA","OSLA"))) -> ISLA
A17: 16 | B17: 1903Z62995 | C17: P1 | D17: SUPERVISION | E17: Orange Money /cross selling | F17: 43536.441 | G17: 43536.528 | H17: 125 | I17: Indisponibilité des services Marchant P2P OM et Distributeur consultation solde OM | J17: BUG du serveur d’application (glassfish) | K17: Redéploiement du serveur d’application (glassfish) et du fichier war sur les deux serveurs webservice (sonfonia & camayenne) | L17: ASBD / DevOps | M17: Clos | O17: =IF(AND(C17=$B$60,H17<=$D$60),"ISLA",IF((AND(C17=$B$61,H17<=$D$61)),"ISLA",IF((AND(C17=$B$62,H17<=$D$62)),"ISLA","OSLA"))) -> OSLA
A18: 17 | B18: 1903Z54585 | C18: P1 | D18: SUPERVISION | E18: Data Mobile | F18: 43536.469 | G18: 43536.493 | H18: 35 | I18: Baisse de trafic Internet | J18: Investigations en cours (Ticket problème 1903Z65085) | K18: Aucune | L18: GNOC | M18: Clos | O18: =IF(AND(C18=$B$60,H18<=$D$60),"ISLA",IF((AND(C18=$B$61,H18<=$D$61)),"ISLA",IF((AND(C18=$B$62,H18<=$D$62)),"ISLA","OSLA"))) -> ISLA
A19: 18 | B19: 1903Z53249 | C19: P1 | D19: SUPERVISION | E19: Orange Money, CMS, transfert data, consultation solde data et report avantage | F19: 43536.517 | G19: 43536.548 | H19: 45 | I19: Dégradation des services Orange Money et quelques VAS (CMS, transfert data, consultation solde data, report avantage) | J19: Investigations en cours (Ticket problème 1903Z62707) | K19: Aucune | L19: ASBD | M19: Clos | O19: =IF(AND(C19=$B$60,H19<=$D$60),"ISLA",IF((AND(C19=$B$61,H19<=$D$61)),"ISLA",IF((AND(C19=$B$62,H19<=$D$62)),"ISLA","OSLA"))) -> ISLA
